{
  "snapshot_meta": {
    "prediction_enabled": true,
    "prediction_score_version": "v5.5_prediction_quality_v2",
    "prediction_reference_timestamp": "2026-06-29 16:31:25",
    "snapshot_date": "2026-06-29",
    "prediction_input_fields": [
      "Instrument",
      "Preferred_Side",
      "Setup_Archetype",
      "Decision_Book",
      "W1_Bias",
      "D1_Bias",
      "Alignment",
      "Price_Side_vs_D1_Range",
      "Liquidity_Condition",
      "Sweep_Quality",
      "Liquidity_Side",
      "Liquidity_Tier",
      "Liquidity_Reference_Type",
      "Rejection_Quality",
      "Follow_Through",
      "Both_Sides_Taken_Recently",
      "Displacement_Quality",
      "MSS_BOS",
      "Pivot_Regime",
      "Pivot_Zone_Fit",
      "Pivot_Conflict",
      "Pivot_Stretch",
      "Data_Quality",
      "Confidence_Score",
      "Confidence_Band",
      "Technical_Quality_Score_10",
      "Execution_Realism_Score_10",
      "Calibrated_Confidence_Score_10",
      "Context_Quality_Score_10",
      "Trigger_Quality_Score_10",
      "Conflict_Penalty_Score_10",
      "Balance_Score_10",
      "Opportunity_Score_10",
      "Kill_Switch_Score_10",
      "False_Positive_Risk_Score_10",
      "Archetype_Tax_Score_10",
      "Survivability_Score_10",
      "Asymmetry_Score_10",
      "Calibration_Utility_Score_10",
      "Comparative_Edge_Score_10",
      "Comparator_Floor_Score_10",
      "Dominance_Score_10",
      "Selection_Score",
      "Final_Rank_Score",
      "Admission_Class",
      "Override_Reason",
      "Shortlist_Eligibility",
      "Admission_Binding_Status",
      "Selection_Lane",
      "Primary_Shortlist_Flag",
      "Shadow_Watchlist_Flag",
      "Gate_Passed",
      "Gate_Fail_Reasons",
      "Veto_Flag",
      "Veto_Reasons",
      "Current_Price",
      "Best_Entry",
      "SL",
      "TP1",
      "TP2",
      "RR_TP1",
      "RR_TP2",
      "Entry_Distance_ATR"
    ],
    "prediction_forbidden_fields": [
      "Verifier_Triggered",
      "Verifier_TP1_Hit",
      "Verifier_TP2_Hit",
      "Verifier_SL_Hit",
      "Verifier_First_Event",
      "Verifier_Outcome_Label",
      "Verifier_MFE",
      "Verifier_MAE",
      "Verifier_R_Multiple",
      "Verifier_Weighted_Return_R",
      "Verifier48_Triggered",
      "Verifier48_TP1_Hit",
      "Verifier48_TP2_Hit",
      "Verifier48_SL_Hit",
      "Verifier48_First_Event",
      "Verifier48_Outcome_Label",
      "Verifier48_MFE",
      "Verifier48_MAE",
      "Verifier48_R_Multiple",
      "Verifier48_Weighted_Return_R",
      "Verifier72_Triggered",
      "Verifier72_TP1_Hit",
      "Verifier72_TP2_Hit",
      "Verifier72_SL_Hit",
      "Verifier72_First_Event",
      "Verifier72_Outcome_Label",
      "Verifier72_MFE",
      "Verifier72_MAE",
      "Verifier72_R_Multiple",
      "Verifier72_Weighted_Return_R"
    ],
    "prediction_top_n": 8
  },
  "predictions": [
    {
      "Snapshot_Date": "2026-06-29",
      "Prediction_Reference_Timestamp": "2026-06-29 16:31:25",
      "Market_Reference_Timestamp": "1970-01-01 00:00:00.000000698",
      "Instrument": "EURGBP",
      "status": "OK",
      "Universe_Layer": "Layer 1 — Core execution universe",
      "Cluster_Tags": "EUR relative-value cluster, EUR weakness, HTF aligned",
      "W1_Bias": "BEARISH",
      "D1_Bias": "BEARISH",
      "Price_Side_vs_D1_Range": "discount",
      "Alignment": "aligned",
      "Liquidity_Condition": "external liquidity taken",
      "Sweep_Quality": "sweep + close back inside range",
      "Liquidity_Side": "sell-side",
      "Liquidity_Tier": "minor",
      "Liquidity_Reference_Type": "swing low",
      "Rejection_Quality": "moderate rejection",
      "Follow_Through": "limited follow-through",
      "Both_Sides_Taken_Recently": true,
      "Displacement_Quality": "moderate displacement",
      "MSS_BOS": "partial shift",
      "Array_Quality": "good",
      "Session_Quality": "acceptable but not ideal",
      "RS_RW_Alignment": "no clear alignment",
      "SMT_Hint": "none",
      "Pivot_Regime": "daily: bearish below pivot | weekly: bearish below pivot",
      "Pivot_Zone_Fit": "price in neutral zone",
      "Pivot_Confluence": "mixed confluence",
      "Pivot_Conflict": "no meaningful pivot conflict",
      "Pivot_Stretch": "not stretched",
      "Technical_Score_0_4": 1.55,
      "Legacy_Confidence_Score": 0.75,
      "Legacy_Confidence_Band": "medium",
      "Confidence_Score": 0.504,
      "Confidence_Band": "low",
      "Technical_Quality_Score_10": 7.4,
      "Execution_Realism_Score_10": 10.0,
      "Calibrated_Confidence_Score_10": 5.04,
      "Selection_Score": -6.4869,
      "Final_Rank_Score": -6.5309,
      "Data_Quality": "good",
      "Entry_Label": "B-tier reactive setup",
      "Preferred_Side": "SHORT",
      "Best_Entry": 0.862,
      "Structural_Entry": 0.8665,
      "Calibration_Entry": 0.862,
      "Entry_Distance_ATR": 0.015,
      "SL": 0.8627,
      "TP1": 0.8612,
      "TP2": 0.8606,
      "Current_Price": 0.862,
      "ATR_H1": 0.0007,
      "RR_TP1": 1.1429,
      "RR_TP2": 2.0,
      "Execution_Line": "Sell-limit: 0.862 | SL: 0.8627 | TP1: 0.8612 | TP2: 0.8606 | RR1: 1.1429 | RR2: 2.0",
      "Execution_Source": "zone",
      "Setup_Archetype": "continuation",
      "Decision_Book": "A-book",
      "Live_Gate_Passed": true,
      "Calibration_Gate_Passed": true,
      "Gate_Passed": true,
      "Gate_Fail_Reasons": "",
      "Decision_Setup_Quality": 3.4,
      "Decision_Execution_Quality": 3.8,
      "Decision_Portfolio_Fit": 0.0,
      "Decision_Rank_Score": -9.2984,
      "Base_Ranking_Score": -9.2384,
      "Overlap_Penalty": 0.0,
      "Ranking_Score": -6.5309,
      "Calibration_Soft_Candidate": false,
      "Calibration_Candidate_Bucket": "hard_pass",
      "Soft_Candidate": false,
      "Soft_Fail_Adjustment": 0.0,
      "Continuation_Subquality": 0.11,
      "Continuation_Elite_Eligible": true,
      "Context_Quality_Score_10": 7.2,
      "Trigger_Quality_Score_10": 6.0,
      "Conflict_Penalty_Score_10": 0.0,
      "Opportunity_Score_10": 5.0,
      "Balance_Score_10": 6.4,
      "Kill_Switch_Score_10": 0.0,
      "False_Positive_Risk_Score_10": 5.1,
      "Archetype_Tax_Score_10": 3.8,
      "Survivability_Score_10": 6.77,
      "Asymmetry_Score_10": 7.8,
      "Calibration_Utility_Score_10": 4.4,
      "Radical_Confidence_Score_10": 5.04,
      "Admission_Class": "blocked",
      "Override_Reason": "gatepass_primary_block",
      "Shortlist_Eligibility": "blocked",
      "Admission_Binding_Status": "blocked_gatepass",
      "Selection_Lane": "blocked_gatepass",
      "Leakage_Penalty_Score": 3.0,
      "Veto_Flag": false,
      "Veto_Reasons": "",
      "Selector_Profile": "v5.5_prediction_ready_selector",
      "Fragility_Reason": "",
      "Idea_Family": "continuation|no_theme|SHORT|nonusd|normal",
      "Survivor_Score": 4.0055,
      "Tournament_Pool": "radical_board",
      "Tournament_Pool_Display": "Radical board",
      "Tournament_Pool_Eligible": "radical_board",
      "Local_Pool_Score": -9.2984,
      "Tournament_Finalist_Flag": false,
      "Shortlist_Slot_Name": "",
      "Shortlist_Slot_Order": NaN,
      "Crowding_Block_Reason": "",
      "Selection_Passed_Over_For_Diversity": "",
      "Comparative_Edge_Score_10": 5.5,
      "Comparator_Floor_Score_10": 2.0,
      "Dominance_Score_10": 4.45,
      "Primary_Shortlist_Flag": false,
      "Primary_Override_Flag": false,
      "Shadow_Watchlist_Flag": false,
      "Shadow_Watchlist_Reason": "",
      "Shadow_Watchlist_Order": NaN,
      "In_Top_Shortlist": false,
      "Setup_Quality_Grade_10": 4.92,
      "Setup_Quality_Grade_100": 49.2,
      "Setup_Quality_Band": "C",
      "Prediction_Top_Strengths": "execution 10.0, asymmetry 7.8, context 7.2",
      "Prediction_Main_Risks": "gate_pressure 7.7, false_positive_risk 5.1",
      "Prediction_Breakdown": "SHORT continuation; strengths: execution 10.0, asymmetry 7.8, context 7.2; risks: gate_pressure 7.7, false_positive_risk 5.1; admission: blocked / blocked_gatepass",
      "Prediction_Score_Version": "v5.5_prediction_quality_v2",
      "Prediction_Uses_Only_Contemporaneous_Inputs": true,
      "Prediction_Forbidden_Field_Leak": false,
      "Prediction_Input_Fingerprint": "5c173caad7fd9bb9",
      "Prediction_Integrity_Status": "clean_contemporaneous_only",
      "Prediction_Rank": 1
    },
    {
      "Snapshot_Date": "2026-06-29",
      "Prediction_Reference_Timestamp": "2026-06-29 16:31:25",
      "Market_Reference_Timestamp": "1970-01-01 00:00:00.000000698",
      "Instrument": "CADJPY",
      "status": "OK",
      "Universe_Layer": "Layer 1 — Core execution universe",
      "Cluster_Tags": "HTF aligned, JPY cluster, commodity bloc, risk-off short",
      "W1_Bias": "BEARISH",
      "D1_Bias": "BEARISH",
      "Price_Side_vs_D1_Range": "premium",
      "Alignment": "aligned",
      "Liquidity_Condition": "external liquidity taken",
      "Sweep_Quality": "sweep + close back inside range",
      "Liquidity_Side": "sell-side",
      "Liquidity_Tier": "major",
      "Liquidity_Reference_Type": "swing low",
      "Rejection_Quality": "strong rejection",
      "Follow_Through": "limited follow-through",
      "Both_Sides_Taken_Recently": true,
      "Displacement_Quality": "weak / no displacement",
      "MSS_BOS": "partial shift",
      "Array_Quality": "good",
      "Session_Quality": "acceptable but not ideal",
      "RS_RW_Alignment": "mixed",
      "SMT_Hint": "none",
      "Pivot_Regime": "daily: bearish below pivot | weekly: bullish above pivot",
      "Pivot_Zone_Fit": "price in sell zone",
      "Pivot_Confluence": "daily only",
      "Pivot_Conflict": "mild pivot conflict",
      "Pivot_Stretch": "not stretched",
      "Technical_Score_0_4": 1.8,
      "Legacy_Confidence_Score": 0.85,
      "Legacy_Confidence_Band": "medium",
      "Confidence_Score": 0.54,
      "Confidence_Band": "low",
      "Technical_Quality_Score_10": 6.0,
      "Execution_Realism_Score_10": 10.0,
      "Calibrated_Confidence_Score_10": 5.4,
      "Selection_Score": -5.7519,
      "Final_Rank_Score": -5.7692,
      "Data_Quality": "good",
      "Entry_Label": "B-tier reactive setup",
      "Preferred_Side": "SHORT",
      "Best_Entry": 113.965,
      "Structural_Entry": 114.037,
      "Calibration_Entry": 113.965,
      "Entry_Distance_ATR": 0.068,
      "SL": 114.054,
      "TP1": 113.857,
      "TP2": 113.773,
      "Current_Price": 113.946,
      "ATR_H1": 0.08,
      "RR_TP1": 1.2135,
      "RR_TP2": 2.1573,
      "Execution_Line": "Sell-limit: 113.965 | SL: 114.054 | TP1: 113.857 | TP2: 113.773 | RR1: 1.2135 | RR2: 2.1573",
      "Execution_Source": "zone",
      "Setup_Archetype": "continuation",
      "Decision_Book": "B-book",
      "Live_Gate_Passed": false,
      "Calibration_Gate_Passed": true,
      "Gate_Passed": true,
      "Gate_Fail_Reasons": "weak_impulse",
      "Decision_Setup_Quality": 2.45,
      "Decision_Execution_Quality": 3.8,
      "Decision_Portfolio_Fit": 0.0,
      "Decision_Rank_Score": -9.7863,
      "Base_Ranking_Score": -9.7263,
      "Overlap_Penalty": 0.0,
      "Ranking_Score": -5.7692,
      "Calibration_Soft_Candidate": true,
      "Calibration_Candidate_Bucket": "hard_pass",
      "Soft_Candidate": true,
      "Soft_Fail_Adjustment": -0.2,
      "Continuation_Subquality": 0.31,
      "Continuation_Elite_Eligible": true,
      "Context_Quality_Score_10": 6.9,
      "Trigger_Quality_Score_10": 4.95,
      "Conflict_Penalty_Score_10": 1.1,
      "Opportunity_Score_10": 6.8,
      "Balance_Score_10": 5.07,
      "Kill_Switch_Score_10": 2.8,
      "False_Positive_Risk_Score_10": 4.5,
      "Archetype_Tax_Score_10": 3.0,
      "Survivability_Score_10": 5.62,
      "Asymmetry_Score_10": 8.3,
      "Calibration_Utility_Score_10": 6.9,
      "Radical_Confidence_Score_10": 5.4,
      "Admission_Class": "blocked",
      "Override_Reason": "gatepass_primary_block",
      "Shortlist_Eligibility": "blocked",
      "Admission_Binding_Status": "blocked_gatepass",
      "Selection_Lane": "blocked_gatepass",
      "Leakage_Penalty_Score": 3.0,
      "Veto_Flag": false,
      "Veto_Reasons": "",
      "Selector_Profile": "v5.5_prediction_ready_selector",
      "Fragility_Reason": "bbook_plus_fail",
      "Idea_Family": "continuation|no_theme|SHORT|nonusd|strong",
      "Survivor_Score": 3.908,
      "Tournament_Pool": "radical_board",
      "Tournament_Pool_Display": "Radical board",
      "Tournament_Pool_Eligible": "radical_board",
      "Local_Pool_Score": -9.7863,
      "Tournament_Finalist_Flag": false,
      "Shortlist_Slot_Name": "",
      "Shortlist_Slot_Order": NaN,
      "Crowding_Block_Reason": "",
      "Selection_Passed_Over_For_Diversity": "",
      "Comparative_Edge_Score_10": 7.27,
      "Comparator_Floor_Score_10": 5.33,
      "Dominance_Score_10": 6.69,
      "Primary_Shortlist_Flag": false,
      "Primary_Override_Flag": false,
      "Shadow_Watchlist_Flag": false,
      "Shadow_Watchlist_Reason": "",
      "Shadow_Watchlist_Order": NaN,
      "In_Top_Shortlist": false,
      "Setup_Quality_Grade_10": 4.41,
      "Setup_Quality_Grade_100": 44.1,
      "Setup_Quality_Band": "C",
      "Prediction_Top_Strengths": "execution 10.0, asymmetry 8.3, utility 6.9",
      "Prediction_Main_Risks": "gate_pressure 11.8, false_positive_risk 4.5",
      "Prediction_Breakdown": "SHORT continuation; strengths: execution 10.0, asymmetry 8.3, utility 6.9; risks: gate_pressure 11.8, false_positive_risk 4.5; admission: blocked / blocked_gatepass",
      "Prediction_Score_Version": "v5.5_prediction_quality_v2",
      "Prediction_Uses_Only_Contemporaneous_Inputs": true,
      "Prediction_Forbidden_Field_Leak": false,
      "Prediction_Input_Fingerprint": "13d9bba65061c933",
      "Prediction_Integrity_Status": "clean_contemporaneous_only",
      "Prediction_Rank": 2
    },
    {
      "Snapshot_Date": "2026-06-29",
      "Prediction_Reference_Timestamp": "2026-06-29 16:31:25",
      "Market_Reference_Timestamp": "1970-01-01 00:00:00.000000698",
      "Instrument": "AUDUSD",
      "status": "OK",
      "Universe_Layer": "Layer 1 — Core execution universe",
      "Cluster_Tags": "HTF aligned, USD basket, USD weakness, commodity bloc",
      "W1_Bias": "BEARISH",
      "D1_Bias": "BEARISH",
      "Price_Side_vs_D1_Range": "discount",
      "Alignment": "aligned",
      "Liquidity_Condition": "external liquidity taken",
      "Sweep_Quality": "sweep + close back inside range",
      "Liquidity_Side": "sell-side",
      "Liquidity_Tier": "major",
      "Liquidity_Reference_Type": "swing low",
      "Rejection_Quality": "strong rejection",
      "Follow_Through": "clean follow-through",
      "Both_Sides_Taken_Recently": true,
      "Displacement_Quality": "moderate displacement",
      "MSS_BOS": "partial shift",
      "Array_Quality": "weak",
      "Session_Quality": "acceptable but not ideal",
      "RS_RW_Alignment": "clear alignment",
      "SMT_Hint": "none",
      "Pivot_Regime": "daily: bearish below pivot | weekly: bearish below pivot",
      "Pivot_Zone_Fit": "price in neutral zone",
      "Pivot_Confluence": "mixed confluence",
      "Pivot_Conflict": "no meaningful pivot conflict",
      "Pivot_Stretch": "not stretched",
      "Technical_Score_0_4": 2.35,
      "Legacy_Confidence_Score": 0.85,
      "Legacy_Confidence_Band": "medium",
      "Confidence_Score": 0.519,
      "Confidence_Band": "low",
      "Technical_Quality_Score_10": 8.65,
      "Execution_Realism_Score_10": 10.0,
      "Calibrated_Confidence_Score_10": 5.19,
      "Selection_Score": -7.121,
      "Final_Rank_Score": -7.149,
      "Data_Quality": "good",
      "Entry_Label": "D-tier avoid",
      "Preferred_Side": "SHORT",
      "Best_Entry": 0.6886,
      "Structural_Entry": 0.6887,
      "Calibration_Entry": 0.6886,
      "Entry_Distance_ATR": 0.0,
      "SL": 0.6896,
      "TP1": 0.6874,
      "TP2": 0.6865,
      "Current_Price": 0.6884,
      "ATR_H1": 0.0007,
      "RR_TP1": 1.2,
      "RR_TP2": 2.1,
      "Execution_Line": "Sell-limit: 0.6886 | SL: 0.6896 | TP1: 0.6874 | TP2: 0.6865 | RR1: 1.2 | RR2: 2.1",
      "Execution_Source": "fallback",
      "Setup_Archetype": "relative_value_continuation",
      "Decision_Book": "B-book",
      "Live_Gate_Passed": false,
      "Calibration_Gate_Passed": true,
      "Gate_Passed": true,
      "Gate_Fail_Reasons": "d_tier",
      "Decision_Setup_Quality": 3.25,
      "Decision_Execution_Quality": 3.8,
      "Decision_Portfolio_Fit": 0.0,
      "Decision_Rank_Score": -10.6701,
      "Base_Ranking_Score": -10.6101,
      "Overlap_Penalty": 0.0,
      "Ranking_Score": -7.149,
      "Calibration_Soft_Candidate": true,
      "Calibration_Candidate_Bucket": "hard_pass",
      "Soft_Candidate": true,
      "Soft_Fail_Adjustment": -0.25,
      "Continuation_Subquality": 0.0,
      "Continuation_Elite_Eligible": false,
      "Context_Quality_Score_10": 7.85,
      "Trigger_Quality_Score_10": 6.5,
      "Conflict_Penalty_Score_10": 1.6,
      "Opportunity_Score_10": 5.75,
      "Balance_Score_10": 6.85,
      "Kill_Switch_Score_10": 3.9,
      "False_Positive_Risk_Score_10": 5.4,
      "Archetype_Tax_Score_10": 7.2,
      "Survivability_Score_10": 6.65,
      "Asymmetry_Score_10": 8.9,
      "Calibration_Utility_Score_10": 5.9,
      "Radical_Confidence_Score_10": 5.19,
      "Admission_Class": "blocked",
      "Override_Reason": "relval_hard_block",
      "Shortlist_Eligibility": "blocked",
      "Admission_Binding_Status": "blocked_relval",
      "Selection_Lane": "blocked_relval",
      "Leakage_Penalty_Score": 3.0,
      "Veto_Flag": false,
      "Veto_Reasons": "",
      "Selector_Profile": "v5.5_prediction_ready_selector",
      "Fragility_Reason": "bbook_plus_fail",
      "Idea_Family": "relval|no_theme|SHORT|nonusd",
      "Survivor_Score": 4.1525,
      "Tournament_Pool": "radical_board",
      "Tournament_Pool_Display": "Radical board",
      "Tournament_Pool_Eligible": "radical_board",
      "Local_Pool_Score": -10.6701,
      "Tournament_Finalist_Flag": false,
      "Shortlist_Slot_Name": "",
      "Shortlist_Slot_Order": NaN,
      "Crowding_Block_Reason": "",
      "Selection_Passed_Over_For_Diversity": "",
      "Comparative_Edge_Score_10": 6.57,
      "Comparator_Floor_Score_10": 4.0,
      "Dominance_Score_10": 5.8,
      "Primary_Shortlist_Flag": false,
      "Primary_Override_Flag": false,
      "Shadow_Watchlist_Flag": false,
      "Shadow_Watchlist_Reason": "",
      "Shadow_Watchlist_Order": NaN,
      "In_Top_Shortlist": false,
      "Setup_Quality_Grade_10": 4.16,
      "Setup_Quality_Grade_100": 41.6,
      "Setup_Quality_Band": "C",
      "Prediction_Top_Strengths": "execution 10.0, asymmetry 8.9, context 7.8",
      "Prediction_Main_Risks": "gate_pressure 11.8, archetype_tax 7.2",
      "Prediction_Breakdown": "SHORT relative_value_continuation; strengths: execution 10.0, asymmetry 8.9, context 7.8; risks: gate_pressure 11.8, archetype_tax 7.2; admission: blocked / blocked_relval",
      "Prediction_Score_Version": "v5.5_prediction_quality_v2",
      "Prediction_Uses_Only_Contemporaneous_Inputs": true,
      "Prediction_Forbidden_Field_Leak": false,
      "Prediction_Input_Fingerprint": "d66597b69cfde597",
      "Prediction_Integrity_Status": "clean_contemporaneous_only",
      "Prediction_Rank": 3
    },
    {
      "Snapshot_Date": "2026-06-29",
      "Prediction_Reference_Timestamp": "2026-06-29 16:31:25",
      "Market_Reference_Timestamp": "1970-01-01 00:00:00.000000698",
      "Instrument": "GBPUSD",
      "status": "OK",
      "Universe_Layer": "Layer 1 — Core execution universe",
      "Cluster_Tags": "HTF conflict, USD basket",
      "W1_Bias": "BEARISH",
      "D1_Bias": "BULLISH",
      "Price_Side_vs_D1_Range": "premium",
      "Alignment": "full conflict",
      "Liquidity_Condition": "external liquidity taken",
      "Sweep_Quality": "clean sweep only",
      "Liquidity_Side": "buy-side",
      "Liquidity_Tier": "minor",
      "Liquidity_Reference_Type": "swing high",
      "Rejection_Quality": "moderate rejection",
      "Follow_Through": "limited follow-through",
      "Both_Sides_Taken_Recently": true,
      "Displacement_Quality": "weak / no displacement",
      "MSS_BOS": "partial shift",
      "Array_Quality": "good",
      "Session_Quality": "acceptable but not ideal",
      "RS_RW_Alignment": "mixed",
      "SMT_Hint": "none",
      "Pivot_Regime": "daily: bullish above pivot | weekly: bullish above pivot",
      "Pivot_Zone_Fit": "price in neutral zone",
      "Pivot_Confluence": "mixed confluence",
      "Pivot_Conflict": "no meaningful pivot conflict",
      "Pivot_Stretch": "moderately stretched",
      "Technical_Score_0_4": 0.7,
      "Legacy_Confidence_Score": 0.75,
      "Legacy_Confidence_Band": "medium",
      "Confidence_Score": 0.377,
      "Confidence_Band": "low",
      "Technical_Quality_Score_10": 3.65,
      "Execution_Realism_Score_10": 10.0,
      "Calibrated_Confidence_Score_10": 3.77,
      "Selection_Score": 1.5173,
      "Final_Rank_Score": 1.4733,
      "Data_Quality": "good",
      "Entry_Label": "B-tier reactive setup",
      "Preferred_Side": "LONG",
      "Best_Entry": 1.3254,
      "Structural_Entry": 1.3173,
      "Calibration_Entry": 1.3254,
      "Entry_Distance_ATR": 0.032,
      "SL": 1.3243,
      "TP1": 1.3266,
      "TP2": 1.3276,
      "Current_Price": 1.3251,
      "ATR_H1": 0.0013,
      "RR_TP1": 1.0909,
      "RR_TP2": 2.0,
      "Execution_Line": "Buy-limit: 1.3254 | SL: 1.3243 | TP1: 1.3266 | TP2: 1.3276 | RR1: 1.0909 | RR2: 2.0",
      "Execution_Source": "zone",
      "Setup_Archetype": "continuation",
      "Decision_Book": "Rejected",
      "Live_Gate_Passed": false,
      "Calibration_Gate_Passed": false,
      "Gate_Passed": false,
      "Gate_Fail_Reasons": "weak_impulse",
      "Decision_Setup_Quality": 0.65,
      "Decision_Execution_Quality": 3.8,
      "Decision_Portfolio_Fit": 0.0,
      "Decision_Rank_Score": -1.1123,
      "Base_Ranking_Score": -1.0523,
      "Overlap_Penalty": 0.0,
      "Ranking_Score": 1.4733,
      "Calibration_Soft_Candidate": false,
      "Calibration_Candidate_Bucket": "hard_reject",
      "Soft_Candidate": false,
      "Soft_Fail_Adjustment": 0.0,
      "Continuation_Subquality": 0.07,
      "Continuation_Elite_Eligible": false,
      "Context_Quality_Score_10": 4.8,
      "Trigger_Quality_Score_10": 4.45,
      "Conflict_Penalty_Score_10": 4.1,
      "Opportunity_Score_10": 5.9,
      "Balance_Score_10": 4.4,
      "Kill_Switch_Score_10": 5.0,
      "False_Positive_Risk_Score_10": 2.9,
      "Archetype_Tax_Score_10": 3.8,
      "Survivability_Score_10": 3.3,
      "Asymmetry_Score_10": 7.8,
      "Calibration_Utility_Score_10": 7.35,
      "Radical_Confidence_Score_10": 3.77,
      "Admission_Class": "eligible",
      "Override_Reason": "",
      "Shortlist_Eligibility": "primary",
      "Admission_Binding_Status": "primary_eligible",
      "Selection_Lane": "primary_not_selected",
      "Leakage_Penalty_Score": 0.0,
      "Veto_Flag": false,
      "Veto_Reasons": "",
      "Selector_Profile": "v5.5_prediction_ready_selector",
      "Fragility_Reason": "hard_reject",
      "Idea_Family": "continuation|no_theme|LONG|nonusd|normal",
      "Survivor_Score": 2.89,
      "Tournament_Pool": "radical_board",
      "Tournament_Pool_Display": "Radical board",
      "Tournament_Pool_Eligible": "radical_board",
      "Local_Pool_Score": -1.1123,
      "Tournament_Finalist_Flag": false,
      "Shortlist_Slot_Name": "",
      "Shortlist_Slot_Order": NaN,
      "Crowding_Block_Reason": "",
      "Selection_Passed_Over_For_Diversity": "",
      "Comparative_Edge_Score_10": 5.1,
      "Comparator_Floor_Score_10": 2.0,
      "Dominance_Score_10": 4.17,
      "Primary_Shortlist_Flag": false,
      "Primary_Override_Flag": false,
      "Shadow_Watchlist_Flag": false,
      "Shadow_Watchlist_Reason": "",
      "Shadow_Watchlist_Order": NaN,
      "In_Top_Shortlist": false,
      "Setup_Quality_Grade_10": 3.92,
      "Setup_Quality_Grade_100": 39.2,
      "Setup_Quality_Band": "D",
      "Prediction_Top_Strengths": "execution 10.0, asymmetry 7.8, utility 7.3",
      "Prediction_Main_Risks": "kill_switch 5.0, conflict 4.1",
      "Prediction_Breakdown": "LONG continuation; strengths: execution 10.0, asymmetry 7.8, utility 7.3; risks: kill_switch 5.0, conflict 4.1; admission: eligible / primary_not_selected",
      "Prediction_Score_Version": "v5.5_prediction_quality_v2",
      "Prediction_Uses_Only_Contemporaneous_Inputs": true,
      "Prediction_Forbidden_Field_Leak": false,
      "Prediction_Input_Fingerprint": "2ade66cc0127b533",
      "Prediction_Integrity_Status": "clean_contemporaneous_only",
      "Prediction_Rank": 4
    },
    {
      "Snapshot_Date": "2026-06-29",
      "Prediction_Reference_Timestamp": "2026-06-29 16:31:25",
      "Market_Reference_Timestamp": "1970-01-01 00:00:00.000000698",
      "Instrument": "USDCAD",
      "status": "OK",
      "Universe_Layer": "Layer 1 — Core execution universe",
      "Cluster_Tags": "HTF aligned, USD basket, USD strength, commodity bloc",
      "W1_Bias": "BULLISH",
      "D1_Bias": "BULLISH",
      "Price_Side_vs_D1_Range": "premium",
      "Alignment": "aligned",
      "Liquidity_Condition": "external liquidity taken",
      "Sweep_Quality": "clean sweep only",
      "Liquidity_Side": "buy-side",
      "Liquidity_Tier": "major",
      "Liquidity_Reference_Type": "swing high",
      "Rejection_Quality": "moderate rejection",
      "Follow_Through": "limited follow-through",
      "Both_Sides_Taken_Recently": true,
      "Displacement_Quality": "weak / no displacement",
      "MSS_BOS": "partial shift",
      "Array_Quality": "weak",
      "Session_Quality": "acceptable but not ideal",
      "RS_RW_Alignment": "mixed",
      "SMT_Hint": "none",
      "Pivot_Regime": "daily: bullish above pivot | weekly: bullish above pivot",
      "Pivot_Zone_Fit": "price in neutral zone",
      "Pivot_Confluence": "mixed confluence",
      "Pivot_Conflict": "no meaningful pivot conflict",
      "Pivot_Stretch": "not stretched",
      "Technical_Score_0_4": 0.9,
      "Legacy_Confidence_Score": 0.75,
      "Legacy_Confidence_Band": "medium",
      "Confidence_Score": 0.386,
      "Confidence_Band": "low",
      "Technical_Quality_Score_10": 6.3,
      "Execution_Realism_Score_10": 9.6,
      "Calibrated_Confidence_Score_10": 3.86,
      "Selection_Score": -7.8057,
      "Final_Rank_Score": -7.8337,
      "Data_Quality": "good",
      "Entry_Label": "D-tier avoid",
      "Preferred_Side": "LONG",
      "Best_Entry": 1.4208,
      "Structural_Entry": 1.4207,
      "Calibration_Entry": 1.4208,
      "Entry_Distance_ATR": 0.029,
      "SL": 1.419,
      "TP1": 1.4229,
      "TP2": 1.4246,
      "Current_Price": 1.4212,
      "ATR_H1": 0.001,
      "RR_TP1": 1.1667,
      "RR_TP2": 2.1111,
      "Execution_Line": "Buy-limit: 1.4208 | SL: 1.419 | TP1: 1.4229 | TP2: 1.4246 | RR1: 1.1667 | RR2: 2.1111",
      "Execution_Source": "fallback",
      "Setup_Archetype": "continuation",
      "Decision_Book": "B-book",
      "Live_Gate_Passed": false,
      "Calibration_Gate_Passed": true,
      "Gate_Passed": true,
      "Gate_Fail_Reasons": "d_tier, weak_impulse",
      "Decision_Setup_Quality": 2.05,
      "Decision_Execution_Quality": 3.3,
      "Decision_Portfolio_Fit": 0.0,
      "Decision_Rank_Score": -11.1728,
      "Base_Ranking_Score": -11.1128,
      "Overlap_Penalty": 0.0,
      "Ranking_Score": -7.8337,
      "Calibration_Soft_Candidate": true,
      "Calibration_Candidate_Bucket": "hard_pass",
      "Soft_Candidate": true,
      "Soft_Fail_Adjustment": -0.45,
      "Continuation_Subquality": 0.27,
      "Continuation_Elite_Eligible": true,
      "Context_Quality_Score_10": 7.5,
      "Trigger_Quality_Score_10": 4.45,
      "Conflict_Penalty_Score_10": 2.7,
      "Opportunity_Score_10": 6.8,
      "Balance_Score_10": 4.76,
      "Kill_Switch_Score_10": 6.7,
      "False_Positive_Risk_Score_10": 3.8,
      "Archetype_Tax_Score_10": 3.0,
      "Survivability_Score_10": 4.22,
      "Asymmetry_Score_10": 7.8,
      "Calibration_Utility_Score_10": 6.9,
      "Radical_Confidence_Score_10": 3.86,
      "Admission_Class": "blocked",
      "Override_Reason": "gatepass_primary_block",
      "Shortlist_Eligibility": "blocked",
      "Admission_Binding_Status": "blocked_gatepass",
      "Selection_Lane": "blocked_gatepass",
      "Leakage_Penalty_Score": 3.0,
      "Veto_Flag": false,
      "Veto_Reasons": "",
      "Selector_Profile": "v5.5_prediction_ready_selector",
      "Fragility_Reason": "bbook_plus_fail",
      "Idea_Family": "continuation|no_theme|LONG|nonusd|strong",
      "Survivor_Score": 3.173,
      "Tournament_Pool": "radical_board",
      "Tournament_Pool_Display": "Radical board",
      "Tournament_Pool_Eligible": "radical_board",
      "Local_Pool_Score": -11.1728,
      "Tournament_Finalist_Flag": false,
      "Shortlist_Slot_Name": "",
      "Shortlist_Slot_Order": NaN,
      "Crowding_Block_Reason": "",
      "Selection_Passed_Over_For_Diversity": "",
      "Comparative_Edge_Score_10": 6.17,
      "Comparator_Floor_Score_10": 4.0,
      "Dominance_Score_10": 5.52,
      "Primary_Shortlist_Flag": false,
      "Primary_Override_Flag": false,
      "Shadow_Watchlist_Flag": false,
      "Shadow_Watchlist_Reason": "",
      "Shadow_Watchlist_Order": NaN,
      "In_Top_Shortlist": false,
      "Setup_Quality_Grade_10": 3.31,
      "Setup_Quality_Grade_100": 33.1,
      "Setup_Quality_Band": "D",
      "Prediction_Top_Strengths": "execution 9.6, asymmetry 7.8, context 7.5",
      "Prediction_Main_Risks": "gate_pressure 11.8, kill_switch 6.7",
      "Prediction_Breakdown": "LONG continuation; strengths: execution 9.6, asymmetry 7.8, context 7.5; risks: gate_pressure 11.8, kill_switch 6.7; admission: blocked / blocked_gatepass",
      "Prediction_Score_Version": "v5.5_prediction_quality_v2",
      "Prediction_Uses_Only_Contemporaneous_Inputs": true,
      "Prediction_Forbidden_Field_Leak": false,
      "Prediction_Input_Fingerprint": "57dd790a40f71eb4",
      "Prediction_Integrity_Status": "clean_contemporaneous_only",
      "Prediction_Rank": 5
    },
    {
      "Snapshot_Date": "2026-06-29",
      "Prediction_Reference_Timestamp": "2026-06-29 16:31:25",
      "Market_Reference_Timestamp": "1970-01-01 00:00:00.000000698",
      "Instrument": "EURCHF",
      "status": "OK",
      "Universe_Layer": "Layer 1 — Core execution universe",
      "Cluster_Tags": "CHF haven cluster, EUR relative-value cluster, HTF conflict",
      "W1_Bias": "BEARISH",
      "D1_Bias": "BULLISH",
      "Price_Side_vs_D1_Range": "premium",
      "Alignment": "full conflict",
      "Liquidity_Condition": "external liquidity taken",
      "Sweep_Quality": "sweep + close back inside range",
      "Liquidity_Side": "sell-side",
      "Liquidity_Tier": "minor",
      "Liquidity_Reference_Type": "swing low",
      "Rejection_Quality": "strong rejection",
      "Follow_Through": "limited follow-through",
      "Both_Sides_Taken_Recently": true,
      "Displacement_Quality": "strong displacement",
      "MSS_BOS": "clear MSS/BOS",
      "Array_Quality": "weak",
      "Session_Quality": "acceptable but not ideal",
      "RS_RW_Alignment": "clear alignment",
      "SMT_Hint": "none",
      "Pivot_Regime": "daily: bullish above pivot | weekly: bearish below pivot",
      "Pivot_Zone_Fit": "price in buy zone",
      "Pivot_Confluence": "daily only",
      "Pivot_Conflict": "mild pivot conflict",
      "Pivot_Stretch": "not stretched",
      "Technical_Score_0_4": 2.2,
      "Legacy_Confidence_Score": 0.99,
      "Legacy_Confidence_Band": "high",
      "Confidence_Score": 0.375,
      "Confidence_Band": "low",
      "Technical_Quality_Score_10": 6.05,
      "Execution_Realism_Score_10": 10.0,
      "Calibrated_Confidence_Score_10": 3.75,
      "Selection_Score": -7.2366,
      "Final_Rank_Score": -7.2646,
      "Data_Quality": "good",
      "Entry_Label": "D-tier avoid",
      "Preferred_Side": "LONG",
      "Best_Entry": 0.9231,
      "Structural_Entry": 0.9209,
      "Calibration_Entry": 0.9231,
      "Entry_Distance_ATR": 0.059,
      "SL": 0.9224,
      "TP1": 0.924,
      "TP2": 0.9247,
      "Current_Price": 0.9232,
      "ATR_H1": 0.0007,
      "RR_TP1": 1.2857,
      "RR_TP2": 2.2857,
      "Execution_Line": "Buy-limit: 0.9231 | SL: 0.9224 | TP1: 0.924 | TP2: 0.9247 | RR1: 1.2857 | RR2: 2.2857",
      "Execution_Source": "zone",
      "Setup_Archetype": "continuation",
      "Decision_Book": "B-book",
      "Live_Gate_Passed": false,
      "Calibration_Gate_Passed": true,
      "Gate_Passed": true,
      "Gate_Fail_Reasons": "d_tier",
      "Decision_Setup_Quality": 2.0,
      "Decision_Execution_Quality": 3.8,
      "Decision_Portfolio_Fit": 0.0,
      "Decision_Rank_Score": -10.8956,
      "Base_Ranking_Score": -10.8356,
      "Overlap_Penalty": 0.0,
      "Ranking_Score": -7.2646,
      "Calibration_Soft_Candidate": true,
      "Calibration_Candidate_Bucket": "hard_pass",
      "Soft_Candidate": true,
      "Soft_Fail_Adjustment": -0.25,
      "Continuation_Subquality": 0.4,
      "Continuation_Elite_Eligible": true,
      "Context_Quality_Score_10": 4.2,
      "Trigger_Quality_Score_10": 7.85,
      "Conflict_Penalty_Score_10": 4.6,
      "Opportunity_Score_10": 6.8,
      "Balance_Score_10": 4.06,
      "Kill_Switch_Score_10": 6.1,
      "False_Positive_Risk_Score_10": 3.8,
      "Archetype_Tax_Score_10": 3.0,
      "Survivability_Score_10": 3.77,
      "Asymmetry_Score_10": 8.3,
      "Calibration_Utility_Score_10": 6.9,
      "Radical_Confidence_Score_10": 3.75,
      "Admission_Class": "blocked",
      "Override_Reason": "gatepass_primary_block",
      "Shortlist_Eligibility": "blocked",
      "Admission_Binding_Status": "blocked_gatepass",
      "Selection_Lane": "blocked_gatepass",
      "Leakage_Penalty_Score": 3.0,
      "Veto_Flag": false,
      "Veto_Reasons": "",
      "Selector_Profile": "v5.5_prediction_ready_selector",
      "Fragility_Reason": "bbook_plus_fail",
      "Idea_Family": "continuation|no_theme|LONG|nonusd|strong",
      "Survivor_Score": 2.8805,
      "Tournament_Pool": "radical_board",
      "Tournament_Pool_Display": "Radical board",
      "Tournament_Pool_Eligible": "radical_board",
      "Local_Pool_Score": -10.8956,
      "Tournament_Finalist_Flag": false,
      "Shortlist_Slot_Name": "",
      "Shortlist_Slot_Order": NaN,
      "Crowding_Block_Reason": "",
      "Selection_Passed_Over_For_Diversity": "",
      "Comparative_Edge_Score_10": 6.81,
      "Comparator_Floor_Score_10": 4.0,
      "Dominance_Score_10": 5.97,
      "Primary_Shortlist_Flag": false,
      "Primary_Override_Flag": false,
      "Shadow_Watchlist_Flag": false,
      "Shadow_Watchlist_Reason": "",
      "Shadow_Watchlist_Order": NaN,
      "In_Top_Shortlist": false,
      "Setup_Quality_Grade_10": 3.26,
      "Setup_Quality_Grade_100": 32.6,
      "Setup_Quality_Band": "D",
      "Prediction_Top_Strengths": "execution 10.0, asymmetry 8.3, trigger 7.8",
      "Prediction_Main_Risks": "gate_pressure 11.8, kill_switch 6.1",
      "Prediction_Breakdown": "LONG continuation; strengths: execution 10.0, asymmetry 8.3, trigger 7.8; risks: gate_pressure 11.8, kill_switch 6.1; admission: blocked / blocked_gatepass",
      "Prediction_Score_Version": "v5.5_prediction_quality_v2",
      "Prediction_Uses_Only_Contemporaneous_Inputs": true,
      "Prediction_Forbidden_Field_Leak": false,
      "Prediction_Input_Fingerprint": "9dc0f54ddcf8ee53",
      "Prediction_Integrity_Status": "clean_contemporaneous_only",
      "Prediction_Rank": 6
    },
    {
      "Snapshot_Date": "2026-06-29",
      "Prediction_Reference_Timestamp": "2026-06-29 16:31:25",
      "Market_Reference_Timestamp": "1970-01-01 00:00:00.000000698",
      "Instrument": "EURAUD",
      "status": "OK",
      "Universe_Layer": "Layer 2 — Relative-value crosses",
      "Cluster_Tags": "EUR relative-value cluster, HTF aligned, commodity bloc",
      "W1_Bias": "BULLISH",
      "D1_Bias": "BULLISH",
      "Price_Side_vs_D1_Range": "premium",
      "Alignment": "aligned",
      "Liquidity_Condition": "external liquidity taken",
      "Sweep_Quality": "clean sweep only",
      "Liquidity_Side": "buy-side",
      "Liquidity_Tier": "minor",
      "Liquidity_Reference_Type": "swing high",
      "Rejection_Quality": "weak/no rejection",
      "Follow_Through": "limited follow-through",
      "Both_Sides_Taken_Recently": true,
      "Displacement_Quality": "strong displacement",
      "MSS_BOS": "partial shift",
      "Array_Quality": "good",
      "Session_Quality": "acceptable but not ideal",
      "RS_RW_Alignment": "clear alignment",
      "SMT_Hint": "none",
      "Pivot_Regime": "daily: bullish above pivot | weekly: bullish above pivot",
      "Pivot_Zone_Fit": "price in neutral zone",
      "Pivot_Confluence": "mixed confluence",
      "Pivot_Conflict": "no meaningful pivot conflict",
      "Pivot_Stretch": "moderately stretched",
      "Technical_Score_0_4": 2.05,
      "Legacy_Confidence_Score": 0.85,
      "Legacy_Confidence_Band": "medium",
      "Confidence_Score": 0.379,
      "Confidence_Band": "low",
      "Technical_Quality_Score_10": 7.95,
      "Execution_Realism_Score_10": 10.0,
      "Calibrated_Confidence_Score_10": 3.79,
      "Selection_Score": -9.7368,
      "Final_Rank_Score": -9.7928,
      "Data_Quality": "good",
      "Entry_Label": "B-tier reactive setup",
      "Preferred_Side": "LONG",
      "Best_Entry": 1.6589,
      "Structural_Entry": 1.6391,
      "Calibration_Entry": 1.6589,
      "Entry_Distance_ATR": 0.061,
      "SL": 1.6576,
      "TP1": 1.6605,
      "TP2": 1.6617,
      "Current_Price": 1.6592,
      "ATR_H1": 0.0016,
      "RR_TP1": 1.2308,
      "RR_TP2": 2.1538,
      "Execution_Line": "Buy-limit: 1.6589 | SL: 1.6576 | TP1: 1.6605 | TP2: 1.6617 | RR1: 1.2308 | RR2: 2.1538",
      "Execution_Source": "zone",
      "Setup_Archetype": "relative_value_continuation",
      "Decision_Book": "A-book",
      "Live_Gate_Passed": true,
      "Calibration_Gate_Passed": true,
      "Gate_Passed": true,
      "Gate_Fail_Reasons": "",
      "Decision_Setup_Quality": 3.65,
      "Decision_Execution_Quality": 3.8,
      "Decision_Portfolio_Fit": 0.0,
      "Decision_Rank_Score": -10.7689,
      "Base_Ranking_Score": -10.7089,
      "Overlap_Penalty": 0.0,
      "Ranking_Score": -9.7928,
      "Calibration_Soft_Candidate": false,
      "Calibration_Candidate_Bucket": "hard_pass",
      "Soft_Candidate": false,
      "Soft_Fail_Adjustment": 0.0,
      "Continuation_Subquality": 0.0,
      "Continuation_Elite_Eligible": false,
      "Context_Quality_Score_10": 7.2,
      "Trigger_Quality_Score_10": 5.85,
      "Conflict_Penalty_Score_10": 0.0,
      "Opportunity_Score_10": 3.95,
      "Balance_Score_10": 6.26,
      "Kill_Switch_Score_10": 0.0,
      "False_Positive_Risk_Score_10": 7.5,
      "Archetype_Tax_Score_10": 7.2,
      "Survivability_Score_10": 6.66,
      "Asymmetry_Score_10": 7.2,
      "Calibration_Utility_Score_10": 3.4,
      "Radical_Confidence_Score_10": 3.79,
      "Admission_Class": "blocked",
      "Override_Reason": "false_positive_block",
      "Shortlist_Eligibility": "blocked",
      "Admission_Binding_Status": "blocked_false_positive",
      "Selection_Lane": "blocked_false_positive",
      "Leakage_Penalty_Score": 3.0,
      "Veto_Flag": true,
      "Veto_Reasons": "false_positive_block",
      "Selector_Profile": "v5.5_prediction_ready_selector",
      "Fragility_Reason": "",
      "Idea_Family": "relval|no_theme|LONG|nonusd",
      "Survivor_Score": 3.134,
      "Tournament_Pool": "radical_board",
      "Tournament_Pool_Display": "Radical board",
      "Tournament_Pool_Eligible": "radical_board",
      "Local_Pool_Score": -10.7689,
      "Tournament_Finalist_Flag": false,
      "Shortlist_Slot_Name": "",
      "Shortlist_Slot_Order": NaN,
      "Crowding_Block_Reason": "",
      "Selection_Passed_Over_For_Diversity": "",
      "Comparative_Edge_Score_10": 2.0,
      "Comparator_Floor_Score_10": 0.5,
      "Dominance_Score_10": 1.55,
      "Primary_Shortlist_Flag": false,
      "Primary_Override_Flag": false,
      "Shadow_Watchlist_Flag": false,
      "Shadow_Watchlist_Reason": "",
      "Shadow_Watchlist_Order": NaN,
      "In_Top_Shortlist": false,
      "Setup_Quality_Grade_10": 3.2,
      "Setup_Quality_Grade_100": 32.0,
      "Setup_Quality_Band": "D",
      "Prediction_Top_Strengths": "execution 10.0, asymmetry 7.2, context 7.2",
      "Prediction_Main_Risks": "gate_pressure 12.7, false_positive_risk 7.5",
      "Prediction_Breakdown": "LONG relative_value_continuation; strengths: execution 10.0, asymmetry 7.2, context 7.2; risks: gate_pressure 12.7, false_positive_risk 7.5; admission: blocked / blocked_false_positive",
      "Prediction_Score_Version": "v5.5_prediction_quality_v2",
      "Prediction_Uses_Only_Contemporaneous_Inputs": true,
      "Prediction_Forbidden_Field_Leak": false,
      "Prediction_Input_Fingerprint": "c369985c4e4298df",
      "Prediction_Integrity_Status": "clean_contemporaneous_only",
      "Prediction_Rank": 7
    },
    {
      "Snapshot_Date": "2026-06-29",
      "Prediction_Reference_Timestamp": "2026-06-29 16:31:25",
      "Market_Reference_Timestamp": "1970-01-01 00:00:00.000000698",
      "Instrument": "USDJPY",
      "status": "OK",
      "Universe_Layer": "Layer 1 — Core execution universe",
      "Cluster_Tags": "HTF aligned, JPY cluster, USD basket, USD strength",
      "W1_Bias": "BULLISH",
      "D1_Bias": "BULLISH",
      "Price_Side_vs_D1_Range": "premium",
      "Alignment": "aligned",
      "Liquidity_Condition": "external liquidity taken",
      "Sweep_Quality": "clean sweep only",
      "Liquidity_Side": "buy-side",
      "Liquidity_Tier": "minor",
      "Liquidity_Reference_Type": "swing high",
      "Rejection_Quality": "moderate rejection",
      "Follow_Through": "limited follow-through",
      "Both_Sides_Taken_Recently": true,
      "Displacement_Quality": "weak / no displacement",
      "MSS_BOS": "partial shift",
      "Array_Quality": "weak",
      "Session_Quality": "acceptable but not ideal",
      "RS_RW_Alignment": "mixed",
      "SMT_Hint": "none",
      "Pivot_Regime": "daily: bullish above pivot | weekly: bullish above pivot",
      "Pivot_Zone_Fit": "price in neutral zone",
      "Pivot_Confluence": "mixed confluence",
      "Pivot_Conflict": "no meaningful pivot conflict",
      "Pivot_Stretch": "not stretched",
      "Technical_Score_0_4": 0.8,
      "Legacy_Confidence_Score": 0.75,
      "Legacy_Confidence_Band": "medium",
      "Confidence_Score": 0.372,
      "Confidence_Band": "low",
      "Technical_Quality_Score_10": 6.05,
      "Execution_Realism_Score_10": 7.85,
      "Calibrated_Confidence_Score_10": 3.72,
      "Selection_Score": -8.1253,
      "Final_Rank_Score": -8.1533,
      "Data_Quality": "good",
      "Entry_Label": "D-tier avoid",
      "Preferred_Side": "LONG",
      "Best_Entry": 161.935,
      "Structural_Entry": 161.927,
      "Calibration_Entry": 161.935,
      "Entry_Distance_ATR": 0.052,
      "SL": 161.732,
      "TP1": 162.181,
      "TP2": 162.372,
      "Current_Price": 161.934,
      "ATR_H1": 0.056,
      "RR_TP1": 1.2118,
      "RR_TP2": 2.1527,
      "Execution_Line": "Buy-limit: 161.935 | SL: 161.732 | TP1: 162.181 | TP2: 162.372 | RR1: 1.2118 | RR2: 2.1527",
      "Execution_Source": "fallback",
      "Setup_Archetype": "continuation",
      "Decision_Book": "B-book",
      "Live_Gate_Passed": false,
      "Calibration_Gate_Passed": true,
      "Gate_Passed": true,
      "Gate_Fail_Reasons": "d_tier, weak_impulse",
      "Decision_Setup_Quality": 1.85,
      "Decision_Execution_Quality": 2.6,
      "Decision_Portfolio_Fit": 0.0,
      "Decision_Rank_Score": -11.3428,
      "Base_Ranking_Score": -11.2828,
      "Overlap_Penalty": 0.0,
      "Ranking_Score": -8.1533,
      "Calibration_Soft_Candidate": true,
      "Calibration_Candidate_Bucket": "hard_pass",
      "Soft_Candidate": true,
      "Soft_Fail_Adjustment": -0.45,
      "Continuation_Subquality": 0.13,
      "Continuation_Elite_Eligible": true,
      "Context_Quality_Score_10": 7.2,
      "Trigger_Quality_Score_10": 4.45,
      "Conflict_Penalty_Score_10": 2.7,
      "Opportunity_Score_10": 6.8,
      "Balance_Score_10": 6.33,
      "Kill_Switch_Score_10": 6.7,
      "False_Positive_Risk_Score_10": 3.8,
      "Archetype_Tax_Score_10": 3.8,
      "Survivability_Score_10": 4.01,
      "Asymmetry_Score_10": 7.8,
      "Calibration_Utility_Score_10": 6.9,
      "Radical_Confidence_Score_10": 3.72,
      "Admission_Class": "blocked",
      "Override_Reason": "gatepass_primary_block",
      "Shortlist_Eligibility": "blocked",
      "Admission_Binding_Status": "blocked_gatepass",
      "Selection_Lane": "blocked_gatepass",
      "Leakage_Penalty_Score": 3.0,
      "Veto_Flag": false,
      "Veto_Reasons": "",
      "Selector_Profile": "v5.5_prediction_ready_selector",
      "Fragility_Reason": "bbook_plus_fail",
      "Idea_Family": "continuation|no_theme|LONG|nonusd|normal",
      "Survivor_Score": 3.0365,
      "Tournament_Pool": "radical_board",
      "Tournament_Pool_Display": "Radical board",
      "Tournament_Pool_Eligible": "radical_board",
      "Local_Pool_Score": -11.3428,
      "Tournament_Finalist_Flag": false,
      "Shortlist_Slot_Name": "",
      "Shortlist_Slot_Order": NaN,
      "Crowding_Block_Reason": "",
      "Selection_Passed_Over_For_Diversity": "",
      "Comparative_Edge_Score_10": 5.84,
      "Comparator_Floor_Score_10": 4.0,
      "Dominance_Score_10": 5.29,
      "Primary_Shortlist_Flag": false,
      "Primary_Override_Flag": false,
      "Shadow_Watchlist_Flag": false,
      "Shadow_Watchlist_Reason": "",
      "Shadow_Watchlist_Order": NaN,
      "In_Top_Shortlist": false,
      "Setup_Quality_Grade_10": 3.08,
      "Setup_Quality_Grade_100": 30.8,
      "Setup_Quality_Band": "D",
      "Prediction_Top_Strengths": "execution 7.8, asymmetry 7.8, context 7.2",
      "Prediction_Main_Risks": "gate_pressure 11.8, kill_switch 6.7",
      "Prediction_Breakdown": "LONG continuation; strengths: execution 7.8, asymmetry 7.8, context 7.2; risks: gate_pressure 11.8, kill_switch 6.7; admission: blocked / blocked_gatepass",
      "Prediction_Score_Version": "v5.5_prediction_quality_v2",
      "Prediction_Uses_Only_Contemporaneous_Inputs": true,
      "Prediction_Forbidden_Field_Leak": false,
      "Prediction_Input_Fingerprint": "247a9359008bb5ed",
      "Prediction_Integrity_Status": "clean_contemporaneous_only",
      "Prediction_Rank": 8
    },
    {
      "Snapshot_Date": "2026-06-29",
      "Prediction_Reference_Timestamp": "2026-06-29 16:31:25",
      "Market_Reference_Timestamp": "1970-01-01 00:00:00.000000698",
      "Instrument": "AUDNZD",
      "status": "OK",
      "Universe_Layer": "Layer 2 — Relative-value crosses",
      "Cluster_Tags": "HTF aligned, commodity bloc",
      "W1_Bias": "BEARISH",
      "D1_Bias": "BEARISH",
      "Price_Side_vs_D1_Range": "premium",
      "Alignment": "aligned",
      "Liquidity_Condition": "external liquidity taken",
      "Sweep_Quality": "clean sweep only",
      "Liquidity_Side": "sell-side",
      "Liquidity_Tier": "minor",
      "Liquidity_Reference_Type": "swing low",
      "Rejection_Quality": "weak/no rejection",
      "Follow_Through": "limited follow-through",
      "Both_Sides_Taken_Recently": true,
      "Displacement_Quality": "weak / no displacement",
      "MSS_BOS": "partial shift",
      "Array_Quality": "strong",
      "Session_Quality": "acceptable but not ideal",
      "RS_RW_Alignment": "clear alignment",
      "SMT_Hint": "none",
      "Pivot_Regime": "daily: bearish below pivot | weekly: bearish below pivot",
      "Pivot_Zone_Fit": "price in neutral zone",
      "Pivot_Confluence": "mixed confluence",
      "Pivot_Conflict": "no meaningful pivot conflict",
      "Pivot_Stretch": "not stretched",
      "Technical_Score_0_4": 1.6,
      "Legacy_Confidence_Score": 0.75,
      "Legacy_Confidence_Band": "medium",
      "Confidence_Score": 0.415,
      "Confidence_Band": "low",
      "Technical_Quality_Score_10": 5.95,
      "Execution_Realism_Score_10": 10.0,
      "Calibrated_Confidence_Score_10": 4.15,
      "Selection_Score": -9.2457,
      "Final_Rank_Score": -9.295,
      "Data_Quality": "good",
      "Entry_Label": "B-tier reactive setup",
      "Preferred_Side": "SHORT",
      "Best_Entry": 1.219,
      "Structural_Entry": 1.2216,
      "Calibration_Entry": 1.219,
      "Entry_Distance_ATR": 0.087,
      "SL": 1.22,
      "TP1": 1.2178,
      "TP2": 1.2169,
      "Current_Price": 1.219,
      "ATR_H1": 0.0008,
      "RR_TP1": 1.2,
      "RR_TP2": 2.1,
      "Execution_Line": "Sell-limit: 1.219 | SL: 1.22 | TP1: 1.2178 | TP2: 1.2169 | RR1: 1.2 | RR2: 2.1",
      "Execution_Source": "zone",
      "Setup_Archetype": "relative_value_continuation",
      "Decision_Book": "B-book",
      "Live_Gate_Passed": false,
      "Calibration_Gate_Passed": true,
      "Gate_Passed": true,
      "Gate_Fail_Reasons": "weak_impulse",
      "Decision_Setup_Quality": 2.15,
      "Decision_Execution_Quality": 3.8,
      "Decision_Portfolio_Fit": 0.0,
      "Decision_Rank_Score": -11.142,
      "Base_Ranking_Score": -11.082,
      "Overlap_Penalty": 0.0,
      "Ranking_Score": -9.295,
      "Calibration_Soft_Candidate": true,
      "Calibration_Candidate_Bucket": "hard_pass",
      "Soft_Candidate": true,
      "Soft_Fail_Adjustment": -0.2,
      "Continuation_Subquality": 0.0,
      "Continuation_Elite_Eligible": false,
      "Context_Quality_Score_10": 7.2,
      "Trigger_Quality_Score_10": 3.65,
      "Conflict_Penalty_Score_10": 1.1,
      "Opportunity_Score_10": 5.75,
      "Balance_Score_10": 3.32,
      "Kill_Switch_Score_10": 2.8,
      "False_Positive_Risk_Score_10": 5.4,
      "Archetype_Tax_Score_10": 7.2,
      "Survivability_Score_10": 4.56,
      "Asymmetry_Score_10": 7.2,
      "Calibration_Utility_Score_10": 5.9,
      "Radical_Confidence_Score_10": 4.15,
      "Admission_Class": "blocked",
      "Override_Reason": "relval_hard_block",
      "Shortlist_Eligibility": "blocked",
      "Admission_Binding_Status": "blocked_relval",
      "Selection_Lane": "blocked_relval",
      "Leakage_Penalty_Score": 3.0,
      "Veto_Flag": false,
      "Veto_Reasons": "",
      "Selector_Profile": "v5.5_prediction_ready_selector",
      "Fragility_Reason": "bbook_plus_fail",
      "Idea_Family": "relval|no_theme|SHORT|nonusd",
      "Survivor_Score": 2.794,
      "Tournament_Pool": "radical_board",
      "Tournament_Pool_Display": "Radical board",
      "Tournament_Pool_Eligible": "radical_board",
      "Local_Pool_Score": -11.142,
      "Tournament_Finalist_Flag": false,
      "Shortlist_Slot_Name": "",
      "Shortlist_Slot_Order": NaN,
      "Crowding_Block_Reason": "",
      "Selection_Passed_Over_For_Diversity": "",
      "Comparative_Edge_Score_10": 3.67,
      "Comparator_Floor_Score_10": 1.33,
      "Dominance_Score_10": 2.97,
      "Primary_Shortlist_Flag": false,
      "Primary_Override_Flag": false,
      "Shadow_Watchlist_Flag": false,
      "Shadow_Watchlist_Reason": "",
      "Shadow_Watchlist_Order": NaN,
      "In_Top_Shortlist": false,
      "Setup_Quality_Grade_10": 2.95,
      "Setup_Quality_Grade_100": 29.5,
      "Setup_Quality_Band": "D",
      "Prediction_Top_Strengths": "execution 10.0, asymmetry 7.2, context 7.2",
      "Prediction_Main_Risks": "gate_pressure 11.8, archetype_tax 7.2",
      "Prediction_Breakdown": "SHORT relative_value_continuation; strengths: execution 10.0, asymmetry 7.2, context 7.2; risks: gate_pressure 11.8, archetype_tax 7.2; admission: blocked / blocked_relval",
      "Prediction_Score_Version": "v5.5_prediction_quality_v2",
      "Prediction_Uses_Only_Contemporaneous_Inputs": true,
      "Prediction_Forbidden_Field_Leak": false,
      "Prediction_Input_Fingerprint": "856600a274a4178f",
      "Prediction_Integrity_Status": "clean_contemporaneous_only",
      "Prediction_Rank": 9
    },
    {
      "Snapshot_Date": "2026-06-29",
      "Prediction_Reference_Timestamp": "2026-06-29 16:31:25",
      "Market_Reference_Timestamp": "1970-01-01 00:00:00.000000698",
      "Instrument": "GBPCAD",
      "status": "OK",
      "Universe_Layer": "Layer 2 — Relative-value crosses",
      "Cluster_Tags": "HTF aligned, commodity bloc",
      "W1_Bias": "BULLISH",
      "D1_Bias": "BULLISH",
      "Price_Side_vs_D1_Range": "premium",
      "Alignment": "aligned",
      "Liquidity_Condition": "external liquidity taken",
      "Sweep_Quality": "clean sweep only",
      "Liquidity_Side": "buy-side",
      "Liquidity_Tier": "major",
      "Liquidity_Reference_Type": "swing high",
      "Rejection_Quality": "weak/no rejection",
      "Follow_Through": "limited follow-through",
      "Both_Sides_Taken_Recently": true,
      "Displacement_Quality": "weak / no displacement",
      "MSS_BOS": "partial shift",
      "Array_Quality": "weak",
      "Session_Quality": "acceptable but not ideal",
      "RS_RW_Alignment": "mixed",
      "SMT_Hint": "none",
      "Pivot_Regime": "daily: bullish above pivot | weekly: bullish above pivot",
      "Pivot_Zone_Fit": "price in neutral zone",
      "Pivot_Confluence": "mixed confluence",
      "Pivot_Conflict": "no meaningful pivot conflict",
      "Pivot_Stretch": "moderately stretched",
      "Technical_Score_0_4": 0.45,
      "Legacy_Confidence_Score": 0.75,
      "Legacy_Confidence_Band": "medium",
      "Confidence_Score": 0.327,
      "Confidence_Band": "low",
      "Technical_Quality_Score_10": 5.6,
      "Execution_Realism_Score_10": 10.0,
      "Calibrated_Confidence_Score_10": 3.27,
      "Selection_Score": -9.6356,
      "Final_Rank_Score": -9.685,
      "Data_Quality": "good",
      "Entry_Label": "D-tier avoid",
      "Preferred_Side": "LONG",
      "Best_Entry": 1.8832,
      "Structural_Entry": 1.8831,
      "Calibration_Entry": 1.8832,
      "Entry_Distance_ATR": 0.048,
      "SL": 1.8809,
      "TP1": 1.8861,
      "TP2": 1.8883,
      "Current_Price": 1.8833,
      "ATR_H1": 0.0015,
      "RR_TP1": 1.2609,
      "RR_TP2": 2.2174,
      "Execution_Line": "Buy-limit: 1.8832 | SL: 1.8809 | TP1: 1.8861 | TP2: 1.8883 | RR1: 1.2609 | RR2: 2.2174",
      "Execution_Source": "fallback",
      "Setup_Archetype": "continuation",
      "Decision_Book": "B-book",
      "Live_Gate_Passed": false,
      "Calibration_Gate_Passed": true,
      "Gate_Passed": true,
      "Gate_Fail_Reasons": "d_tier, weak_impulse",
      "Decision_Setup_Quality": 1.75,
      "Decision_Execution_Quality": 3.8,
      "Decision_Portfolio_Fit": 0.0,
      "Decision_Rank_Score": -11.498,
      "Base_Ranking_Score": -11.438,
      "Overlap_Penalty": 0.0,
      "Ranking_Score": -9.685,
      "Calibration_Soft_Candidate": true,
      "Calibration_Candidate_Bucket": "hard_pass",
      "Soft_Candidate": true,
      "Soft_Fail_Adjustment": -0.45,
      "Continuation_Subquality": -0.07,
      "Continuation_Elite_Eligible": false,
      "Context_Quality_Score_10": 7.5,
      "Trigger_Quality_Score_10": 3.65,
      "Conflict_Penalty_Score_10": 2.7,
      "Opportunity_Score_10": 6.35,
      "Balance_Score_10": 3.32,
      "Kill_Switch_Score_10": 6.7,
      "False_Positive_Risk_Score_10": 3.8,
      "Archetype_Tax_Score_10": 3.4,
      "Survivability_Score_10": 3.54,
      "Asymmetry_Score_10": 7.2,
      "Calibration_Utility_Score_10": 6.9,
      "Radical_Confidence_Score_10": 3.27,
      "Admission_Class": "blocked",
      "Override_Reason": "gatepass_primary_block",
      "Shortlist_Eligibility": "blocked",
      "Admission_Binding_Status": "blocked_gatepass",
      "Selection_Lane": "blocked_gatepass",
      "Leakage_Penalty_Score": 3.0,
      "Veto_Flag": false,
      "Veto_Reasons": "",
      "Selector_Profile": "v5.5_prediction_ready_selector",
      "Fragility_Reason": "bbook_plus_fail",
      "Idea_Family": "continuation|no_theme|LONG|nonusd|normal",
      "Survivor_Score": 2.731,
      "Tournament_Pool": "radical_board",
      "Tournament_Pool_Display": "Radical board",
      "Tournament_Pool_Eligible": "radical_board",
      "Local_Pool_Score": -11.498,
      "Tournament_Finalist_Flag": false,
      "Shortlist_Slot_Name": "",
      "Shortlist_Slot_Order": NaN,
      "Crowding_Block_Reason": "",
      "Selection_Passed_Over_For_Diversity": "",
      "Comparative_Edge_Score_10": 3.59,
      "Comparator_Floor_Score_10": 1.33,
      "Dominance_Score_10": 2.92,
      "Primary_Shortlist_Flag": false,
      "Primary_Override_Flag": false,
      "Shadow_Watchlist_Flag": false,
      "Shadow_Watchlist_Reason": "",
      "Shadow_Watchlist_Order": NaN,
      "In_Top_Shortlist": false,
      "Setup_Quality_Grade_10": 2.71,
      "Setup_Quality_Grade_100": 27.1,
      "Setup_Quality_Band": "D",
      "Prediction_Top_Strengths": "execution 10.0, context 7.5, asymmetry 7.2",
      "Prediction_Main_Risks": "gate_pressure 11.8, kill_switch 6.7",
      "Prediction_Breakdown": "LONG continuation; strengths: execution 10.0, context 7.5, asymmetry 7.2; risks: gate_pressure 11.8, kill_switch 6.7; admission: blocked / blocked_gatepass",
      "Prediction_Score_Version": "v5.5_prediction_quality_v2",
      "Prediction_Uses_Only_Contemporaneous_Inputs": true,
      "Prediction_Forbidden_Field_Leak": false,
      "Prediction_Input_Fingerprint": "fe24854806d834e5",
      "Prediction_Integrity_Status": "clean_contemporaneous_only",
      "Prediction_Rank": 10
    },
    {
      "Snapshot_Date": "2026-06-29",
      "Prediction_Reference_Timestamp": "2026-06-29 16:31:25",
      "Market_Reference_Timestamp": "1970-01-01 00:00:00.000000698",
      "Instrument": "GBPJPY",
      "status": "OK",
      "Universe_Layer": "Layer 1 — Core execution universe",
      "Cluster_Tags": "HTF aligned, JPY cluster",
      "W1_Bias": "BULLISH",
      "D1_Bias": "BULLISH",
      "Price_Side_vs_D1_Range": "premium",
      "Alignment": "aligned",
      "Liquidity_Condition": "external liquidity taken",
      "Sweep_Quality": "clean sweep only",
      "Liquidity_Side": "buy-side",
      "Liquidity_Tier": "major",
      "Liquidity_Reference_Type": "swing high",
      "Rejection_Quality": "weak/no rejection",
      "Follow_Through": "limited follow-through",
      "Both_Sides_Taken_Recently": true,
      "Displacement_Quality": "weak / no displacement",
      "MSS_BOS": "partial shift",
      "Array_Quality": "weak",
      "Session_Quality": "acceptable but not ideal",
      "RS_RW_Alignment": "clear alignment",
      "SMT_Hint": "none",
      "Pivot_Regime": "daily: bullish above pivot | weekly: bullish above pivot",
      "Pivot_Zone_Fit": "price in neutral zone",
      "Pivot_Confluence": "mixed confluence",
      "Pivot_Conflict": "no meaningful pivot conflict",
      "Pivot_Stretch": "moderately stretched",
      "Technical_Score_0_4": 0.35,
      "Legacy_Confidence_Score": 0.75,
      "Legacy_Confidence_Band": "medium",
      "Confidence_Score": 0.277,
      "Confidence_Band": "low",
      "Technical_Quality_Score_10": 6.2,
      "Execution_Realism_Score_10": 10.0,
      "Calibrated_Confidence_Score_10": 2.77,
      "Selection_Score": -10.8513,
      "Final_Rank_Score": -10.9007,
      "Data_Quality": "good",
      "Entry_Label": "D-tier avoid",
      "Preferred_Side": "LONG",
      "Best_Entry": 214.612,
      "Structural_Entry": 213.217,
      "Calibration_Entry": 214.612,
      "Entry_Distance_ATR": 0.049,
      "SL": 214.445,
      "TP1": 214.814,
      "TP2": 214.972,
      "Current_Price": 214.58,
      "ATR_H1": 0.193,
      "RR_TP1": 1.2096,
      "RR_TP2": 2.1557,
      "Execution_Line": "Buy-limit: 214.612 | SL: 214.445 | TP1: 214.814 | TP2: 214.972 | RR1: 1.2096 | RR2: 2.1557",
      "Execution_Source": "zone",
      "Setup_Archetype": "relative_value_continuation",
      "Decision_Book": "B-book",
      "Live_Gate_Passed": false,
      "Calibration_Gate_Passed": true,
      "Gate_Passed": true,
      "Gate_Fail_Reasons": "d_tier, weak_impulse",
      "Decision_Setup_Quality": 1.75,
      "Decision_Execution_Quality": 3.8,
      "Decision_Portfolio_Fit": 0.0,
      "Decision_Rank_Score": -12.5202,
      "Base_Ranking_Score": -12.4602,
      "Overlap_Penalty": 0.0,
      "Ranking_Score": -10.9007,
      "Calibration_Soft_Candidate": true,
      "Calibration_Candidate_Bucket": "hard_pass",
      "Soft_Candidate": true,
      "Soft_Fail_Adjustment": -0.45,
      "Continuation_Subquality": 0.0,
      "Continuation_Elite_Eligible": false,
      "Context_Quality_Score_10": 7.5,
      "Trigger_Quality_Score_10": 3.65,
      "Conflict_Penalty_Score_10": 2.7,
      "Opportunity_Score_10": 5.75,
      "Balance_Score_10": 3.32,
      "Kill_Switch_Score_10": 6.7,
      "False_Positive_Risk_Score_10": 5.4,
      "Archetype_Tax_Score_10": 7.2,
      "Survivability_Score_10": 3.54,
      "Asymmetry_Score_10": 7.2,
      "Calibration_Utility_Score_10": 5.9,
      "Radical_Confidence_Score_10": 2.77,
      "Admission_Class": "blocked",
      "Override_Reason": "relval_hard_block",
      "Shortlist_Eligibility": "blocked",
      "Admission_Binding_Status": "blocked_relval",
      "Selection_Lane": "blocked_relval",
      "Leakage_Penalty_Score": 3.0,
      "Veto_Flag": false,
      "Veto_Reasons": "",
      "Selector_Profile": "v5.5_prediction_ready_selector",
      "Fragility_Reason": "bbook_plus_fail",
      "Idea_Family": "relval|no_theme|LONG|nonusd",
      "Survivor_Score": 2.131,
      "Tournament_Pool": "radical_board",
      "Tournament_Pool_Display": "Radical board",
      "Tournament_Pool_Eligible": "radical_board",
      "Local_Pool_Score": -12.5202,
      "Tournament_Finalist_Flag": false,
      "Shortlist_Slot_Name": "",
      "Shortlist_Slot_Order": NaN,
      "Crowding_Block_Reason": "",
      "Selection_Passed_Over_For_Diversity": "",
      "Comparative_Edge_Score_10": 3.17,
      "Comparator_Floor_Score_10": 1.33,
      "Dominance_Score_10": 2.62,
      "Primary_Shortlist_Flag": false,
      "Primary_Override_Flag": false,
      "Shadow_Watchlist_Flag": false,
      "Shadow_Watchlist_Reason": "",
      "Shadow_Watchlist_Order": NaN,
      "In_Top_Shortlist": false,
      "Setup_Quality_Grade_10": 2.03,
      "Setup_Quality_Grade_100": 20.3,
      "Setup_Quality_Band": "E",
      "Prediction_Top_Strengths": "execution 10.0, context 7.5, asymmetry 7.2",
      "Prediction_Main_Risks": "gate_pressure 11.8, archetype_tax 7.2",
      "Prediction_Breakdown": "LONG relative_value_continuation; strengths: execution 10.0, context 7.5, asymmetry 7.2; risks: gate_pressure 11.8, archetype_tax 7.2; admission: blocked / blocked_relval",
      "Prediction_Score_Version": "v5.5_prediction_quality_v2",
      "Prediction_Uses_Only_Contemporaneous_Inputs": true,
      "Prediction_Forbidden_Field_Leak": false,
      "Prediction_Input_Fingerprint": "006ae4e638e536bc",
      "Prediction_Integrity_Status": "clean_contemporaneous_only",
      "Prediction_Rank": 11
    },
    {
      "Snapshot_Date": "2026-06-29",
      "Prediction_Reference_Timestamp": "2026-06-29 16:31:25",
      "Market_Reference_Timestamp": "1970-01-01 00:00:00.000000698",
      "Instrument": "NZDCAD",
      "status": "OK",
      "Universe_Layer": "Layer 2 — Relative-value crosses",
      "Cluster_Tags": "HTF conflict, commodity bloc",
      "W1_Bias": "BEARISH",
      "D1_Bias": "BULLISH",
      "Price_Side_vs_D1_Range": "discount",
      "Alignment": "full conflict",
      "Liquidity_Condition": "external liquidity taken",
      "Sweep_Quality": "sweep + close back inside range",
      "Liquidity_Side": "buy-side",
      "Liquidity_Tier": "major",
      "Liquidity_Reference_Type": "swing high",
      "Rejection_Quality": "strong rejection",
      "Follow_Through": "clean follow-through",
      "Both_Sides_Taken_Recently": true,
      "Displacement_Quality": "weak / no displacement",
      "MSS_BOS": "partial shift",
      "Array_Quality": "weak",
      "Session_Quality": "acceptable but not ideal",
      "RS_RW_Alignment": "mixed",
      "SMT_Hint": "none",
      "Pivot_Regime": "daily: bullish above pivot | weekly: bearish below pivot",
      "Pivot_Zone_Fit": "price in buy zone",
      "Pivot_Confluence": "daily only",
      "Pivot_Conflict": "mild pivot conflict",
      "Pivot_Stretch": "not stretched",
      "Technical_Score_0_4": 0.85,
      "Legacy_Confidence_Score": 0.85,
      "Legacy_Confidence_Band": "medium",
      "Confidence_Score": 0.24,
      "Confidence_Band": "low",
      "Technical_Quality_Score_10": 3.6,
      "Execution_Realism_Score_10": 10.0,
      "Calibrated_Confidence_Score_10": 2.4,
      "Selection_Score": -11.0097,
      "Final_Rank_Score": -11.0644,
      "Data_Quality": "good",
      "Entry_Label": "D-tier avoid",
      "Preferred_Side": "LONG",
      "Best_Entry": 0.8028,
      "Structural_Entry": 0.8055,
      "Calibration_Entry": 0.8028,
      "Entry_Distance_ATR": 0.0,
      "SL": 0.8022,
      "TP1": 0.8036,
      "TP2": 0.8041,
      "Current_Price": 0.8026,
      "ATR_H1": 0.0007,
      "RR_TP1": 1.3333,
      "RR_TP2": 2.1667,
      "Execution_Line": "Buy-limit: 0.8028 | SL: 0.8022 | TP1: 0.8036 | TP2: 0.8041 | RR1: 1.3333 | RR2: 2.1667",
      "Execution_Source": "zone",
      "Setup_Archetype": "continuation",
      "Decision_Book": "Rejected",
      "Live_Gate_Passed": false,
      "Calibration_Gate_Passed": false,
      "Gate_Passed": false,
      "Gate_Fail_Reasons": "d_tier, weak_impulse",
      "Decision_Setup_Quality": 0.05,
      "Decision_Execution_Quality": 3.8,
      "Decision_Portfolio_Fit": 0.0,
      "Decision_Rank_Score": -12.0379,
      "Base_Ranking_Score": -11.9779,
      "Overlap_Penalty": 0.0,
      "Ranking_Score": -11.0644,
      "Calibration_Soft_Candidate": false,
      "Calibration_Candidate_Bucket": "hard_reject",
      "Soft_Candidate": false,
      "Soft_Fail_Adjustment": 0.0,
      "Continuation_Subquality": 0.41,
      "Continuation_Elite_Eligible": false,
      "Context_Quality_Score_10": 4.85,
      "Trigger_Quality_Score_10": 4.95,
      "Conflict_Penalty_Score_10": 5.7,
      "Opportunity_Score_10": 6.35,
      "Balance_Score_10": 4.94,
      "Kill_Switch_Score_10": 8.9,
      "False_Positive_Risk_Score_10": 2.9,
      "Archetype_Tax_Score_10": 3.0,
      "Survivability_Score_10": 2.57,
      "Asymmetry_Score_10": 8.9,
      "Calibration_Utility_Score_10": 7.35,
      "Radical_Confidence_Score_10": 2.4,
      "Admission_Class": "blocked",
      "Override_Reason": "kill_switch_block",
      "Shortlist_Eligibility": "blocked",
      "Admission_Binding_Status": "blocked_kill",
      "Selection_Lane": "blocked_kill",
      "Leakage_Penalty_Score": 3.0,
      "Veto_Flag": true,
      "Veto_Reasons": "kill_switch_block",
      "Selector_Profile": "v5.5_prediction_ready_selector",
      "Fragility_Reason": "hard_reject",
      "Idea_Family": "continuation|no_theme|LONG|nonusd|strong",
      "Survivor_Score": 2.4155,
      "Tournament_Pool": "radical_board",
      "Tournament_Pool_Display": "Radical board",
      "Tournament_Pool_Eligible": "radical_board",
      "Local_Pool_Score": -12.0379,
      "Tournament_Finalist_Flag": false,
      "Shortlist_Slot_Name": "",
      "Shortlist_Slot_Order": NaN,
      "Crowding_Block_Reason": "",
      "Selection_Passed_Over_For_Diversity": "",
      "Comparative_Edge_Score_10": 1.95,
      "Comparator_Floor_Score_10": 0.67,
      "Dominance_Score_10": 1.56,
      "Primary_Shortlist_Flag": false,
      "Primary_Override_Flag": false,
      "Shadow_Watchlist_Flag": false,
      "Shadow_Watchlist_Reason": "",
      "Shadow_Watchlist_Order": NaN,
      "In_Top_Shortlist": false,
      "Setup_Quality_Grade_10": 1.64,
      "Setup_Quality_Grade_100": 16.4,
      "Setup_Quality_Band": "E",
      "Prediction_Top_Strengths": "execution 10.0, asymmetry 8.9, utility 7.3",
      "Prediction_Main_Risks": "gate_pressure 16.8, kill_switch 8.9",
      "Prediction_Breakdown": "LONG continuation; strengths: execution 10.0, asymmetry 8.9, utility 7.3; risks: gate_pressure 16.8, kill_switch 8.9; admission: blocked / blocked_kill",
      "Prediction_Score_Version": "v5.5_prediction_quality_v2",
      "Prediction_Uses_Only_Contemporaneous_Inputs": true,
      "Prediction_Forbidden_Field_Leak": false,
      "Prediction_Input_Fingerprint": "b95759d3e3d7eda8",
      "Prediction_Integrity_Status": "clean_contemporaneous_only",
      "Prediction_Rank": 12
    },
    {
      "Snapshot_Date": "2026-06-29",
      "Prediction_Reference_Timestamp": "2026-06-29 16:31:25",
      "Market_Reference_Timestamp": "1970-01-01 00:00:00.000000698",
      "Instrument": "USDCHF",
      "status": "OK",
      "Universe_Layer": "Layer 1 — Core execution universe",
      "Cluster_Tags": "CHF haven cluster, HTF aligned, USD basket, USD strength",
      "W1_Bias": "BULLISH",
      "D1_Bias": "BULLISH",
      "Price_Side_vs_D1_Range": "premium",
      "Alignment": "aligned",
      "Liquidity_Condition": "external liquidity taken",
      "Sweep_Quality": "clean sweep only",
      "Liquidity_Side": "sell-side",
      "Liquidity_Tier": "major",
      "Liquidity_Reference_Type": "swing low",
      "Rejection_Quality": "moderate rejection",
      "Follow_Through": "limited follow-through",
      "Both_Sides_Taken_Recently": true,
      "Displacement_Quality": "weak / no displacement",
      "MSS_BOS": "partial shift",
      "Array_Quality": "weak",
      "Session_Quality": "acceptable but not ideal",
      "RS_RW_Alignment": "mixed",
      "SMT_Hint": "none",
      "Pivot_Regime": "daily: bearish below pivot | weekly: bearish below pivot",
      "Pivot_Zone_Fit": "price in buy zone",
      "Pivot_Confluence": "daily only",
      "Pivot_Conflict": "strong pivot conflict",
      "Pivot_Stretch": "not stretched",
      "Technical_Score_0_4": 0.55,
      "Legacy_Confidence_Score": 0.6,
      "Legacy_Confidence_Band": "low",
      "Confidence_Score": 0.244,
      "Confidence_Band": "low",
      "Technical_Quality_Score_10": 4.8,
      "Execution_Realism_Score_10": 10.0,
      "Calibrated_Confidence_Score_10": 2.44,
      "Selection_Score": -10.9895,
      "Final_Rank_Score": -11.0389,
      "Data_Quality": "good",
      "Entry_Label": "D-tier avoid",
      "Preferred_Side": "LONG",
      "Best_Entry": 0.8081,
      "Structural_Entry": 0.8081,
      "Calibration_Entry": 0.8081,
      "Entry_Distance_ATR": 0.04,
      "SL": 0.8071,
      "TP1": 0.8093,
      "TP2": 0.8103,
      "Current_Price": 0.8082,
      "ATR_H1": 0.0008,
      "RR_TP1": 1.2,
      "RR_TP2": 2.2,
      "Execution_Line": "Buy-limit: 0.8081 | SL: 0.8071 | TP1: 0.8093 | TP2: 0.8103 | RR1: 1.2 | RR2: 2.2",
      "Execution_Source": "fallback",
      "Setup_Archetype": "continuation",
      "Decision_Book": "B-book",
      "Live_Gate_Passed": false,
      "Calibration_Gate_Passed": true,
      "Gate_Passed": true,
      "Gate_Fail_Reasons": "d_tier, weak_impulse",
      "Decision_Setup_Quality": 1.2,
      "Decision_Execution_Quality": 3.8,
      "Decision_Portfolio_Fit": 0.0,
      "Decision_Rank_Score": -12.5617,
      "Base_Ranking_Score": -12.5017,
      "Overlap_Penalty": 0.0,
      "Ranking_Score": -11.0389,
      "Calibration_Soft_Candidate": true,
      "Calibration_Candidate_Bucket": "hard_pass",
      "Soft_Candidate": true,
      "Soft_Fail_Adjustment": -0.45,
      "Continuation_Subquality": 0.01,
      "Continuation_Elite_Eligible": false,
      "Context_Quality_Score_10": 5.95,
      "Trigger_Quality_Score_10": 4.45,
      "Conflict_Penalty_Score_10": 4.9,
      "Opportunity_Score_10": 6.35,
      "Balance_Score_10": 4.4,
      "Kill_Switch_Score_10": 8.5,
      "False_Positive_Risk_Score_10": 5.4,
      "Archetype_Tax_Score_10": 3.4,
      "Survivability_Score_10": 3.19,
      "Asymmetry_Score_10": 7.8,
      "Calibration_Utility_Score_10": 6.9,
      "Radical_Confidence_Score_10": 2.44,
      "Admission_Class": "blocked",
      "Override_Reason": "kill_switch_block",
      "Shortlist_Eligibility": "blocked",
      "Admission_Binding_Status": "blocked_kill",
      "Selection_Lane": "blocked_kill",
      "Leakage_Penalty_Score": 3.0,
      "Veto_Flag": true,
      "Veto_Reasons": "kill_switch_block",
      "Selector_Profile": "v5.5_prediction_ready_selector",
      "Fragility_Reason": "bbook_plus_fail",
      "Idea_Family": "continuation|no_theme|LONG|nonusd|normal",
      "Survivor_Score": 2.1035,
      "Tournament_Pool": "radical_board",
      "Tournament_Pool_Display": "Radical board",
      "Tournament_Pool_Eligible": "radical_board",
      "Local_Pool_Score": -12.5617,
      "Tournament_Finalist_Flag": false,
      "Shortlist_Slot_Name": "",
      "Shortlist_Slot_Order": NaN,
      "Crowding_Block_Reason": "",
      "Selection_Passed_Over_For_Diversity": "",
      "Comparative_Edge_Score_10": 2.96,
      "Comparator_Floor_Score_10": 1.33,
      "Dominance_Score_10": 2.47,
      "Primary_Shortlist_Flag": false,
      "Primary_Override_Flag": false,
      "Shadow_Watchlist_Flag": false,
      "Shadow_Watchlist_Reason": "",
      "Shadow_Watchlist_Order": NaN,
      "In_Top_Shortlist": false,
      "Setup_Quality_Grade_10": 1.39,
      "Setup_Quality_Grade_100": 13.9,
      "Setup_Quality_Band": "E",
      "Prediction_Top_Strengths": "execution 10.0, asymmetry 7.8, utility 6.9",
      "Prediction_Main_Risks": "gate_pressure 16.8, kill_switch 8.5",
      "Prediction_Breakdown": "LONG continuation; strengths: execution 10.0, asymmetry 7.8, utility 6.9; risks: gate_pressure 16.8, kill_switch 8.5; admission: blocked / blocked_kill",
      "Prediction_Score_Version": "v5.5_prediction_quality_v2",
      "Prediction_Uses_Only_Contemporaneous_Inputs": true,
      "Prediction_Forbidden_Field_Leak": false,
      "Prediction_Input_Fingerprint": "e1383c639c2e501c",
      "Prediction_Integrity_Status": "clean_contemporaneous_only",
      "Prediction_Rank": 13
    },
    {
      "Snapshot_Date": "2026-06-29",
      "Prediction_Reference_Timestamp": "2026-06-29 16:31:25",
      "Market_Reference_Timestamp": "1970-01-01 00:00:00.000000698",
      "Instrument": "EURUSD",
      "status": "OK",
      "Universe_Layer": "Layer 1 — Core execution universe",
      "Cluster_Tags": "HTF conflict, USD basket",
      "W1_Bias": "BEARISH",
      "D1_Bias": "BULLISH",
      "Price_Side_vs_D1_Range": "discount",
      "Alignment": "full conflict",
      "Liquidity_Condition": "external liquidity taken",
      "Sweep_Quality": "clean sweep only",
      "Liquidity_Side": "buy-side",
      "Liquidity_Tier": "minor",
      "Liquidity_Reference_Type": "swing high",
      "Rejection_Quality": "weak/no rejection",
      "Follow_Through": "limited follow-through",
      "Both_Sides_Taken_Recently": true,
      "Displacement_Quality": "moderate displacement",
      "MSS_BOS": "partial shift",
      "Array_Quality": "strong",
      "Session_Quality": "acceptable but not ideal",
      "RS_RW_Alignment": "clear alignment",
      "SMT_Hint": "none",
      "Pivot_Regime": "daily: bullish above pivot | weekly: bullish above pivot",
      "Pivot_Zone_Fit": "price in neutral zone",
      "Pivot_Confluence": "mixed confluence",
      "Pivot_Conflict": "no meaningful pivot conflict",
      "Pivot_Stretch": "moderately stretched",
      "Technical_Score_0_4": 2.05,
      "Legacy_Confidence_Score": 0.75,
      "Legacy_Confidence_Band": "medium",
      "Confidence_Score": 0.176,
      "Confidence_Band": "low",
      "Technical_Quality_Score_10": 4.3,
      "Execution_Realism_Score_10": 10.0,
      "Calibrated_Confidence_Score_10": 1.76,
      "Selection_Score": -10.1996,
      "Final_Rank_Score": -10.2543,
      "Data_Quality": "good",
      "Entry_Label": "B-tier reactive setup",
      "Preferred_Side": "LONG",
      "Best_Entry": 1.1423,
      "Structural_Entry": 1.1387,
      "Calibration_Entry": 1.1423,
      "Entry_Distance_ATR": 0.087,
      "SL": 1.1415,
      "TP1": 1.1434,
      "TP2": 1.1443,
      "Current_Price": 1.1423,
      "ATR_H1": 0.0011,
      "RR_TP1": 1.375,
      "RR_TP2": 2.5,
      "Execution_Line": "Buy-limit: 1.1423 | SL: 1.1415 | TP1: 1.1434 | TP2: 1.1443 | RR1: 1.375 | RR2: 2.5",
      "Execution_Source": "zone",
      "Setup_Archetype": "continuation",
      "Decision_Book": "A-book",
      "Live_Gate_Passed": false,
      "Calibration_Gate_Passed": true,
      "Gate_Passed": true,
      "Gate_Fail_Reasons": "full_conflict",
      "Decision_Setup_Quality": 1.3,
      "Decision_Execution_Quality": 3.8,
      "Decision_Portfolio_Fit": 0.0,
      "Decision_Rank_Score": -11.5577,
      "Base_Ranking_Score": -11.4977,
      "Overlap_Penalty": 0.0,
      "Ranking_Score": -10.2543,
      "Calibration_Soft_Candidate": false,
      "Calibration_Candidate_Bucket": "hard_pass",
      "Soft_Candidate": false,
      "Soft_Fail_Adjustment": 0.0,
      "Continuation_Subquality": -0.05,
      "Continuation_Elite_Eligible": false,
      "Context_Quality_Score_10": 4.8,
      "Trigger_Quality_Score_10": 5.2,
      "Conflict_Penalty_Score_10": 3.0,
      "Opportunity_Score_10": 2.35,
      "Balance_Score_10": 4.87,
      "Kill_Switch_Score_10": 4.2,
      "False_Positive_Risk_Score_10": 5.4,
      "Archetype_Tax_Score_10": 3.4,
      "Survivability_Score_10": 4.04,
      "Asymmetry_Score_10": 7.2,
      "Calibration_Utility_Score_10": 2.2,
      "Radical_Confidence_Score_10": 1.76,
      "Admission_Class": "blocked",
      "Override_Reason": "hard_reject",
      "Shortlist_Eligibility": "blocked",
      "Admission_Binding_Status": "blocked_hard",
      "Selection_Lane": "blocked_hard",
      "Leakage_Penalty_Score": 3.0,
      "Veto_Flag": false,
      "Veto_Reasons": "",
      "Selector_Profile": "v5.5_prediction_ready_selector",
      "Fragility_Reason": "weak_continuation_subquality",
      "Idea_Family": "continuation|no_theme|LONG|nonusd|normal",
      "Survivor_Score": 1.716,
      "Tournament_Pool": "radical_board",
      "Tournament_Pool_Display": "Radical board",
      "Tournament_Pool_Eligible": "radical_board",
      "Local_Pool_Score": -11.5577,
      "Tournament_Finalist_Flag": false,
      "Shortlist_Slot_Name": "",
      "Shortlist_Slot_Order": NaN,
      "Crowding_Block_Reason": "",
      "Selection_Passed_Over_For_Diversity": "",
      "Comparative_Edge_Score_10": 2.67,
      "Comparator_Floor_Score_10": 0.67,
      "Dominance_Score_10": 2.07,
      "Primary_Shortlist_Flag": false,
      "Primary_Override_Flag": false,
      "Shadow_Watchlist_Flag": false,
      "Shadow_Watchlist_Reason": "",
      "Shadow_Watchlist_Order": NaN,
      "In_Top_Shortlist": false,
      "Setup_Quality_Grade_10": 1.14,
      "Setup_Quality_Grade_100": 11.4,
      "Setup_Quality_Band": "E",
      "Prediction_Top_Strengths": "execution 10.0, asymmetry 7.2, trigger 5.2",
      "Prediction_Main_Risks": "gate_pressure 17.7, false_positive_risk 5.4",
      "Prediction_Breakdown": "LONG continuation; strengths: execution 10.0, asymmetry 7.2, trigger 5.2; risks: gate_pressure 17.7, false_positive_risk 5.4; admission: blocked / blocked_hard",
      "Prediction_Score_Version": "v5.5_prediction_quality_v2",
      "Prediction_Uses_Only_Contemporaneous_Inputs": true,
      "Prediction_Forbidden_Field_Leak": false,
      "Prediction_Input_Fingerprint": "6b7753ad5d8e6157",
      "Prediction_Integrity_Status": "clean_contemporaneous_only",
      "Prediction_Rank": 14
    },
    {
      "Snapshot_Date": "2026-06-29",
      "Prediction_Reference_Timestamp": "2026-06-29 16:31:25",
      "Market_Reference_Timestamp": "1970-01-01 00:00:00.000000698",
      "Instrument": "EURJPY",
      "status": "OK",
      "Universe_Layer": "Layer 1 — Core execution universe",
      "Cluster_Tags": "EUR relative-value cluster, HTF conflict, JPY cluster",
      "W1_Bias": "BEARISH",
      "D1_Bias": "BULLISH",
      "Price_Side_vs_D1_Range": "premium",
      "Alignment": "full conflict",
      "Liquidity_Condition": "external liquidity taken",
      "Sweep_Quality": "clean sweep only",
      "Liquidity_Side": "buy-side",
      "Liquidity_Tier": "minor",
      "Liquidity_Reference_Type": "swing high",
      "Rejection_Quality": "weak/no rejection",
      "Follow_Through": "limited follow-through",
      "Both_Sides_Taken_Recently": true,
      "Displacement_Quality": "moderate displacement",
      "MSS_BOS": "partial shift",
      "Array_Quality": "good",
      "Session_Quality": "acceptable but not ideal",
      "RS_RW_Alignment": "clear alignment",
      "SMT_Hint": "none",
      "Pivot_Regime": "daily: bullish above pivot | weekly: bullish above pivot",
      "Pivot_Zone_Fit": "price in neutral zone",
      "Pivot_Confluence": "mixed confluence",
      "Pivot_Conflict": "no meaningful pivot conflict",
      "Pivot_Stretch": "not stretched",
      "Technical_Score_0_4": 1.65,
      "Legacy_Confidence_Score": 0.75,
      "Legacy_Confidence_Band": "medium",
      "Confidence_Score": 0.176,
      "Confidence_Band": "low",
      "Technical_Quality_Score_10": 4.3,
      "Execution_Realism_Score_10": 10.0,
      "Calibrated_Confidence_Score_10": 1.76,
      "Selection_Score": -10.1996,
      "Final_Rank_Score": -10.2543,
      "Data_Quality": "good",
      "Entry_Label": "B-tier reactive setup",
      "Preferred_Side": "LONG",
      "Best_Entry": 185.006,
      "Structural_Entry": 183.691,
      "Calibration_Entry": 185.006,
      "Entry_Distance_ATR": 0.05,
      "SL": 184.863,
      "TP1": 185.18,
      "TP2": 185.316,
      "Current_Price": 184.968,
      "ATR_H1": 0.181,
      "RR_TP1": 1.2168,
      "RR_TP2": 2.1678,
      "Execution_Line": "Buy-limit: 185.006 | SL: 184.863 | TP1: 185.18 | TP2: 185.316 | RR1: 1.2168 | RR2: 2.1678",
      "Execution_Source": "zone",
      "Setup_Archetype": "continuation",
      "Decision_Book": "A-book",
      "Live_Gate_Passed": false,
      "Calibration_Gate_Passed": true,
      "Gate_Passed": true,
      "Gate_Fail_Reasons": "full_conflict",
      "Decision_Setup_Quality": 1.3,
      "Decision_Execution_Quality": 3.8,
      "Decision_Portfolio_Fit": 0.0,
      "Decision_Rank_Score": -11.5577,
      "Base_Ranking_Score": -11.4977,
      "Overlap_Penalty": 0.0,
      "Ranking_Score": -10.2543,
      "Calibration_Soft_Candidate": false,
      "Calibration_Candidate_Bucket": "hard_pass",
      "Soft_Candidate": false,
      "Soft_Fail_Adjustment": 0.0,
      "Continuation_Subquality": 0.01,
      "Continuation_Elite_Eligible": false,
      "Context_Quality_Score_10": 4.8,
      "Trigger_Quality_Score_10": 5.2,
      "Conflict_Penalty_Score_10": 3.0,
      "Opportunity_Score_10": 2.35,
      "Balance_Score_10": 4.87,
      "Kill_Switch_Score_10": 4.2,
      "False_Positive_Risk_Score_10": 5.4,
      "Archetype_Tax_Score_10": 3.4,
      "Survivability_Score_10": 4.04,
      "Asymmetry_Score_10": 7.2,
      "Calibration_Utility_Score_10": 2.2,
      "Radical_Confidence_Score_10": 1.76,
      "Admission_Class": "blocked",
      "Override_Reason": "hard_reject",
      "Shortlist_Eligibility": "blocked",
      "Admission_Binding_Status": "blocked_hard",
      "Selection_Lane": "blocked_hard",
      "Leakage_Penalty_Score": 3.0,
      "Veto_Flag": false,
      "Veto_Reasons": "",
      "Selector_Profile": "v5.5_prediction_ready_selector",
      "Fragility_Reason": "",
      "Idea_Family": "continuation|no_theme|LONG|nonusd|normal",
      "Survivor_Score": 1.716,
      "Tournament_Pool": "radical_board",
      "Tournament_Pool_Display": "Radical board",
      "Tournament_Pool_Eligible": "radical_board",
      "Local_Pool_Score": -11.5577,
      "Tournament_Finalist_Flag": false,
      "Shortlist_Slot_Name": "",
      "Shortlist_Slot_Order": NaN,
      "Crowding_Block_Reason": "",
      "Selection_Passed_Over_For_Diversity": "",
      "Comparative_Edge_Score_10": 2.67,
      "Comparator_Floor_Score_10": 0.67,
      "Dominance_Score_10": 2.07,
      "Primary_Shortlist_Flag": false,
      "Primary_Override_Flag": false,
      "Shadow_Watchlist_Flag": false,
      "Shadow_Watchlist_Reason": "",
      "Shadow_Watchlist_Order": NaN,
      "In_Top_Shortlist": false,
      "Setup_Quality_Grade_10": 1.14,
      "Setup_Quality_Grade_100": 11.4,
      "Setup_Quality_Band": "E",
      "Prediction_Top_Strengths": "execution 10.0, asymmetry 7.2, trigger 5.2",
      "Prediction_Main_Risks": "gate_pressure 17.7, false_positive_risk 5.4",
      "Prediction_Breakdown": "LONG continuation; strengths: execution 10.0, asymmetry 7.2, trigger 5.2; risks: gate_pressure 17.7, false_positive_risk 5.4; admission: blocked / blocked_hard",
      "Prediction_Score_Version": "v5.5_prediction_quality_v2",
      "Prediction_Uses_Only_Contemporaneous_Inputs": true,
      "Prediction_Forbidden_Field_Leak": false,
      "Prediction_Input_Fingerprint": "4c55af2a652f992b",
      "Prediction_Integrity_Status": "clean_contemporaneous_only",
      "Prediction_Rank": 15
    },
    {
      "Snapshot_Date": "2026-06-29",
      "Prediction_Reference_Timestamp": "2026-06-29 16:31:25",
      "Market_Reference_Timestamp": "1970-01-01 00:00:00.000000698",
      "Instrument": "AUDCHF",
      "status": "OK",
      "Universe_Layer": "Layer 2 — Relative-value crosses",
      "Cluster_Tags": "CHF haven cluster, HTF conflict, commodity bloc",
      "W1_Bias": "BEARISH",
      "D1_Bias": "BULLISH",
      "Price_Side_vs_D1_Range": "discount",
      "Alignment": "full conflict",
      "Liquidity_Condition": "external liquidity taken",
      "Sweep_Quality": "clean sweep only",
      "Liquidity_Side": "sell-side",
      "Liquidity_Tier": "minor",
      "Liquidity_Reference_Type": "swing low",
      "Rejection_Quality": "moderate rejection",
      "Follow_Through": "limited follow-through",
      "Both_Sides_Taken_Recently": true,
      "Displacement_Quality": "moderate displacement",
      "MSS_BOS": "partial shift",
      "Array_Quality": "weak",
      "Session_Quality": "acceptable but not ideal",
      "RS_RW_Alignment": "no clear alignment",
      "SMT_Hint": "none",
      "Pivot_Regime": "daily: bearish below pivot | weekly: bearish below pivot",
      "Pivot_Zone_Fit": "price in buy zone",
      "Pivot_Confluence": "daily only",
      "Pivot_Conflict": "strong pivot conflict",
      "Pivot_Stretch": "not stretched",
      "Technical_Score_0_4": 0.35,
      "Legacy_Confidence_Score": 0.6,
      "Legacy_Confidence_Band": "low",
      "Confidence_Score": 0.0,
      "Confidence_Band": "low",
      "Technical_Quality_Score_10": 3.5,
      "Execution_Realism_Score_10": 10.0,
      "Calibrated_Confidence_Score_10": 0.0,
      "Selection_Score": -12.5679,
      "Final_Rank_Score": -12.6239,
      "Data_Quality": "good",
      "Entry_Label": "D-tier avoid",
      "Preferred_Side": "LONG",
      "Best_Entry": 0.5564,
      "Structural_Entry": 0.5601,
      "Calibration_Entry": 0.5564,
      "Entry_Distance_ATR": 0.059,
      "SL": 0.5559,
      "TP1": 0.557,
      "TP2": 0.5575,
      "Current_Price": 0.5564,
      "ATR_H1": 0.0005,
      "RR_TP1": 1.2,
      "RR_TP2": 2.2,
      "Execution_Line": "Buy-limit: 0.5564 | SL: 0.5559 | TP1: 0.557 | TP2: 0.5575 | RR1: 1.2 | RR2: 2.2",
      "Execution_Source": "zone",
      "Setup_Archetype": "continuation",
      "Decision_Book": "Rejected",
      "Live_Gate_Passed": false,
      "Calibration_Gate_Passed": false,
      "Gate_Passed": false,
      "Gate_Fail_Reasons": "d_tier, stacked_conflict",
      "Decision_Setup_Quality": 0.15,
      "Decision_Execution_Quality": 3.8,
      "Decision_Portfolio_Fit": 0.0,
      "Decision_Rank_Score": -13.3859,
      "Base_Ranking_Score": -13.3259,
      "Overlap_Penalty": 0.0,
      "Ranking_Score": -12.6239,
      "Calibration_Soft_Candidate": false,
      "Calibration_Candidate_Bucket": "hard_reject",
      "Soft_Candidate": false,
      "Soft_Fail_Adjustment": 0.0,
      "Continuation_Subquality": -0.15,
      "Continuation_Elite_Eligible": false,
      "Context_Quality_Score_10": 3.25,
      "Trigger_Quality_Score_10": 6.0,
      "Conflict_Penalty_Score_10": 9.3,
      "Opportunity_Score_10": 5.9,
      "Balance_Score_10": 2.78,
      "Kill_Switch_Score_10": 9.7,
      "False_Positive_Risk_Score_10": 3.8,
      "Archetype_Tax_Score_10": 3.4,
      "Survivability_Score_10": 0.54,
      "Asymmetry_Score_10": 7.8,
      "Calibration_Utility_Score_10": 7.35,
      "Radical_Confidence_Score_10": 0.0,
      "Admission_Class": "blocked",
      "Override_Reason": "kill_switch_block",
      "Shortlist_Eligibility": "blocked",
      "Admission_Binding_Status": "blocked_kill",
      "Selection_Lane": "blocked_kill",
      "Leakage_Penalty_Score": 3.0,
      "Veto_Flag": true,
      "Veto_Reasons": "kill_switch_block",
      "Selector_Profile": "v5.5_prediction_ready_selector",
      "Fragility_Reason": "hard_reject",
      "Idea_Family": "continuation|no_theme|LONG|nonusd|normal",
      "Survivor_Score": 0.871,
      "Tournament_Pool": "radical_board",
      "Tournament_Pool_Display": "Radical board",
      "Tournament_Pool_Eligible": "radical_board",
      "Local_Pool_Score": -13.3859,
      "Tournament_Finalist_Flag": false,
      "Shortlist_Slot_Name": "",
      "Shortlist_Slot_Order": NaN,
      "Crowding_Block_Reason": "",
      "Selection_Passed_Over_For_Diversity": "",
      "Comparative_Edge_Score_10": 1.53,
      "Comparator_Floor_Score_10": 0.5,
      "Dominance_Score_10": 1.22,
      "Primary_Shortlist_Flag": false,
      "Primary_Override_Flag": false,
      "Shadow_Watchlist_Flag": false,
      "Shadow_Watchlist_Reason": "",
      "Shadow_Watchlist_Order": NaN,
      "In_Top_Shortlist": false,
      "Setup_Quality_Grade_10": 0.11,
      "Setup_Quality_Grade_100": 1.1,
      "Setup_Quality_Band": "E",
      "Prediction_Top_Strengths": "execution 10.0, asymmetry 7.8, utility 7.3",
      "Prediction_Main_Risks": "gate_pressure 16.8, kill_switch 9.7",
      "Prediction_Breakdown": "LONG continuation; strengths: execution 10.0, asymmetry 7.8, utility 7.3; risks: gate_pressure 16.8, kill_switch 9.7; admission: blocked / blocked_kill",
      "Prediction_Score_Version": "v5.5_prediction_quality_v2",
      "Prediction_Uses_Only_Contemporaneous_Inputs": true,
      "Prediction_Forbidden_Field_Leak": false,
      "Prediction_Input_Fingerprint": "4c6b32d660f30d93",
      "Prediction_Integrity_Status": "clean_contemporaneous_only",
      "Prediction_Rank": 16
    }
  ]
}