{
  "snapshot_meta": {
    "prediction_enabled": true,
    "prediction_score_version": "v5.5_prediction_quality_v2",
    "prediction_reference_timestamp": "2026-05-20 09:53:33",
    "snapshot_date": "2026-05-20",
    "prediction_input_fields": [
      "Instrument",
      "Preferred_Side",
      "Setup_Archetype",
      "Decision_Book",
      "W1_Bias",
      "D1_Bias",
      "Alignment",
      "Price_Side_vs_D1_Range",
      "Liquidity_Condition",
      "Sweep_Quality",
      "Liquidity_Side",
      "Liquidity_Tier",
      "Liquidity_Reference_Type",
      "Rejection_Quality",
      "Follow_Through",
      "Both_Sides_Taken_Recently",
      "Displacement_Quality",
      "MSS_BOS",
      "Pivot_Regime",
      "Pivot_Zone_Fit",
      "Pivot_Conflict",
      "Pivot_Stretch",
      "Data_Quality",
      "Confidence_Score",
      "Confidence_Band",
      "Technical_Quality_Score_10",
      "Execution_Realism_Score_10",
      "Calibrated_Confidence_Score_10",
      "Context_Quality_Score_10",
      "Trigger_Quality_Score_10",
      "Conflict_Penalty_Score_10",
      "Balance_Score_10",
      "Opportunity_Score_10",
      "Kill_Switch_Score_10",
      "False_Positive_Risk_Score_10",
      "Archetype_Tax_Score_10",
      "Survivability_Score_10",
      "Asymmetry_Score_10",
      "Calibration_Utility_Score_10",
      "Comparative_Edge_Score_10",
      "Comparator_Floor_Score_10",
      "Dominance_Score_10",
      "Selection_Score",
      "Final_Rank_Score",
      "Admission_Class",
      "Override_Reason",
      "Shortlist_Eligibility",
      "Admission_Binding_Status",
      "Selection_Lane",
      "Primary_Shortlist_Flag",
      "Shadow_Watchlist_Flag",
      "Gate_Passed",
      "Gate_Fail_Reasons",
      "Veto_Flag",
      "Veto_Reasons",
      "Current_Price",
      "Best_Entry",
      "SL",
      "TP1",
      "TP2",
      "RR_TP1",
      "RR_TP2",
      "Entry_Distance_ATR"
    ],
    "prediction_forbidden_fields": [
      "Verifier_Triggered",
      "Verifier_TP1_Hit",
      "Verifier_TP2_Hit",
      "Verifier_SL_Hit",
      "Verifier_First_Event",
      "Verifier_Outcome_Label",
      "Verifier_MFE",
      "Verifier_MAE",
      "Verifier_R_Multiple",
      "Verifier_Weighted_Return_R",
      "Verifier48_Triggered",
      "Verifier48_TP1_Hit",
      "Verifier48_TP2_Hit",
      "Verifier48_SL_Hit",
      "Verifier48_First_Event",
      "Verifier48_Outcome_Label",
      "Verifier48_MFE",
      "Verifier48_MAE",
      "Verifier48_R_Multiple",
      "Verifier48_Weighted_Return_R",
      "Verifier72_Triggered",
      "Verifier72_TP1_Hit",
      "Verifier72_TP2_Hit",
      "Verifier72_SL_Hit",
      "Verifier72_First_Event",
      "Verifier72_Outcome_Label",
      "Verifier72_MFE",
      "Verifier72_MAE",
      "Verifier72_R_Multiple",
      "Verifier72_Weighted_Return_R"
    ],
    "prediction_top_n": 8
  },
  "predictions": [
    {
      "Snapshot_Date": "2026-05-20",
      "Prediction_Reference_Timestamp": "2026-05-20 09:53:33",
      "Market_Reference_Timestamp": "1970-01-01 00:00:00.000000698",
      "Instrument": "NZDCAD",
      "status": "OK",
      "Universe_Layer": "Layer 2 — Relative-value crosses",
      "Cluster_Tags": "HTF aligned, commodity bloc",
      "W1_Bias": "BEARISH",
      "D1_Bias": "BEARISH",
      "Price_Side_vs_D1_Range": "discount",
      "Alignment": "aligned",
      "Liquidity_Condition": "external liquidity taken",
      "Sweep_Quality": "sweep + close back inside range",
      "Liquidity_Side": "sell-side",
      "Liquidity_Tier": "major",
      "Liquidity_Reference_Type": "swing low",
      "Rejection_Quality": "strong rejection",
      "Follow_Through": "clean follow-through",
      "Both_Sides_Taken_Recently": false,
      "Displacement_Quality": "strong displacement",
      "MSS_BOS": "partial shift",
      "Array_Quality": "good",
      "Session_Quality": "acceptable but not ideal",
      "RS_RW_Alignment": "no clear alignment",
      "SMT_Hint": "none",
      "Pivot_Regime": "daily: bullish above pivot | weekly: bearish below pivot",
      "Pivot_Zone_Fit": "price in sell zone",
      "Pivot_Confluence": "daily only",
      "Pivot_Conflict": "mild pivot conflict",
      "Pivot_Stretch": "not stretched",
      "Technical_Score_0_4": 2.3,
      "Legacy_Confidence_Score": 0.95,
      "Legacy_Confidence_Band": "high",
      "Confidence_Score": 0.532,
      "Confidence_Band": "low",
      "Technical_Quality_Score_10": 8.0,
      "Execution_Realism_Score_10": 10.0,
      "Calibrated_Confidence_Score_10": 5.32,
      "Selection_Score": -7.2019,
      "Final_Rank_Score": -7.2513,
      "Data_Quality": "good",
      "Entry_Label": "B-tier reactive setup",
      "Preferred_Side": "SHORT",
      "Best_Entry": 0.8043,
      "Structural_Entry": 0.8105,
      "Calibration_Entry": 0.8043,
      "Entry_Distance_ATR": 0.085,
      "SL": 0.8049,
      "TP1": 0.8035,
      "TP2": 0.8029,
      "Current_Price": 0.8043,
      "ATR_H1": 0.0011,
      "RR_TP1": 1.3333,
      "RR_TP2": 2.3333,
      "Execution_Line": "Sell-limit: 0.8043 | SL: 0.8049 | TP1: 0.8035 | TP2: 0.8029 | RR1: 1.3333 | RR2: 2.3333",
      "Execution_Source": "zone",
      "Setup_Archetype": "continuation",
      "Decision_Book": "A-book",
      "Live_Gate_Passed": true,
      "Calibration_Gate_Passed": true,
      "Gate_Passed": true,
      "Gate_Fail_Reasons": "",
      "Decision_Setup_Quality": 3.95,
      "Decision_Execution_Quality": 3.8,
      "Decision_Portfolio_Fit": 0.0,
      "Decision_Rank_Score": -9.2346,
      "Base_Ranking_Score": -9.1746,
      "Overlap_Penalty": 0.0,
      "Ranking_Score": -7.2513,
      "Calibration_Soft_Candidate": false,
      "Calibration_Candidate_Bucket": "hard_pass",
      "Soft_Candidate": false,
      "Soft_Fail_Adjustment": 0.0,
      "Continuation_Subquality": 0.49,
      "Continuation_Elite_Eligible": true,
      "Context_Quality_Score_10": 7.25,
      "Trigger_Quality_Score_10": 7.15,
      "Conflict_Penalty_Score_10": 0.0,
      "Opportunity_Score_10": 5.0,
      "Balance_Score_10": 7.44,
      "Kill_Switch_Score_10": 0.0,
      "False_Positive_Risk_Score_10": 5.8,
      "Archetype_Tax_Score_10": 3.0,
      "Survivability_Score_10": 7.58,
      "Asymmetry_Score_10": 8.9,
      "Calibration_Utility_Score_10": 4.4,
      "Radical_Confidence_Score_10": 5.32,
      "Admission_Class": "blocked",
      "Override_Reason": "gatepass_primary_block",
      "Shortlist_Eligibility": "blocked",
      "Admission_Binding_Status": "blocked_gatepass",
      "Selection_Lane": "blocked_gatepass",
      "Leakage_Penalty_Score": 3.0,
      "Veto_Flag": false,
      "Veto_Reasons": "",
      "Selector_Profile": "v5.5_prediction_ready_selector",
      "Fragility_Reason": "",
      "Idea_Family": "continuation|no_theme|SHORT|nonusd|strong",
      "Survivor_Score": 4.357,
      "Tournament_Pool": "radical_board",
      "Tournament_Pool_Display": "Radical board",
      "Tournament_Pool_Eligible": "radical_board",
      "Local_Pool_Score": -9.2346,
      "Tournament_Finalist_Flag": false,
      "Shortlist_Slot_Name": "",
      "Shortlist_Slot_Order": NaN,
      "Crowding_Block_Reason": "",
      "Selection_Passed_Over_For_Diversity": "",
      "Comparative_Edge_Score_10": 3.97,
      "Comparator_Floor_Score_10": 1.33,
      "Dominance_Score_10": 3.18,
      "Primary_Shortlist_Flag": false,
      "Primary_Override_Flag": false,
      "Shadow_Watchlist_Flag": false,
      "Shadow_Watchlist_Reason": "",
      "Shadow_Watchlist_Order": NaN,
      "In_Top_Shortlist": false,
      "Setup_Quality_Grade_10": 5.27,
      "Setup_Quality_Grade_100": 52.7,
      "Setup_Quality_Band": "C",
      "Prediction_Top_Strengths": "execution 10.0, asymmetry 8.9, survivability 7.6",
      "Prediction_Main_Risks": "gate_pressure 7.7, false_positive_risk 5.8",
      "Prediction_Breakdown": "SHORT continuation; strengths: execution 10.0, asymmetry 8.9, survivability 7.6; risks: gate_pressure 7.7, false_positive_risk 5.8; admission: blocked / blocked_gatepass",
      "Prediction_Score_Version": "v5.5_prediction_quality_v2",
      "Prediction_Uses_Only_Contemporaneous_Inputs": true,
      "Prediction_Forbidden_Field_Leak": false,
      "Prediction_Input_Fingerprint": "4e4a57e1b71b4cf0",
      "Prediction_Integrity_Status": "clean_contemporaneous_only",
      "Prediction_Rank": 1
    },
    {
      "Snapshot_Date": "2026-05-20",
      "Prediction_Reference_Timestamp": "2026-05-20 09:53:33",
      "Market_Reference_Timestamp": "1970-01-01 00:00:00.000000698",
      "Instrument": "EURGBP",
      "status": "OK",
      "Universe_Layer": "Layer 1 — Core execution universe",
      "Cluster_Tags": "EUR relative-value cluster, EUR weakness, HTF conflict",
      "W1_Bias": "BULLISH",
      "D1_Bias": "BEARISH",
      "Price_Side_vs_D1_Range": "discount",
      "Alignment": "full conflict",
      "Liquidity_Condition": "external liquidity taken",
      "Sweep_Quality": "sweep + close back inside range",
      "Liquidity_Side": "sell-side",
      "Liquidity_Tier": "major",
      "Liquidity_Reference_Type": "swing low",
      "Rejection_Quality": "strong rejection",
      "Follow_Through": "clean follow-through",
      "Both_Sides_Taken_Recently": true,
      "Displacement_Quality": "weak / no displacement",
      "MSS_BOS": "partial shift",
      "Array_Quality": "good",
      "Session_Quality": "acceptable but not ideal",
      "RS_RW_Alignment": "clear alignment",
      "SMT_Hint": "none",
      "Pivot_Regime": "daily: bearish below pivot | weekly: bearish below pivot",
      "Pivot_Zone_Fit": "price in neutral zone",
      "Pivot_Confluence": "mixed confluence",
      "Pivot_Conflict": "no meaningful pivot conflict",
      "Pivot_Stretch": "not stretched",
      "Technical_Score_0_4": 1.55,
      "Legacy_Confidence_Score": 0.85,
      "Legacy_Confidence_Band": "medium",
      "Confidence_Score": 0.499,
      "Confidence_Band": "low",
      "Technical_Quality_Score_10": 4.3,
      "Execution_Realism_Score_10": 10.0,
      "Calibrated_Confidence_Score_10": 4.99,
      "Selection_Score": 2.8316,
      "Final_Rank_Score": 2.7983,
      "Data_Quality": "good",
      "Entry_Label": "B-tier reactive setup",
      "Preferred_Side": "SHORT",
      "Best_Entry": 0.8662,
      "Structural_Entry": 0.8705,
      "Calibration_Entry": 0.8662,
      "Entry_Distance_ATR": 0.102,
      "SL": 0.8669,
      "TP1": 0.8653,
      "TP2": 0.8647,
      "Current_Price": 0.8661,
      "ATR_H1": 0.0006,
      "RR_TP1": 1.2857,
      "RR_TP2": 2.1429,
      "Execution_Line": "Sell-limit: 0.8662 | SL: 0.8669 | TP1: 0.8653 | TP2: 0.8647 | RR1: 1.2857 | RR2: 2.1429",
      "Execution_Source": "zone",
      "Setup_Archetype": "continuation",
      "Decision_Book": "Reserve",
      "Live_Gate_Passed": false,
      "Calibration_Gate_Passed": false,
      "Gate_Passed": false,
      "Gate_Fail_Reasons": "weak_impulse",
      "Decision_Setup_Quality": 1.1,
      "Decision_Execution_Quality": 3.8,
      "Decision_Portfolio_Fit": 0.0,
      "Decision_Rank_Score": -0.5901,
      "Base_Ranking_Score": -0.5301,
      "Overlap_Penalty": 0.0,
      "Ranking_Score": 2.7983,
      "Calibration_Soft_Candidate": true,
      "Calibration_Candidate_Bucket": "challenger",
      "Soft_Candidate": true,
      "Soft_Fail_Adjustment": -0.2,
      "Continuation_Subquality": 0.59,
      "Continuation_Elite_Eligible": false,
      "Context_Quality_Score_10": 5.45,
      "Trigger_Quality_Score_10": 4.95,
      "Conflict_Penalty_Score_10": 4.1,
      "Opportunity_Score_10": 7.15,
      "Balance_Score_10": 5.07,
      "Kill_Switch_Score_10": 5.0,
      "False_Positive_Risk_Score_10": 2.9,
      "Archetype_Tax_Score_10": 3.0,
      "Survivability_Score_10": 4.27,
      "Asymmetry_Score_10": 8.9,
      "Calibration_Utility_Score_10": 8.75,
      "Radical_Confidence_Score_10": 4.99,
      "Admission_Class": "eligible",
      "Override_Reason": "",
      "Shortlist_Eligibility": "primary",
      "Admission_Binding_Status": "primary_eligible",
      "Selection_Lane": "primary_not_selected",
      "Leakage_Penalty_Score": 0.0,
      "Veto_Flag": false,
      "Veto_Reasons": "",
      "Selector_Profile": "v5.5_prediction_ready_selector",
      "Fragility_Reason": "weak_setup_plus_fail",
      "Idea_Family": "continuation|no_theme|SHORT|nonusd|strong",
      "Survivor_Score": 3.8005,
      "Tournament_Pool": "radical_board",
      "Tournament_Pool_Display": "Radical board",
      "Tournament_Pool_Eligible": "radical_board",
      "Local_Pool_Score": -0.5901,
      "Tournament_Finalist_Flag": false,
      "Shortlist_Slot_Name": "",
      "Shortlist_Slot_Order": NaN,
      "Crowding_Block_Reason": "",
      "Selection_Passed_Over_For_Diversity": "",
      "Comparative_Edge_Score_10": 6.48,
      "Comparator_Floor_Score_10": 3.33,
      "Dominance_Score_10": 5.53,
      "Primary_Shortlist_Flag": false,
      "Primary_Override_Flag": false,
      "Shadow_Watchlist_Flag": false,
      "Shadow_Watchlist_Reason": "",
      "Shadow_Watchlist_Order": NaN,
      "In_Top_Shortlist": false,
      "Setup_Quality_Grade_10": 4.87,
      "Setup_Quality_Grade_100": 48.7,
      "Setup_Quality_Band": "C",
      "Prediction_Top_Strengths": "execution 10.0, asymmetry 8.9, utility 8.8",
      "Prediction_Main_Risks": "kill_switch 5.0, conflict 4.1",
      "Prediction_Breakdown": "SHORT continuation; strengths: execution 10.0, asymmetry 8.9, utility 8.8; risks: kill_switch 5.0, conflict 4.1; admission: eligible / primary_not_selected",
      "Prediction_Score_Version": "v5.5_prediction_quality_v2",
      "Prediction_Uses_Only_Contemporaneous_Inputs": true,
      "Prediction_Forbidden_Field_Leak": false,
      "Prediction_Input_Fingerprint": "d8f7e52948e30927",
      "Prediction_Integrity_Status": "clean_contemporaneous_only",
      "Prediction_Rank": 2
    },
    {
      "Snapshot_Date": "2026-05-20",
      "Prediction_Reference_Timestamp": "2026-05-20 09:53:33",
      "Market_Reference_Timestamp": "1970-01-01 00:00:00.000000698",
      "Instrument": "GBPJPY",
      "status": "OK",
      "Universe_Layer": "Layer 1 — Core execution universe",
      "Cluster_Tags": "HTF aligned, JPY cluster, risk-off short",
      "W1_Bias": "BEARISH",
      "D1_Bias": "BEARISH",
      "Price_Side_vs_D1_Range": "premium",
      "Alignment": "aligned",
      "Liquidity_Condition": "external liquidity taken",
      "Sweep_Quality": "sweep + close back inside range",
      "Liquidity_Side": "sell-side",
      "Liquidity_Tier": "minor",
      "Liquidity_Reference_Type": "swing low",
      "Rejection_Quality": "strong rejection",
      "Follow_Through": "clean follow-through",
      "Both_Sides_Taken_Recently": true,
      "Displacement_Quality": "weak / no displacement",
      "MSS_BOS": "partial shift",
      "Array_Quality": "strong",
      "Session_Quality": "acceptable but not ideal",
      "RS_RW_Alignment": "no clear alignment",
      "SMT_Hint": "none",
      "Pivot_Regime": "daily: bearish below pivot | weekly: bullish above pivot",
      "Pivot_Zone_Fit": "price in sell zone",
      "Pivot_Confluence": "daily only",
      "Pivot_Conflict": "mild pivot conflict",
      "Pivot_Stretch": "not stretched",
      "Technical_Score_0_4": 1.6,
      "Legacy_Confidence_Score": 0.85,
      "Legacy_Confidence_Band": "medium",
      "Confidence_Score": 0.553,
      "Confidence_Band": "low",
      "Technical_Quality_Score_10": 5.75,
      "Execution_Realism_Score_10": 10.0,
      "Calibrated_Confidence_Score_10": 5.53,
      "Selection_Score": -5.6683,
      "Final_Rank_Score": -5.6856,
      "Data_Quality": "good",
      "Entry_Label": "B-tier reactive setup",
      "Preferred_Side": "SHORT",
      "Best_Entry": 212.877,
      "Structural_Entry": 213.035,
      "Calibration_Entry": 212.877,
      "Entry_Distance_ATR": 0.052,
      "SL": 213.043,
      "TP1": 212.675,
      "TP2": 212.517,
      "Current_Price": 212.873,
      "ATR_H1": 0.165,
      "RR_TP1": 1.2169,
      "RR_TP2": 2.1687,
      "Execution_Line": "Sell-limit: 212.877 | SL: 213.043 | TP1: 212.675 | TP2: 212.517 | RR1: 1.2169 | RR2: 2.1687",
      "Execution_Source": "zone",
      "Setup_Archetype": "continuation",
      "Decision_Book": "B-book",
      "Live_Gate_Passed": false,
      "Calibration_Gate_Passed": true,
      "Gate_Passed": true,
      "Gate_Fail_Reasons": "weak_impulse",
      "Decision_Setup_Quality": 2.25,
      "Decision_Execution_Quality": 3.8,
      "Decision_Portfolio_Fit": 0.0,
      "Decision_Rank_Score": -9.7614,
      "Base_Ranking_Score": -9.7014,
      "Overlap_Penalty": 0.0,
      "Ranking_Score": -5.6856,
      "Calibration_Soft_Candidate": true,
      "Calibration_Candidate_Bucket": "hard_pass",
      "Soft_Candidate": true,
      "Soft_Fail_Adjustment": -0.2,
      "Continuation_Subquality": 0.31,
      "Continuation_Elite_Eligible": true,
      "Context_Quality_Score_10": 6.95,
      "Trigger_Quality_Score_10": 4.95,
      "Conflict_Penalty_Score_10": 1.1,
      "Opportunity_Score_10": 6.8,
      "Balance_Score_10": 5.07,
      "Kill_Switch_Score_10": 2.8,
      "False_Positive_Risk_Score_10": 4.5,
      "Archetype_Tax_Score_10": 3.0,
      "Survivability_Score_10": 5.63,
      "Asymmetry_Score_10": 8.9,
      "Calibration_Utility_Score_10": 6.9,
      "Radical_Confidence_Score_10": 5.53,
      "Admission_Class": "blocked",
      "Override_Reason": "gatepass_primary_block",
      "Shortlist_Eligibility": "blocked",
      "Admission_Binding_Status": "blocked_gatepass",
      "Selection_Lane": "blocked_gatepass",
      "Leakage_Penalty_Score": 3.0,
      "Veto_Flag": false,
      "Veto_Reasons": "",
      "Selector_Profile": "v5.5_prediction_ready_selector",
      "Fragility_Reason": "bbook_plus_fail",
      "Idea_Family": "continuation|no_theme|SHORT|nonusd|strong",
      "Survivor_Score": 3.9145,
      "Tournament_Pool": "radical_board",
      "Tournament_Pool_Display": "Radical board",
      "Tournament_Pool_Eligible": "radical_board",
      "Local_Pool_Score": -9.7614,
      "Tournament_Finalist_Flag": false,
      "Shortlist_Slot_Name": "",
      "Shortlist_Slot_Order": NaN,
      "Crowding_Block_Reason": "",
      "Selection_Passed_Over_For_Diversity": "",
      "Comparative_Edge_Score_10": 7.4,
      "Comparator_Floor_Score_10": 5.33,
      "Dominance_Score_10": 6.78,
      "Primary_Shortlist_Flag": false,
      "Primary_Override_Flag": false,
      "Shadow_Watchlist_Flag": false,
      "Shadow_Watchlist_Reason": "",
      "Shadow_Watchlist_Order": NaN,
      "In_Top_Shortlist": false,
      "Setup_Quality_Grade_10": 4.51,
      "Setup_Quality_Grade_100": 45.1,
      "Setup_Quality_Band": "C",
      "Prediction_Top_Strengths": "execution 10.0, asymmetry 8.9, context 7.0",
      "Prediction_Main_Risks": "gate_pressure 11.8, false_positive_risk 4.5",
      "Prediction_Breakdown": "SHORT continuation; strengths: execution 10.0, asymmetry 8.9, context 7.0; risks: gate_pressure 11.8, false_positive_risk 4.5; admission: blocked / blocked_gatepass",
      "Prediction_Score_Version": "v5.5_prediction_quality_v2",
      "Prediction_Uses_Only_Contemporaneous_Inputs": true,
      "Prediction_Forbidden_Field_Leak": false,
      "Prediction_Input_Fingerprint": "a91a4e7c03ce992a",
      "Prediction_Integrity_Status": "clean_contemporaneous_only",
      "Prediction_Rank": 3
    },
    {
      "Snapshot_Date": "2026-05-20",
      "Prediction_Reference_Timestamp": "2026-05-20 09:53:33",
      "Market_Reference_Timestamp": "1970-01-01 00:00:00.000000698",
      "Instrument": "AUDUSD",
      "status": "OK",
      "Universe_Layer": "Layer 1 — Core execution universe",
      "Cluster_Tags": "HTF aligned, USD basket, USD weakness, commodity bloc",
      "W1_Bias": "BEARISH",
      "D1_Bias": "BEARISH",
      "Price_Side_vs_D1_Range": "discount",
      "Alignment": "aligned",
      "Liquidity_Condition": "external liquidity taken",
      "Sweep_Quality": "clean sweep only",
      "Liquidity_Side": "sell-side",
      "Liquidity_Tier": "major",
      "Liquidity_Reference_Type": "swing low",
      "Rejection_Quality": "moderate rejection",
      "Follow_Through": "limited follow-through",
      "Both_Sides_Taken_Recently": false,
      "Displacement_Quality": "strong displacement",
      "MSS_BOS": "partial shift",
      "Array_Quality": "good",
      "Session_Quality": "acceptable but not ideal",
      "RS_RW_Alignment": "clear alignment",
      "SMT_Hint": "none",
      "Pivot_Regime": "daily: bearish below pivot | weekly: bearish below pivot",
      "Pivot_Zone_Fit": "price in neutral zone",
      "Pivot_Confluence": "mixed confluence",
      "Pivot_Conflict": "no meaningful pivot conflict",
      "Pivot_Stretch": "not stretched",
      "Technical_Score_0_4": 2.65,
      "Legacy_Confidence_Score": 0.85,
      "Legacy_Confidence_Band": "medium",
      "Confidence_Score": 0.416,
      "Confidence_Band": "low",
      "Technical_Quality_Score_10": 8.9,
      "Execution_Realism_Score_10": 10.0,
      "Calibrated_Confidence_Score_10": 4.16,
      "Selection_Score": -9.5758,
      "Final_Rank_Score": -9.6318,
      "Data_Quality": "good",
      "Entry_Label": "B-tier reactive setup",
      "Preferred_Side": "SHORT",
      "Best_Entry": 0.7114,
      "Structural_Entry": 0.7237,
      "Calibration_Entry": 0.7114,
      "Entry_Distance_ATR": 0.122,
      "SL": 0.7123,
      "TP1": 0.7102,
      "TP2": 0.7093,
      "Current_Price": 0.7112,
      "ATR_H1": 0.0009,
      "RR_TP1": 1.3333,
      "RR_TP2": 2.3333,
      "Execution_Line": "Sell-limit: 0.7114 | SL: 0.7123 | TP1: 0.7102 | TP2: 0.7093 | RR1: 1.3333 | RR2: 2.3333",
      "Execution_Source": "zone",
      "Setup_Archetype": "relative_value_continuation",
      "Decision_Book": "A-book",
      "Live_Gate_Passed": true,
      "Calibration_Gate_Passed": true,
      "Gate_Passed": true,
      "Gate_Fail_Reasons": "",
      "Decision_Setup_Quality": 4.0,
      "Decision_Execution_Quality": 3.8,
      "Decision_Portfolio_Fit": 0.0,
      "Decision_Rank_Score": -10.4508,
      "Base_Ranking_Score": -10.3908,
      "Overlap_Penalty": 0.0,
      "Ranking_Score": -9.6318,
      "Calibration_Soft_Candidate": false,
      "Calibration_Candidate_Bucket": "hard_pass",
      "Soft_Candidate": false,
      "Soft_Fail_Adjustment": 0.0,
      "Continuation_Subquality": 0.0,
      "Continuation_Elite_Eligible": false,
      "Context_Quality_Score_10": 7.5,
      "Trigger_Quality_Score_10": 6.65,
      "Conflict_Penalty_Score_10": 0.0,
      "Opportunity_Score_10": 3.95,
      "Balance_Score_10": 6.99,
      "Kill_Switch_Score_10": 0.0,
      "False_Positive_Risk_Score_10": 6.7,
      "Archetype_Tax_Score_10": 7.2,
      "Survivability_Score_10": 7.29,
      "Asymmetry_Score_10": 7.8,
      "Calibration_Utility_Score_10": 3.4,
      "Radical_Confidence_Score_10": 4.16,
      "Admission_Class": "blocked",
      "Override_Reason": "relval_hard_block",
      "Shortlist_Eligibility": "blocked",
      "Admission_Binding_Status": "blocked_relval",
      "Selection_Lane": "blocked_relval",
      "Leakage_Penalty_Score": 3.0,
      "Veto_Flag": false,
      "Veto_Reasons": "",
      "Selector_Profile": "v5.5_prediction_ready_selector",
      "Fragility_Reason": "",
      "Idea_Family": "relval|no_theme|SHORT|nonusd",
      "Survivor_Score": 3.7435,
      "Tournament_Pool": "radical_board",
      "Tournament_Pool_Display": "Radical board",
      "Tournament_Pool_Eligible": "radical_board",
      "Local_Pool_Score": -10.4508,
      "Tournament_Finalist_Flag": false,
      "Shortlist_Slot_Name": "",
      "Shortlist_Slot_Order": NaN,
      "Crowding_Block_Reason": "",
      "Selection_Passed_Over_For_Diversity": "",
      "Comparative_Edge_Score_10": 1.65,
      "Comparator_Floor_Score_10": 0.5,
      "Dominance_Score_10": 1.31,
      "Primary_Shortlist_Flag": false,
      "Primary_Override_Flag": false,
      "Shadow_Watchlist_Flag": false,
      "Shadow_Watchlist_Reason": "",
      "Shadow_Watchlist_Order": NaN,
      "In_Top_Shortlist": false,
      "Setup_Quality_Grade_10": 4.21,
      "Setup_Quality_Grade_100": 42.1,
      "Setup_Quality_Band": "C",
      "Prediction_Top_Strengths": "execution 10.0, asymmetry 7.8, context 7.5",
      "Prediction_Main_Risks": "gate_pressure 7.7, archetype_tax 7.2",
      "Prediction_Breakdown": "SHORT relative_value_continuation; strengths: execution 10.0, asymmetry 7.8, context 7.5; risks: gate_pressure 7.7, archetype_tax 7.2; admission: blocked / blocked_relval",
      "Prediction_Score_Version": "v5.5_prediction_quality_v2",
      "Prediction_Uses_Only_Contemporaneous_Inputs": true,
      "Prediction_Forbidden_Field_Leak": false,
      "Prediction_Input_Fingerprint": "2fd3f314b10e5816",
      "Prediction_Integrity_Status": "clean_contemporaneous_only",
      "Prediction_Rank": 4
    },
    {
      "Snapshot_Date": "2026-05-20",
      "Prediction_Reference_Timestamp": "2026-05-20 09:53:33",
      "Market_Reference_Timestamp": "1970-01-01 00:00:00.000000698",
      "Instrument": "AUDCHF",
      "status": "OK",
      "Universe_Layer": "Layer 2 — Relative-value crosses",
      "Cluster_Tags": "CHF haven cluster, CHF strength, HTF conflict, commodity bloc",
      "W1_Bias": "BULLISH",
      "D1_Bias": "BEARISH",
      "Price_Side_vs_D1_Range": "discount",
      "Alignment": "full conflict",
      "Liquidity_Condition": "external liquidity taken",
      "Sweep_Quality": "clean sweep only",
      "Liquidity_Side": "buy-side",
      "Liquidity_Tier": "major",
      "Liquidity_Reference_Type": "swing high",
      "Rejection_Quality": "moderate rejection",
      "Follow_Through": "limited follow-through",
      "Both_Sides_Taken_Recently": true,
      "Displacement_Quality": "weak / no displacement",
      "MSS_BOS": "partial shift",
      "Array_Quality": "good",
      "Session_Quality": "acceptable but not ideal",
      "RS_RW_Alignment": "clear alignment",
      "SMT_Hint": "none",
      "Pivot_Regime": "daily: bullish above pivot | weekly: bearish below pivot",
      "Pivot_Zone_Fit": "price in sell zone",
      "Pivot_Confluence": "daily only",
      "Pivot_Conflict": "mild pivot conflict",
      "Pivot_Stretch": "not stretched",
      "Technical_Score_0_4": 1.5,
      "Legacy_Confidence_Score": 0.75,
      "Legacy_Confidence_Band": "medium",
      "Confidence_Score": 0.37,
      "Confidence_Band": "low",
      "Technical_Quality_Score_10": 3.2,
      "Execution_Realism_Score_10": 9.97,
      "Calibrated_Confidence_Score_10": 3.7,
      "Selection_Score": 0.8404,
      "Final_Rank_Score": 0.7911,
      "Data_Quality": "good",
      "Entry_Label": "B-tier reactive setup",
      "Preferred_Side": "SHORT",
      "Best_Entry": 0.5623,
      "Structural_Entry": 0.5664,
      "Calibration_Entry": 0.5623,
      "Entry_Distance_ATR": 0.035,
      "SL": 0.5628,
      "TP1": 0.5618,
      "TP2": 0.5614,
      "Current_Price": 0.562,
      "ATR_H1": 0.0006,
      "RR_TP1": 1.0,
      "RR_TP2": 1.8,
      "Execution_Line": "Sell-limit: 0.5623 | SL: 0.5628 | TP1: 0.5618 | TP2: 0.5614 | RR1: 1.0 | RR2: 1.8",
      "Execution_Source": "zone",
      "Setup_Archetype": "continuation",
      "Decision_Book": "Rejected",
      "Live_Gate_Passed": false,
      "Calibration_Gate_Passed": false,
      "Gate_Passed": false,
      "Gate_Fail_Reasons": "weak_impulse",
      "Decision_Setup_Quality": 0.4,
      "Decision_Execution_Quality": 3.45,
      "Decision_Portfolio_Fit": 0.0,
      "Decision_Rank_Score": -1.0236,
      "Base_Ranking_Score": -0.9636,
      "Overlap_Penalty": 0.0,
      "Ranking_Score": 0.7911,
      "Calibration_Soft_Candidate": false,
      "Calibration_Candidate_Bucket": "hard_reject",
      "Soft_Candidate": false,
      "Soft_Fail_Adjustment": 0.0,
      "Continuation_Subquality": 0.23,
      "Continuation_Elite_Eligible": false,
      "Context_Quality_Score_10": 4.5,
      "Trigger_Quality_Score_10": 4.45,
      "Conflict_Penalty_Score_10": 4.1,
      "Opportunity_Score_10": 6.35,
      "Balance_Score_10": 4.42,
      "Kill_Switch_Score_10": 5.0,
      "False_Positive_Risk_Score_10": 2.9,
      "Archetype_Tax_Score_10": 3.0,
      "Survivability_Score_10": 3.22,
      "Asymmetry_Score_10": 7.8,
      "Calibration_Utility_Score_10": 7.35,
      "Radical_Confidence_Score_10": 3.7,
      "Admission_Class": "eligible",
      "Override_Reason": "",
      "Shortlist_Eligibility": "primary",
      "Admission_Binding_Status": "primary_eligible",
      "Selection_Lane": "primary_not_selected",
      "Leakage_Penalty_Score": 0.0,
      "Veto_Flag": false,
      "Veto_Reasons": "",
      "Selector_Profile": "v5.5_prediction_ready_selector",
      "Fragility_Reason": "hard_reject",
      "Idea_Family": "continuation|no_theme|SHORT|nonusd|strong",
      "Survivor_Score": 2.838,
      "Tournament_Pool": "radical_board",
      "Tournament_Pool_Display": "Radical board",
      "Tournament_Pool_Eligible": "radical_board",
      "Local_Pool_Score": -1.0236,
      "Tournament_Finalist_Flag": false,
      "Shortlist_Slot_Name": "",
      "Shortlist_Slot_Order": NaN,
      "Crowding_Block_Reason": "",
      "Selection_Passed_Over_For_Diversity": "",
      "Comparative_Edge_Score_10": 3.6,
      "Comparator_Floor_Score_10": 1.33,
      "Dominance_Score_10": 2.92,
      "Primary_Shortlist_Flag": false,
      "Primary_Override_Flag": false,
      "Shadow_Watchlist_Flag": false,
      "Shadow_Watchlist_Reason": "",
      "Shadow_Watchlist_Order": NaN,
      "In_Top_Shortlist": false,
      "Setup_Quality_Grade_10": 3.87,
      "Setup_Quality_Grade_100": 38.7,
      "Setup_Quality_Band": "D",
      "Prediction_Top_Strengths": "execution 10.0, asymmetry 7.8, utility 7.3",
      "Prediction_Main_Risks": "kill_switch 5.0, conflict 4.1",
      "Prediction_Breakdown": "SHORT continuation; strengths: execution 10.0, asymmetry 7.8, utility 7.3; risks: kill_switch 5.0, conflict 4.1; admission: eligible / primary_not_selected",
      "Prediction_Score_Version": "v5.5_prediction_quality_v2",
      "Prediction_Uses_Only_Contemporaneous_Inputs": true,
      "Prediction_Forbidden_Field_Leak": false,
      "Prediction_Input_Fingerprint": "cf1baeb183bd36ee",
      "Prediction_Integrity_Status": "clean_contemporaneous_only",
      "Prediction_Rank": 5
    },
    {
      "Snapshot_Date": "2026-05-20",
      "Prediction_Reference_Timestamp": "2026-05-20 09:53:33",
      "Market_Reference_Timestamp": "1970-01-01 00:00:00.000000698",
      "Instrument": "USDJPY",
      "status": "OK",
      "Universe_Layer": "Layer 1 — Core execution universe",
      "Cluster_Tags": "HTF aligned, JPY cluster, USD basket, USD strength",
      "W1_Bias": "BULLISH",
      "D1_Bias": "BULLISH",
      "Price_Side_vs_D1_Range": "premium",
      "Alignment": "aligned",
      "Liquidity_Condition": "external liquidity taken",
      "Sweep_Quality": "sweep + close back inside range",
      "Liquidity_Side": "sell-side",
      "Liquidity_Tier": "major",
      "Liquidity_Reference_Type": "swing low",
      "Rejection_Quality": "moderate rejection",
      "Follow_Through": "clean follow-through",
      "Both_Sides_Taken_Recently": true,
      "Displacement_Quality": "moderate displacement",
      "MSS_BOS": "partial shift",
      "Array_Quality": "weak",
      "Session_Quality": "acceptable but not ideal",
      "RS_RW_Alignment": "clear alignment",
      "SMT_Hint": "none",
      "Pivot_Regime": "daily: bullish above pivot | weekly: bullish above pivot",
      "Pivot_Zone_Fit": "price in neutral zone",
      "Pivot_Confluence": "mixed confluence",
      "Pivot_Conflict": "no meaningful pivot conflict",
      "Pivot_Stretch": "not stretched",
      "Technical_Score_0_4": 2.25,
      "Legacy_Confidence_Score": 0.75,
      "Legacy_Confidence_Band": "medium",
      "Confidence_Score": 0.493,
      "Confidence_Band": "low",
      "Technical_Quality_Score_10": 8.25,
      "Execution_Realism_Score_10": 9.6,
      "Calibrated_Confidence_Score_10": 4.93,
      "Selection_Score": -7.6424,
      "Final_Rank_Score": -7.6758,
      "Data_Quality": "good",
      "Entry_Label": "D-tier avoid",
      "Preferred_Side": "LONG",
      "Best_Entry": 159.063,
      "Structural_Entry": 159.056,
      "Calibration_Entry": 159.063,
      "Entry_Distance_ATR": 0.055,
      "SL": 158.864,
      "TP1": 159.305,
      "TP2": 159.493,
      "Current_Price": 159.059,
      "ATR_H1": 0.099,
      "RR_TP1": 1.2161,
      "RR_TP2": 2.1608,
      "Execution_Line": "Buy-limit: 159.063 | SL: 158.864 | TP1: 159.305 | TP2: 159.493 | RR1: 1.2161 | RR2: 2.1608",
      "Execution_Source": "fallback",
      "Setup_Archetype": "relative_value_continuation",
      "Decision_Book": "B-book",
      "Live_Gate_Passed": false,
      "Calibration_Gate_Passed": true,
      "Gate_Passed": true,
      "Gate_Fail_Reasons": "d_tier",
      "Decision_Setup_Quality": 3.0,
      "Decision_Execution_Quality": 3.3,
      "Decision_Portfolio_Fit": 0.0,
      "Decision_Rank_Score": -10.7442,
      "Base_Ranking_Score": -10.6842,
      "Overlap_Penalty": 0.0,
      "Ranking_Score": -7.6758,
      "Calibration_Soft_Candidate": true,
      "Calibration_Candidate_Bucket": "hard_pass",
      "Soft_Candidate": true,
      "Soft_Fail_Adjustment": -0.25,
      "Continuation_Subquality": 0.0,
      "Continuation_Elite_Eligible": false,
      "Context_Quality_Score_10": 7.85,
      "Trigger_Quality_Score_10": 6.0,
      "Conflict_Penalty_Score_10": 1.6,
      "Opportunity_Score_10": 5.75,
      "Balance_Score_10": 6.76,
      "Kill_Switch_Score_10": 3.9,
      "False_Positive_Risk_Score_10": 5.4,
      "Archetype_Tax_Score_10": 7.2,
      "Survivability_Score_10": 6.24,
      "Asymmetry_Score_10": 8.4,
      "Calibration_Utility_Score_10": 5.9,
      "Radical_Confidence_Score_10": 4.93,
      "Admission_Class": "blocked",
      "Override_Reason": "relval_hard_block",
      "Shortlist_Eligibility": "blocked",
      "Admission_Binding_Status": "blocked_relval",
      "Selection_Lane": "blocked_relval",
      "Leakage_Penalty_Score": 3.0,
      "Veto_Flag": false,
      "Veto_Reasons": "",
      "Selector_Profile": "v5.5_prediction_ready_selector",
      "Fragility_Reason": "bbook_plus_fail",
      "Idea_Family": "relval|no_theme|LONG|nonusd",
      "Survivor_Score": 3.886,
      "Tournament_Pool": "radical_board",
      "Tournament_Pool_Display": "Radical board",
      "Tournament_Pool_Eligible": "radical_board",
      "Local_Pool_Score": -10.7442,
      "Tournament_Finalist_Flag": false,
      "Shortlist_Slot_Name": "",
      "Shortlist_Slot_Order": NaN,
      "Crowding_Block_Reason": "",
      "Selection_Passed_Over_For_Diversity": "",
      "Comparative_Edge_Score_10": 5.77,
      "Comparator_Floor_Score_10": 3.33,
      "Dominance_Score_10": 5.04,
      "Primary_Shortlist_Flag": false,
      "Primary_Override_Flag": false,
      "Shadow_Watchlist_Flag": false,
      "Shadow_Watchlist_Reason": "",
      "Shadow_Watchlist_Order": NaN,
      "In_Top_Shortlist": false,
      "Setup_Quality_Grade_10": 3.86,
      "Setup_Quality_Grade_100": 38.6,
      "Setup_Quality_Band": "D",
      "Prediction_Top_Strengths": "execution 9.6, asymmetry 8.4, context 7.8",
      "Prediction_Main_Risks": "gate_pressure 11.8, archetype_tax 7.2",
      "Prediction_Breakdown": "LONG relative_value_continuation; strengths: execution 9.6, asymmetry 8.4, context 7.8; risks: gate_pressure 11.8, archetype_tax 7.2; admission: blocked / blocked_relval",
      "Prediction_Score_Version": "v5.5_prediction_quality_v2",
      "Prediction_Uses_Only_Contemporaneous_Inputs": true,
      "Prediction_Forbidden_Field_Leak": false,
      "Prediction_Input_Fingerprint": "720e942603568c27",
      "Prediction_Integrity_Status": "clean_contemporaneous_only",
      "Prediction_Rank": 6
    },
    {
      "Snapshot_Date": "2026-05-20",
      "Prediction_Reference_Timestamp": "2026-05-20 09:53:33",
      "Market_Reference_Timestamp": "1970-01-01 00:00:00.000000698",
      "Instrument": "GBPUSD",
      "status": "OK",
      "Universe_Layer": "Layer 1 — Core execution universe",
      "Cluster_Tags": "HTF aligned, USD basket, USD weakness",
      "W1_Bias": "BEARISH",
      "D1_Bias": "BEARISH",
      "Price_Side_vs_D1_Range": "discount",
      "Alignment": "aligned",
      "Liquidity_Condition": "external liquidity taken",
      "Sweep_Quality": "sweep + close back inside range",
      "Liquidity_Side": "buy-side",
      "Liquidity_Tier": "minor",
      "Liquidity_Reference_Type": "swing high",
      "Rejection_Quality": "strong rejection",
      "Follow_Through": "clean follow-through",
      "Both_Sides_Taken_Recently": true,
      "Displacement_Quality": "weak / no displacement",
      "MSS_BOS": "partial shift",
      "Array_Quality": "weak",
      "Session_Quality": "acceptable but not ideal",
      "RS_RW_Alignment": "no clear alignment",
      "SMT_Hint": "none",
      "Pivot_Regime": "daily: bearish below pivot | weekly: bearish below pivot",
      "Pivot_Zone_Fit": "price in neutral zone",
      "Pivot_Confluence": "mixed confluence",
      "Pivot_Conflict": "no meaningful pivot conflict",
      "Pivot_Stretch": "not stretched",
      "Technical_Score_0_4": 0.65,
      "Legacy_Confidence_Score": 0.85,
      "Legacy_Confidence_Band": "medium",
      "Confidence_Score": 0.432,
      "Confidence_Band": "low",
      "Technical_Quality_Score_10": 6.45,
      "Execution_Realism_Score_10": 9.6,
      "Calibrated_Confidence_Score_10": 4.32,
      "Selection_Score": -7.9249,
      "Final_Rank_Score": -7.9635,
      "Data_Quality": "good",
      "Entry_Label": "D-tier avoid",
      "Preferred_Side": "SHORT",
      "Best_Entry": 1.3388,
      "Structural_Entry": 1.3536,
      "Calibration_Entry": 1.3388,
      "Entry_Distance_ATR": 0.067,
      "SL": 1.3413,
      "TP1": 1.3357,
      "TP2": 1.3333,
      "Current_Price": 1.3384,
      "ATR_H1": 0.0012,
      "RR_TP1": 1.24,
      "RR_TP2": 2.2,
      "Execution_Line": "Sell-limit: 1.3388 | SL: 1.3413 | TP1: 1.3357 | TP2: 1.3333 | RR1: 1.24 | RR2: 2.2",
      "Execution_Source": "zone",
      "Setup_Archetype": "continuation",
      "Decision_Book": "B-book",
      "Live_Gate_Passed": false,
      "Calibration_Gate_Passed": true,
      "Gate_Passed": true,
      "Gate_Fail_Reasons": "d_tier, weak_impulse",
      "Decision_Setup_Quality": 2.1,
      "Decision_Execution_Quality": 3.3,
      "Decision_Portfolio_Fit": 0.0,
      "Decision_Rank_Score": -10.9812,
      "Base_Ranking_Score": -10.9212,
      "Overlap_Penalty": 0.0,
      "Ranking_Score": -7.9635,
      "Calibration_Soft_Candidate": true,
      "Calibration_Candidate_Bucket": "hard_pass",
      "Soft_Candidate": true,
      "Soft_Fail_Adjustment": -0.45,
      "Continuation_Subquality": 0.39,
      "Continuation_Elite_Eligible": true,
      "Context_Quality_Score_10": 7.55,
      "Trigger_Quality_Score_10": 4.95,
      "Conflict_Penalty_Score_10": 2.7,
      "Opportunity_Score_10": 6.8,
      "Balance_Score_10": 5.43,
      "Kill_Switch_Score_10": 6.7,
      "False_Positive_Risk_Score_10": 3.8,
      "Archetype_Tax_Score_10": 3.0,
      "Survivability_Score_10": 4.64,
      "Asymmetry_Score_10": 8.9,
      "Calibration_Utility_Score_10": 6.9,
      "Radical_Confidence_Score_10": 4.32,
      "Admission_Class": "blocked",
      "Override_Reason": "gatepass_primary_block",
      "Shortlist_Eligibility": "blocked",
      "Admission_Binding_Status": "blocked_gatepass",
      "Selection_Lane": "blocked_gatepass",
      "Leakage_Penalty_Score": 3.0,
      "Veto_Flag": false,
      "Veto_Reasons": "",
      "Selector_Profile": "v5.5_prediction_ready_selector",
      "Fragility_Reason": "bbook_plus_fail",
      "Idea_Family": "continuation|no_theme|SHORT|nonusd|strong",
      "Survivor_Score": 3.446,
      "Tournament_Pool": "radical_board",
      "Tournament_Pool_Display": "Radical board",
      "Tournament_Pool_Eligible": "radical_board",
      "Local_Pool_Score": -10.9812,
      "Tournament_Finalist_Flag": false,
      "Shortlist_Slot_Name": "",
      "Shortlist_Slot_Order": NaN,
      "Crowding_Block_Reason": "",
      "Selection_Passed_Over_For_Diversity": "",
      "Comparative_Edge_Score_10": 5.85,
      "Comparator_Floor_Score_10": 2.67,
      "Dominance_Score_10": 4.9,
      "Primary_Shortlist_Flag": false,
      "Primary_Override_Flag": false,
      "Shadow_Watchlist_Flag": false,
      "Shadow_Watchlist_Reason": "",
      "Shadow_Watchlist_Order": NaN,
      "In_Top_Shortlist": false,
      "Setup_Quality_Grade_10": 3.62,
      "Setup_Quality_Grade_100": 36.2,
      "Setup_Quality_Band": "D",
      "Prediction_Top_Strengths": "execution 9.6, asymmetry 8.9, context 7.5",
      "Prediction_Main_Risks": "gate_pressure 11.8, kill_switch 6.7",
      "Prediction_Breakdown": "SHORT continuation; strengths: execution 9.6, asymmetry 8.9, context 7.5; risks: gate_pressure 11.8, kill_switch 6.7; admission: blocked / blocked_gatepass",
      "Prediction_Score_Version": "v5.5_prediction_quality_v2",
      "Prediction_Uses_Only_Contemporaneous_Inputs": true,
      "Prediction_Forbidden_Field_Leak": false,
      "Prediction_Input_Fingerprint": "14a8f755d1306e9a",
      "Prediction_Integrity_Status": "clean_contemporaneous_only",
      "Prediction_Rank": 7
    },
    {
      "Snapshot_Date": "2026-05-20",
      "Prediction_Reference_Timestamp": "2026-05-20 09:53:33",
      "Market_Reference_Timestamp": "1970-01-01 00:00:00.000000698",
      "Instrument": "USDCHF",
      "status": "OK",
      "Universe_Layer": "Layer 1 — Core execution universe",
      "Cluster_Tags": "CHF haven cluster, HTF aligned, USD basket, USD strength",
      "W1_Bias": "BULLISH",
      "D1_Bias": "BULLISH",
      "Price_Side_vs_D1_Range": "premium",
      "Alignment": "aligned",
      "Liquidity_Condition": "external liquidity taken",
      "Sweep_Quality": "clean sweep only",
      "Liquidity_Side": "buy-side",
      "Liquidity_Tier": "major",
      "Liquidity_Reference_Type": "swing high",
      "Rejection_Quality": "weak/no rejection",
      "Follow_Through": "limited follow-through",
      "Both_Sides_Taken_Recently": false,
      "Displacement_Quality": "weak / no displacement",
      "MSS_BOS": "partial shift",
      "Array_Quality": "good",
      "Session_Quality": "acceptable but not ideal",
      "RS_RW_Alignment": "mixed",
      "SMT_Hint": "none",
      "Pivot_Regime": "daily: bullish above pivot | weekly: bullish above pivot",
      "Pivot_Zone_Fit": "price in neutral zone",
      "Pivot_Confluence": "mixed confluence",
      "Pivot_Conflict": "no meaningful pivot conflict",
      "Pivot_Stretch": "not stretched",
      "Technical_Score_0_4": 0.85,
      "Legacy_Confidence_Score": 0.75,
      "Legacy_Confidence_Band": "medium",
      "Confidence_Score": 0.474,
      "Confidence_Band": "low",
      "Technical_Quality_Score_10": 5.6,
      "Execution_Realism_Score_10": 10.0,
      "Calibrated_Confidence_Score_10": 4.74,
      "Selection_Score": -9.2938,
      "Final_Rank_Score": -9.3498,
      "Data_Quality": "good",
      "Entry_Label": "B-tier reactive setup",
      "Preferred_Side": "LONG",
      "Best_Entry": 0.7904,
      "Structural_Entry": 0.7809,
      "Calibration_Entry": 0.7904,
      "Entry_Distance_ATR": 0.015,
      "SL": 0.7897,
      "TP1": 0.7911,
      "TP2": 0.7917,
      "Current_Price": 0.7903,
      "ATR_H1": 0.0006,
      "RR_TP1": 1.0,
      "RR_TP2": 1.8571,
      "Execution_Line": "Buy-limit: 0.7904 | SL: 0.7897 | TP1: 0.7911 | TP2: 0.7917 | RR1: 1.0 | RR2: 1.8571",
      "Execution_Source": "zone",
      "Setup_Archetype": "continuation",
      "Decision_Book": "B-book",
      "Live_Gate_Passed": false,
      "Calibration_Gate_Passed": true,
      "Gate_Passed": true,
      "Gate_Fail_Reasons": "weak_impulse",
      "Decision_Setup_Quality": 2.35,
      "Decision_Execution_Quality": 3.8,
      "Decision_Portfolio_Fit": 0.0,
      "Decision_Rank_Score": -10.1705,
      "Base_Ranking_Score": -10.1105,
      "Overlap_Penalty": 0.0,
      "Ranking_Score": -9.3498,
      "Calibration_Soft_Candidate": true,
      "Calibration_Candidate_Bucket": "hard_pass",
      "Soft_Candidate": true,
      "Soft_Fail_Adjustment": -0.2,
      "Continuation_Subquality": 0.15,
      "Continuation_Elite_Eligible": true,
      "Context_Quality_Score_10": 7.5,
      "Trigger_Quality_Score_10": 3.65,
      "Conflict_Penalty_Score_10": 1.1,
      "Opportunity_Score_10": 6.8,
      "Balance_Score_10": 3.32,
      "Kill_Switch_Score_10": 2.8,
      "False_Positive_Risk_Score_10": 3.8,
      "Archetype_Tax_Score_10": 3.8,
      "Survivability_Score_10": 4.6,
      "Asymmetry_Score_10": 7.2,
      "Calibration_Utility_Score_10": 6.9,
      "Radical_Confidence_Score_10": 4.74,
      "Admission_Class": "blocked",
      "Override_Reason": "gatepass_primary_block",
      "Shortlist_Eligibility": "blocked",
      "Admission_Binding_Status": "blocked_gatepass",
      "Selection_Lane": "blocked_gatepass",
      "Leakage_Penalty_Score": 3.0,
      "Veto_Flag": false,
      "Veto_Reasons": "",
      "Selector_Profile": "v5.5_prediction_ready_selector",
      "Fragility_Reason": "bbook_plus_fail",
      "Idea_Family": "continuation|no_theme|LONG|nonusd|normal",
      "Survivor_Score": 3.42,
      "Tournament_Pool": "radical_board",
      "Tournament_Pool_Display": "Radical board",
      "Tournament_Pool_Eligible": "radical_board",
      "Local_Pool_Score": -10.1705,
      "Tournament_Finalist_Flag": false,
      "Shortlist_Slot_Name": "",
      "Shortlist_Slot_Order": NaN,
      "Crowding_Block_Reason": "",
      "Selection_Passed_Over_For_Diversity": "",
      "Comparative_Edge_Score_10": 1.66,
      "Comparator_Floor_Score_10": 0.5,
      "Dominance_Score_10": 1.31,
      "Primary_Shortlist_Flag": false,
      "Primary_Override_Flag": false,
      "Shadow_Watchlist_Flag": false,
      "Shadow_Watchlist_Reason": "",
      "Shadow_Watchlist_Order": NaN,
      "In_Top_Shortlist": false,
      "Setup_Quality_Grade_10": 3.52,
      "Setup_Quality_Grade_100": 35.2,
      "Setup_Quality_Band": "D",
      "Prediction_Top_Strengths": "execution 10.0, context 7.5, asymmetry 7.2",
      "Prediction_Main_Risks": "gate_pressure 11.8, false_positive_risk 3.8",
      "Prediction_Breakdown": "LONG continuation; strengths: execution 10.0, context 7.5, asymmetry 7.2; risks: gate_pressure 11.8, false_positive_risk 3.8; admission: blocked / blocked_gatepass",
      "Prediction_Score_Version": "v5.5_prediction_quality_v2",
      "Prediction_Uses_Only_Contemporaneous_Inputs": true,
      "Prediction_Forbidden_Field_Leak": false,
      "Prediction_Input_Fingerprint": "28218c5895f79cfa",
      "Prediction_Integrity_Status": "clean_contemporaneous_only",
      "Prediction_Rank": 8
    },
    {
      "Snapshot_Date": "2026-05-20",
      "Prediction_Reference_Timestamp": "2026-05-20 09:53:33",
      "Market_Reference_Timestamp": "1970-01-01 00:00:00.000000698",
      "Instrument": "GBPCAD",
      "status": "OK",
      "Universe_Layer": "Layer 2 — Relative-value crosses",
      "Cluster_Tags": "HTF aligned, commodity bloc",
      "W1_Bias": "BEARISH",
      "D1_Bias": "BEARISH",
      "Price_Side_vs_D1_Range": "discount",
      "Alignment": "aligned",
      "Liquidity_Condition": "external liquidity taken",
      "Sweep_Quality": "sweep + close back inside range",
      "Liquidity_Side": "sell-side",
      "Liquidity_Tier": "major",
      "Liquidity_Reference_Type": "swing low",
      "Rejection_Quality": "strong rejection",
      "Follow_Through": "clean follow-through",
      "Both_Sides_Taken_Recently": true,
      "Displacement_Quality": "weak / no displacement",
      "MSS_BOS": "partial shift",
      "Array_Quality": "weak",
      "Session_Quality": "acceptable but not ideal",
      "RS_RW_Alignment": "no clear alignment",
      "SMT_Hint": "none",
      "Pivot_Regime": "daily: bearish below pivot | weekly: bullish above pivot",
      "Pivot_Zone_Fit": "price in sell zone",
      "Pivot_Confluence": "daily only",
      "Pivot_Conflict": "mild pivot conflict",
      "Pivot_Stretch": "not stretched",
      "Technical_Score_0_4": 0.95,
      "Legacy_Confidence_Score": 0.85,
      "Legacy_Confidence_Band": "medium",
      "Confidence_Score": 0.419,
      "Confidence_Band": "low",
      "Technical_Quality_Score_10": 6.0,
      "Execution_Realism_Score_10": 9.97,
      "Calibrated_Confidence_Score_10": 4.19,
      "Selection_Score": -8.2774,
      "Final_Rank_Score": -8.3161,
      "Data_Quality": "good",
      "Entry_Label": "D-tier avoid",
      "Preferred_Side": "SHORT",
      "Best_Entry": 1.844,
      "Structural_Entry": 1.844,
      "Calibration_Entry": 1.844,
      "Entry_Distance_ATR": 0.071,
      "SL": 1.8463,
      "TP1": 1.8412,
      "TP2": 1.839,
      "Current_Price": 1.8432,
      "ATR_H1": 0.0016,
      "RR_TP1": 1.2174,
      "RR_TP2": 2.1739,
      "Execution_Line": "Sell-limit: 1.844 | SL: 1.8463 | TP1: 1.8412 | TP2: 1.839 | RR1: 1.2174 | RR2: 2.1739",
      "Execution_Source": "fallback",
      "Setup_Archetype": "continuation",
      "Decision_Book": "B-book",
      "Live_Gate_Passed": false,
      "Calibration_Gate_Passed": true,
      "Gate_Passed": true,
      "Gate_Fail_Reasons": "d_tier, weak_impulse",
      "Decision_Setup_Quality": 1.85,
      "Decision_Execution_Quality": 3.45,
      "Decision_Portfolio_Fit": 0.0,
      "Decision_Rank_Score": -11.1799,
      "Base_Ranking_Score": -11.1199,
      "Overlap_Penalty": 0.0,
      "Ranking_Score": -8.3161,
      "Calibration_Soft_Candidate": true,
      "Calibration_Candidate_Bucket": "hard_pass",
      "Soft_Candidate": true,
      "Soft_Fail_Adjustment": -0.45,
      "Continuation_Subquality": 0.33,
      "Continuation_Elite_Eligible": true,
      "Context_Quality_Score_10": 7.25,
      "Trigger_Quality_Score_10": 4.95,
      "Conflict_Penalty_Score_10": 2.7,
      "Opportunity_Score_10": 6.8,
      "Balance_Score_10": 5.1,
      "Kill_Switch_Score_10": 6.7,
      "False_Positive_Risk_Score_10": 4.5,
      "Archetype_Tax_Score_10": 3.0,
      "Survivability_Score_10": 4.63,
      "Asymmetry_Score_10": 8.9,
      "Calibration_Utility_Score_10": 6.9,
      "Radical_Confidence_Score_10": 4.19,
      "Admission_Class": "blocked",
      "Override_Reason": "gatepass_primary_block",
      "Shortlist_Eligibility": "blocked",
      "Admission_Binding_Status": "blocked_gatepass",
      "Selection_Lane": "blocked_gatepass",
      "Leakage_Penalty_Score": 3.0,
      "Veto_Flag": false,
      "Veto_Reasons": "",
      "Selector_Profile": "v5.5_prediction_ready_selector",
      "Fragility_Reason": "bbook_plus_fail",
      "Idea_Family": "continuation|no_theme|SHORT|nonusd|strong",
      "Survivor_Score": 3.2645,
      "Tournament_Pool": "radical_board",
      "Tournament_Pool_Display": "Radical board",
      "Tournament_Pool_Eligible": "radical_board",
      "Local_Pool_Score": -11.1799,
      "Tournament_Finalist_Flag": false,
      "Shortlist_Slot_Name": "",
      "Shortlist_Slot_Order": NaN,
      "Crowding_Block_Reason": "",
      "Selection_Passed_Over_For_Diversity": "",
      "Comparative_Edge_Score_10": 5.52,
      "Comparator_Floor_Score_10": 2.67,
      "Dominance_Score_10": 4.66,
      "Primary_Shortlist_Flag": false,
      "Primary_Override_Flag": false,
      "Shadow_Watchlist_Flag": false,
      "Shadow_Watchlist_Reason": "",
      "Shadow_Watchlist_Order": NaN,
      "In_Top_Shortlist": false,
      "Setup_Quality_Grade_10": 3.49,
      "Setup_Quality_Grade_100": 34.9,
      "Setup_Quality_Band": "D",
      "Prediction_Top_Strengths": "execution 10.0, asymmetry 8.9, context 7.2",
      "Prediction_Main_Risks": "gate_pressure 11.8, kill_switch 6.7",
      "Prediction_Breakdown": "SHORT continuation; strengths: execution 10.0, asymmetry 8.9, context 7.2; risks: gate_pressure 11.8, kill_switch 6.7; admission: blocked / blocked_gatepass",
      "Prediction_Score_Version": "v5.5_prediction_quality_v2",
      "Prediction_Uses_Only_Contemporaneous_Inputs": true,
      "Prediction_Forbidden_Field_Leak": false,
      "Prediction_Input_Fingerprint": "14d5d7d3d97f85fa",
      "Prediction_Integrity_Status": "clean_contemporaneous_only",
      "Prediction_Rank": 9
    },
    {
      "Snapshot_Date": "2026-05-20",
      "Prediction_Reference_Timestamp": "2026-05-20 09:53:33",
      "Market_Reference_Timestamp": "1970-01-01 00:00:00.000000698",
      "Instrument": "EURUSD",
      "status": "OK",
      "Universe_Layer": "Layer 1 — Core execution universe",
      "Cluster_Tags": "EUR weakness, HTF aligned, USD basket, USD weakness",
      "W1_Bias": "BEARISH",
      "D1_Bias": "BEARISH",
      "Price_Side_vs_D1_Range": "discount",
      "Alignment": "aligned",
      "Liquidity_Condition": "external liquidity taken",
      "Sweep_Quality": "sweep + close back inside range",
      "Liquidity_Side": "sell-side",
      "Liquidity_Tier": "minor",
      "Liquidity_Reference_Type": "swing low",
      "Rejection_Quality": "moderate rejection",
      "Follow_Through": "limited follow-through",
      "Both_Sides_Taken_Recently": false,
      "Displacement_Quality": "weak / no displacement",
      "MSS_BOS": "partial shift",
      "Array_Quality": "good",
      "Session_Quality": "acceptable but not ideal",
      "RS_RW_Alignment": "clear alignment",
      "SMT_Hint": "none",
      "Pivot_Regime": "daily: bearish below pivot | weekly: bearish below pivot",
      "Pivot_Zone_Fit": "price in neutral zone",
      "Pivot_Confluence": "mixed confluence",
      "Pivot_Conflict": "no meaningful pivot conflict",
      "Pivot_Stretch": "not stretched",
      "Technical_Score_0_4": 1.6,
      "Legacy_Confidence_Score": 0.75,
      "Legacy_Confidence_Band": "medium",
      "Confidence_Score": 0.462,
      "Confidence_Band": "low",
      "Technical_Quality_Score_10": 6.65,
      "Execution_Realism_Score_10": 10.0,
      "Calibrated_Confidence_Score_10": 4.62,
      "Selection_Score": -8.4793,
      "Final_Rank_Score": -8.5179,
      "Data_Quality": "good",
      "Entry_Label": "B-tier reactive setup",
      "Preferred_Side": "SHORT",
      "Best_Entry": 1.1592,
      "Structural_Entry": 1.1727,
      "Calibration_Entry": 1.1592,
      "Entry_Distance_ATR": 0.036,
      "SL": 1.1603,
      "TP1": 1.158,
      "TP2": 1.157,
      "Current_Price": 1.1591,
      "ATR_H1": 0.0008,
      "RR_TP1": 1.0909,
      "RR_TP2": 2.0,
      "Execution_Line": "Sell-limit: 1.1592 | SL: 1.1603 | TP1: 1.158 | TP2: 1.157 | RR1: 1.0909 | RR2: 2.0",
      "Execution_Source": "zone",
      "Setup_Archetype": "relative_value_continuation",
      "Decision_Book": "B-book",
      "Live_Gate_Passed": false,
      "Calibration_Gate_Passed": true,
      "Gate_Passed": true,
      "Gate_Fail_Reasons": "weak_impulse",
      "Decision_Setup_Quality": 2.45,
      "Decision_Execution_Quality": 3.8,
      "Decision_Portfolio_Fit": 0.0,
      "Decision_Rank_Score": -10.8551,
      "Base_Ranking_Score": -10.7951,
      "Overlap_Penalty": 0.0,
      "Ranking_Score": -8.5179,
      "Calibration_Soft_Candidate": true,
      "Calibration_Candidate_Bucket": "hard_pass",
      "Soft_Candidate": true,
      "Soft_Fail_Adjustment": -0.2,
      "Continuation_Subquality": 0.0,
      "Continuation_Elite_Eligible": false,
      "Context_Quality_Score_10": 7.2,
      "Trigger_Quality_Score_10": 4.45,
      "Conflict_Penalty_Score_10": 1.1,
      "Opportunity_Score_10": 5.75,
      "Balance_Score_10": 4.4,
      "Kill_Switch_Score_10": 2.8,
      "False_Positive_Risk_Score_10": 5.4,
      "Archetype_Tax_Score_10": 7.2,
      "Survivability_Score_10": 5.27,
      "Asymmetry_Score_10": 7.8,
      "Calibration_Utility_Score_10": 5.9,
      "Radical_Confidence_Score_10": 4.62,
      "Admission_Class": "blocked",
      "Override_Reason": "relval_hard_block",
      "Shortlist_Eligibility": "blocked",
      "Admission_Binding_Status": "blocked_relval",
      "Selection_Lane": "blocked_relval",
      "Leakage_Penalty_Score": 3.0,
      "Veto_Flag": false,
      "Veto_Reasons": "",
      "Selector_Profile": "v5.5_prediction_ready_selector",
      "Fragility_Reason": "bbook_plus_fail",
      "Idea_Family": "relval|no_theme|SHORT|nonusd",
      "Survivor_Score": 3.2555,
      "Tournament_Pool": "radical_board",
      "Tournament_Pool_Display": "Radical board",
      "Tournament_Pool_Eligible": "radical_board",
      "Local_Pool_Score": -10.8551,
      "Tournament_Finalist_Flag": false,
      "Shortlist_Slot_Name": "",
      "Shortlist_Slot_Order": NaN,
      "Crowding_Block_Reason": "",
      "Selection_Passed_Over_For_Diversity": "",
      "Comparative_Edge_Score_10": 4.36,
      "Comparator_Floor_Score_10": 2.67,
      "Dominance_Score_10": 3.85,
      "Primary_Shortlist_Flag": false,
      "Primary_Override_Flag": false,
      "Shadow_Watchlist_Flag": false,
      "Shadow_Watchlist_Reason": "",
      "Shadow_Watchlist_Order": NaN,
      "In_Top_Shortlist": false,
      "Setup_Quality_Grade_10": 3.38,
      "Setup_Quality_Grade_100": 33.8,
      "Setup_Quality_Band": "D",
      "Prediction_Top_Strengths": "execution 10.0, asymmetry 7.8, context 7.2",
      "Prediction_Main_Risks": "gate_pressure 11.8, archetype_tax 7.2",
      "Prediction_Breakdown": "SHORT relative_value_continuation; strengths: execution 10.0, asymmetry 7.8, context 7.2; risks: gate_pressure 11.8, archetype_tax 7.2; admission: blocked / blocked_relval",
      "Prediction_Score_Version": "v5.5_prediction_quality_v2",
      "Prediction_Uses_Only_Contemporaneous_Inputs": true,
      "Prediction_Forbidden_Field_Leak": false,
      "Prediction_Input_Fingerprint": "7055e4cde5f83e6d",
      "Prediction_Integrity_Status": "clean_contemporaneous_only",
      "Prediction_Rank": 10
    },
    {
      "Snapshot_Date": "2026-05-20",
      "Prediction_Reference_Timestamp": "2026-05-20 09:53:33",
      "Market_Reference_Timestamp": "1970-01-01 00:00:00.000000698",
      "Instrument": "AUDNZD",
      "status": "OK",
      "Universe_Layer": "Layer 2 — Relative-value crosses",
      "Cluster_Tags": "HTF conflict, commodity bloc",
      "W1_Bias": "BULLISH",
      "D1_Bias": "BEARISH",
      "Price_Side_vs_D1_Range": "discount",
      "Alignment": "full conflict",
      "Liquidity_Condition": "external liquidity taken",
      "Sweep_Quality": "clean sweep only",
      "Liquidity_Side": "buy-side",
      "Liquidity_Tier": "major",
      "Liquidity_Reference_Type": "swing high",
      "Rejection_Quality": "moderate rejection",
      "Follow_Through": "clean follow-through",
      "Both_Sides_Taken_Recently": true,
      "Displacement_Quality": "moderate displacement",
      "MSS_BOS": "partial shift",
      "Array_Quality": "weak",
      "Session_Quality": "acceptable but not ideal",
      "RS_RW_Alignment": "clear alignment",
      "SMT_Hint": "none",
      "Pivot_Regime": "daily: bearish below pivot | weekly: bearish below pivot",
      "Pivot_Zone_Fit": "price in neutral zone",
      "Pivot_Confluence": "mixed confluence",
      "Pivot_Conflict": "no meaningful pivot conflict",
      "Pivot_Stretch": "not stretched",
      "Technical_Score_0_4": 1.4,
      "Legacy_Confidence_Score": 0.75,
      "Legacy_Confidence_Band": "medium",
      "Confidence_Score": 0.416,
      "Confidence_Band": "low",
      "Technical_Quality_Score_10": 5.25,
      "Execution_Realism_Score_10": 8.72,
      "Calibrated_Confidence_Score_10": 4.16,
      "Selection_Score": -7.7323,
      "Final_Rank_Score": -7.7656,
      "Data_Quality": "good",
      "Entry_Label": "D-tier avoid",
      "Preferred_Side": "SHORT",
      "Best_Entry": 1.2187,
      "Structural_Entry": 1.2221,
      "Calibration_Entry": 1.2187,
      "Entry_Distance_ATR": 0.036,
      "SL": 1.2197,
      "TP1": 1.2176,
      "TP2": 1.2167,
      "Current_Price": 1.2178,
      "ATR_H1": 0.0011,
      "RR_TP1": 1.1,
      "RR_TP2": 2.0,
      "Execution_Line": "Sell-limit: 1.2187 | SL: 1.2197 | TP1: 1.2176 | TP2: 1.2167 | RR1: 1.1 | RR2: 2.0",
      "Execution_Source": "zone",
      "Setup_Archetype": "continuation",
      "Decision_Book": "B-book",
      "Live_Gate_Passed": false,
      "Calibration_Gate_Passed": true,
      "Gate_Passed": true,
      "Gate_Fail_Reasons": "d_tier",
      "Decision_Setup_Quality": 1.2,
      "Decision_Execution_Quality": 2.95,
      "Decision_Portfolio_Fit": 0.0,
      "Decision_Rank_Score": -10.8208,
      "Base_Ranking_Score": -10.7608,
      "Overlap_Penalty": 0.0,
      "Ranking_Score": -7.7656,
      "Calibration_Soft_Candidate": true,
      "Calibration_Candidate_Bucket": "hard_pass",
      "Soft_Candidate": true,
      "Soft_Fail_Adjustment": -0.25,
      "Continuation_Subquality": 0.47,
      "Continuation_Elite_Eligible": false,
      "Context_Quality_Score_10": 5.45,
      "Trigger_Quality_Score_10": 6.0,
      "Conflict_Penalty_Score_10": 4.6,
      "Opportunity_Score_10": 6.8,
      "Balance_Score_10": 6.9,
      "Kill_Switch_Score_10": 6.1,
      "False_Positive_Risk_Score_10": 3.8,
      "Archetype_Tax_Score_10": 3.0,
      "Survivability_Score_10": 4.34,
      "Asymmetry_Score_10": 8.4,
      "Calibration_Utility_Score_10": 6.9,
      "Radical_Confidence_Score_10": 4.16,
      "Admission_Class": "blocked",
      "Override_Reason": "gatepass_primary_block",
      "Shortlist_Eligibility": "blocked",
      "Admission_Binding_Status": "blocked_gatepass",
      "Selection_Lane": "blocked_gatepass",
      "Leakage_Penalty_Score": 3.0,
      "Veto_Flag": false,
      "Veto_Reasons": "",
      "Selector_Profile": "v5.5_prediction_ready_selector",
      "Fragility_Reason": "bbook_plus_fail",
      "Idea_Family": "continuation|no_theme|SHORT|nonusd|strong",
      "Survivor_Score": 3.251,
      "Tournament_Pool": "radical_board",
      "Tournament_Pool_Display": "Radical board",
      "Tournament_Pool_Eligible": "radical_board",
      "Local_Pool_Score": -10.8208,
      "Tournament_Finalist_Flag": false,
      "Shortlist_Slot_Name": "",
      "Shortlist_Slot_Order": NaN,
      "Crowding_Block_Reason": "",
      "Selection_Passed_Over_For_Diversity": "",
      "Comparative_Edge_Score_10": 5.74,
      "Comparator_Floor_Score_10": 3.33,
      "Dominance_Score_10": 5.02,
      "Primary_Shortlist_Flag": false,
      "Primary_Override_Flag": false,
      "Shadow_Watchlist_Flag": false,
      "Shadow_Watchlist_Reason": "",
      "Shadow_Watchlist_Order": NaN,
      "In_Top_Shortlist": false,
      "Setup_Quality_Grade_10": 3.23,
      "Setup_Quality_Grade_100": 32.3,
      "Setup_Quality_Band": "D",
      "Prediction_Top_Strengths": "execution 8.7, asymmetry 8.4, utility 6.9",
      "Prediction_Main_Risks": "gate_pressure 11.8, kill_switch 6.1",
      "Prediction_Breakdown": "SHORT continuation; strengths: execution 8.7, asymmetry 8.4, utility 6.9; risks: gate_pressure 11.8, kill_switch 6.1; admission: blocked / blocked_gatepass",
      "Prediction_Score_Version": "v5.5_prediction_quality_v2",
      "Prediction_Uses_Only_Contemporaneous_Inputs": true,
      "Prediction_Forbidden_Field_Leak": false,
      "Prediction_Input_Fingerprint": "f7eb8a60e7a1cd4f",
      "Prediction_Integrity_Status": "clean_contemporaneous_only",
      "Prediction_Rank": 11
    },
    {
      "Snapshot_Date": "2026-05-20",
      "Prediction_Reference_Timestamp": "2026-05-20 09:53:33",
      "Market_Reference_Timestamp": "1970-01-01 00:00:00.000000698",
      "Instrument": "USDCAD",
      "status": "OK",
      "Universe_Layer": "Layer 1 — Core execution universe",
      "Cluster_Tags": "HTF aligned, USD basket, USD strength, commodity bloc",
      "W1_Bias": "BULLISH",
      "D1_Bias": "BULLISH",
      "Price_Side_vs_D1_Range": "premium",
      "Alignment": "aligned",
      "Liquidity_Condition": "external liquidity taken",
      "Sweep_Quality": "clean sweep only",
      "Liquidity_Side": "buy-side",
      "Liquidity_Tier": "minor",
      "Liquidity_Reference_Type": "swing high",
      "Rejection_Quality": "weak/no rejection",
      "Follow_Through": "limited follow-through",
      "Both_Sides_Taken_Recently": true,
      "Displacement_Quality": "moderate displacement",
      "MSS_BOS": "partial shift",
      "Array_Quality": "weak",
      "Session_Quality": "acceptable but not ideal",
      "RS_RW_Alignment": "clear alignment",
      "SMT_Hint": "none",
      "Pivot_Regime": "daily: bullish above pivot | weekly: bullish above pivot",
      "Pivot_Zone_Fit": "price in neutral zone",
      "Pivot_Confluence": "mixed confluence",
      "Pivot_Conflict": "no meaningful pivot conflict",
      "Pivot_Stretch": "not stretched",
      "Technical_Score_0_4": 1.65,
      "Legacy_Confidence_Score": 0.75,
      "Legacy_Confidence_Band": "medium",
      "Confidence_Score": 0.424,
      "Confidence_Band": "low",
      "Technical_Quality_Score_10": 7.3,
      "Execution_Realism_Score_10": 9.6,
      "Calibrated_Confidence_Score_10": 4.24,
      "Selection_Score": -10.2705,
      "Final_Rank_Score": -10.3251,
      "Data_Quality": "good",
      "Entry_Label": "D-tier avoid",
      "Preferred_Side": "LONG",
      "Best_Entry": 1.3775,
      "Structural_Entry": 1.3775,
      "Calibration_Entry": 1.3775,
      "Entry_Distance_ATR": 0.109,
      "SL": 1.3758,
      "TP1": 1.3796,
      "TP2": 1.3813,
      "Current_Price": 1.3772,
      "ATR_H1": 0.0008,
      "RR_TP1": 1.2353,
      "RR_TP2": 2.2353,
      "Execution_Line": "Buy-limit: 1.3775 | SL: 1.3758 | TP1: 1.3796 | TP2: 1.3813 | RR1: 1.2353 | RR2: 2.2353",
      "Execution_Source": "fallback",
      "Setup_Archetype": "relative_value_continuation",
      "Decision_Book": "B-book",
      "Live_Gate_Passed": false,
      "Calibration_Gate_Passed": true,
      "Gate_Passed": true,
      "Gate_Fail_Reasons": "d_tier",
      "Decision_Setup_Quality": 2.5,
      "Decision_Execution_Quality": 3.3,
      "Decision_Portfolio_Fit": 0.0,
      "Decision_Rank_Score": -11.2515,
      "Base_Ranking_Score": -11.1915,
      "Overlap_Penalty": 0.0,
      "Ranking_Score": -10.3251,
      "Calibration_Soft_Candidate": true,
      "Calibration_Candidate_Bucket": "hard_pass",
      "Soft_Candidate": true,
      "Soft_Fail_Adjustment": -0.25,
      "Continuation_Subquality": 0.0,
      "Continuation_Elite_Eligible": false,
      "Context_Quality_Score_10": 7.2,
      "Trigger_Quality_Score_10": 5.2,
      "Conflict_Penalty_Score_10": 1.6,
      "Opportunity_Score_10": 5.75,
      "Balance_Score_10": 5.77,
      "Kill_Switch_Score_10": 3.9,
      "False_Positive_Risk_Score_10": 6.2,
      "Archetype_Tax_Score_10": 7.2,
      "Survivability_Score_10": 5.53,
      "Asymmetry_Score_10": 7.2,
      "Calibration_Utility_Score_10": 5.9,
      "Radical_Confidence_Score_10": 4.24,
      "Admission_Class": "blocked",
      "Override_Reason": "relval_hard_block",
      "Shortlist_Eligibility": "blocked",
      "Admission_Binding_Status": "blocked_relval",
      "Selection_Lane": "blocked_relval",
      "Leakage_Penalty_Score": 3.0,
      "Veto_Flag": false,
      "Veto_Reasons": "",
      "Selector_Profile": "v5.5_prediction_ready_selector",
      "Fragility_Reason": "bbook_plus_fail",
      "Idea_Family": "relval|no_theme|LONG|nonusd",
      "Survivor_Score": 3.2245,
      "Tournament_Pool": "radical_board",
      "Tournament_Pool_Display": "Radical board",
      "Tournament_Pool_Eligible": "radical_board",
      "Local_Pool_Score": -11.2515,
      "Tournament_Finalist_Flag": false,
      "Shortlist_Slot_Name": "",
      "Shortlist_Slot_Order": NaN,
      "Crowding_Block_Reason": "",
      "Selection_Passed_Over_For_Diversity": "",
      "Comparative_Edge_Score_10": 1.84,
      "Comparator_Floor_Score_10": 0.67,
      "Dominance_Score_10": 1.49,
      "Primary_Shortlist_Flag": false,
      "Primary_Override_Flag": false,
      "Shadow_Watchlist_Flag": false,
      "Shadow_Watchlist_Reason": "",
      "Shadow_Watchlist_Order": NaN,
      "In_Top_Shortlist": false,
      "Setup_Quality_Grade_10": 2.96,
      "Setup_Quality_Grade_100": 29.6,
      "Setup_Quality_Band": "D",
      "Prediction_Top_Strengths": "execution 9.6, asymmetry 7.2, context 7.2",
      "Prediction_Main_Risks": "gate_pressure 11.8, archetype_tax 7.2",
      "Prediction_Breakdown": "LONG relative_value_continuation; strengths: execution 9.6, asymmetry 7.2, context 7.2; risks: gate_pressure 11.8, archetype_tax 7.2; admission: blocked / blocked_relval",
      "Prediction_Score_Version": "v5.5_prediction_quality_v2",
      "Prediction_Uses_Only_Contemporaneous_Inputs": true,
      "Prediction_Forbidden_Field_Leak": false,
      "Prediction_Input_Fingerprint": "cd031202abc8ddb1",
      "Prediction_Integrity_Status": "clean_contemporaneous_only",
      "Prediction_Rank": 12
    },
    {
      "Snapshot_Date": "2026-05-20",
      "Prediction_Reference_Timestamp": "2026-05-20 09:53:33",
      "Market_Reference_Timestamp": "1970-01-01 00:00:00.000000698",
      "Instrument": "CADJPY",
      "status": "OK",
      "Universe_Layer": "Layer 1 — Core execution universe",
      "Cluster_Tags": "HTF aligned, JPY cluster, commodity bloc",
      "W1_Bias": "BULLISH",
      "D1_Bias": "BULLISH",
      "Price_Side_vs_D1_Range": "premium",
      "Alignment": "aligned",
      "Liquidity_Condition": "external liquidity taken",
      "Sweep_Quality": "sweep + close back inside range",
      "Liquidity_Side": "buy-side",
      "Liquidity_Tier": "major",
      "Liquidity_Reference_Type": "swing high",
      "Rejection_Quality": "moderate rejection",
      "Follow_Through": "clean follow-through",
      "Both_Sides_Taken_Recently": true,
      "Displacement_Quality": "weak / no displacement",
      "MSS_BOS": "partial shift",
      "Array_Quality": "weak",
      "Session_Quality": "acceptable but not ideal",
      "RS_RW_Alignment": "clear alignment",
      "SMT_Hint": "none",
      "Pivot_Regime": "daily: bearish below pivot | weekly: bullish above pivot",
      "Pivot_Zone_Fit": "price in buy zone",
      "Pivot_Confluence": "daily only",
      "Pivot_Conflict": "mild pivot conflict",
      "Pivot_Stretch": "not stretched",
      "Technical_Score_0_4": 1.65,
      "Legacy_Confidence_Score": 0.75,
      "Legacy_Confidence_Band": "medium",
      "Confidence_Score": 0.32,
      "Confidence_Band": "low",
      "Technical_Quality_Score_10": 6.2,
      "Execution_Realism_Score_10": 8.72,
      "Calibrated_Confidence_Score_10": 3.2,
      "Selection_Score": -10.9085,
      "Final_Rank_Score": -10.9579,
      "Data_Quality": "good",
      "Entry_Label": "D-tier avoid",
      "Preferred_Side": "LONG",
      "Best_Entry": 115.452,
      "Structural_Entry": 115.447,
      "Calibration_Entry": 115.452,
      "Entry_Distance_ATR": 0.05,
      "SL": 115.308,
      "TP1": 115.627,
      "TP2": 115.764,
      "Current_Price": 115.491,
      "ATR_H1": 0.075,
      "RR_TP1": 1.2153,
      "RR_TP2": 2.1667,
      "Execution_Line": "Buy-limit: 115.452 | SL: 115.308 | TP1: 115.627 | TP2: 115.764 | RR1: 1.2153 | RR2: 2.1667",
      "Execution_Source": "fallback",
      "Setup_Archetype": "relative_value_continuation",
      "Decision_Book": "B-book",
      "Live_Gate_Passed": false,
      "Calibration_Gate_Passed": true,
      "Gate_Passed": true,
      "Gate_Fail_Reasons": "d_tier, weak_impulse",
      "Decision_Setup_Quality": 1.6,
      "Decision_Execution_Quality": 2.95,
      "Decision_Portfolio_Fit": 0.0,
      "Decision_Rank_Score": -12.4601,
      "Base_Ranking_Score": -12.4001,
      "Overlap_Penalty": 0.0,
      "Ranking_Score": -10.9579,
      "Calibration_Soft_Candidate": true,
      "Calibration_Candidate_Bucket": "hard_pass",
      "Soft_Candidate": true,
      "Soft_Fail_Adjustment": -0.45,
      "Continuation_Subquality": 0.0,
      "Continuation_Elite_Eligible": false,
      "Context_Quality_Score_10": 7.25,
      "Trigger_Quality_Score_10": 4.45,
      "Conflict_Penalty_Score_10": 2.7,
      "Opportunity_Score_10": 5.75,
      "Balance_Score_10": 5.55,
      "Kill_Switch_Score_10": 6.7,
      "False_Positive_Risk_Score_10": 6.1,
      "Archetype_Tax_Score_10": 7.2,
      "Survivability_Score_10": 4.11,
      "Asymmetry_Score_10": 8.4,
      "Calibration_Utility_Score_10": 5.9,
      "Radical_Confidence_Score_10": 3.2,
      "Admission_Class": "blocked",
      "Override_Reason": "relval_hard_block",
      "Shortlist_Eligibility": "blocked",
      "Admission_Binding_Status": "blocked_relval",
      "Selection_Lane": "blocked_relval",
      "Leakage_Penalty_Score": 3.0,
      "Veto_Flag": false,
      "Veto_Reasons": "",
      "Selector_Profile": "v5.5_prediction_ready_selector",
      "Fragility_Reason": "bbook_plus_fail",
      "Idea_Family": "relval|no_theme|LONG|nonusd",
      "Survivor_Score": 2.3265,
      "Tournament_Pool": "radical_board",
      "Tournament_Pool_Display": "Radical board",
      "Tournament_Pool_Eligible": "radical_board",
      "Local_Pool_Score": -12.4601,
      "Tournament_Finalist_Flag": false,
      "Shortlist_Slot_Name": "",
      "Shortlist_Slot_Order": NaN,
      "Crowding_Block_Reason": "",
      "Selection_Passed_Over_For_Diversity": "",
      "Comparative_Edge_Score_10": 2.91,
      "Comparator_Floor_Score_10": 1.33,
      "Dominance_Score_10": 2.44,
      "Primary_Shortlist_Flag": false,
      "Primary_Override_Flag": false,
      "Shadow_Watchlist_Flag": false,
      "Shadow_Watchlist_Reason": "",
      "Shadow_Watchlist_Order": NaN,
      "In_Top_Shortlist": false,
      "Setup_Quality_Grade_10": 2.26,
      "Setup_Quality_Grade_100": 22.6,
      "Setup_Quality_Band": "E",
      "Prediction_Top_Strengths": "execution 8.7, asymmetry 8.4, context 7.2",
      "Prediction_Main_Risks": "gate_pressure 11.8, archetype_tax 7.2",
      "Prediction_Breakdown": "LONG relative_value_continuation; strengths: execution 8.7, asymmetry 8.4, context 7.2; risks: gate_pressure 11.8, archetype_tax 7.2; admission: blocked / blocked_relval",
      "Prediction_Score_Version": "v5.5_prediction_quality_v2",
      "Prediction_Uses_Only_Contemporaneous_Inputs": true,
      "Prediction_Forbidden_Field_Leak": false,
      "Prediction_Input_Fingerprint": "5508b5045fafe404",
      "Prediction_Integrity_Status": "clean_contemporaneous_only",
      "Prediction_Rank": 13
    },
    {
      "Snapshot_Date": "2026-05-20",
      "Prediction_Reference_Timestamp": "2026-05-20 09:53:33",
      "Market_Reference_Timestamp": "1970-01-01 00:00:00.000000698",
      "Instrument": "EURJPY",
      "status": "OK",
      "Universe_Layer": "Layer 1 — Core execution universe",
      "Cluster_Tags": "EUR relative-value cluster, EUR weakness, HTF conflict, JPY cluster, risk-off short",
      "W1_Bias": "BULLISH",
      "D1_Bias": "BEARISH",
      "Price_Side_vs_D1_Range": "discount",
      "Alignment": "full conflict",
      "Liquidity_Condition": "external liquidity taken",
      "Sweep_Quality": "sweep + close back inside range",
      "Liquidity_Side": "sell-side",
      "Liquidity_Tier": "major",
      "Liquidity_Reference_Type": "swing low",
      "Rejection_Quality": "strong rejection",
      "Follow_Through": "clean follow-through",
      "Both_Sides_Taken_Recently": false,
      "Displacement_Quality": "weak / no displacement",
      "MSS_BOS": "partial shift",
      "Array_Quality": "weak",
      "Session_Quality": "acceptable but not ideal",
      "RS_RW_Alignment": "no clear alignment",
      "SMT_Hint": "none",
      "Pivot_Regime": "daily: bearish below pivot | weekly: bearish below pivot",
      "Pivot_Zone_Fit": "price in neutral zone",
      "Pivot_Confluence": "mixed confluence",
      "Pivot_Conflict": "no meaningful pivot conflict",
      "Pivot_Stretch": "not stretched",
      "Technical_Score_0_4": 0.55,
      "Legacy_Confidence_Score": 0.85,
      "Legacy_Confidence_Band": "medium",
      "Confidence_Score": 0.259,
      "Confidence_Band": "low",
      "Technical_Quality_Score_10": 4.3,
      "Execution_Realism_Score_10": 9.6,
      "Calibrated_Confidence_Score_10": 2.59,
      "Selection_Score": -10.9523,
      "Final_Rank_Score": -11.007,
      "Data_Quality": "good",
      "Entry_Label": "D-tier avoid",
      "Preferred_Side": "SHORT",
      "Best_Entry": 184.376,
      "Structural_Entry": 184.387,
      "Calibration_Entry": 184.376,
      "Entry_Distance_ATR": 0.055,
      "SL": 184.607,
      "TP1": 184.096,
      "TP2": 183.878,
      "Current_Price": 184.358,
      "ATR_H1": 0.118,
      "RR_TP1": 1.2121,
      "RR_TP2": 2.1558,
      "Execution_Line": "Sell-limit: 184.376 | SL: 184.607 | TP1: 184.096 | TP2: 183.878 | RR1: 1.2121 | RR2: 2.1558",
      "Execution_Source": "fallback",
      "Setup_Archetype": "continuation",
      "Decision_Book": "Rejected",
      "Live_Gate_Passed": false,
      "Calibration_Gate_Passed": false,
      "Gate_Passed": false,
      "Gate_Fail_Reasons": "d_tier, weak_impulse",
      "Decision_Setup_Quality": 0.5,
      "Decision_Execution_Quality": 3.3,
      "Decision_Portfolio_Fit": 0.0,
      "Decision_Rank_Score": -11.9847,
      "Base_Ranking_Score": -11.9247,
      "Overlap_Penalty": 0.0,
      "Ranking_Score": -11.007,
      "Calibration_Soft_Candidate": false,
      "Calibration_Candidate_Bucket": "hard_reject",
      "Soft_Candidate": false,
      "Soft_Fail_Adjustment": 0.0,
      "Continuation_Subquality": 0.51,
      "Continuation_Elite_Eligible": false,
      "Context_Quality_Score_10": 5.45,
      "Trigger_Quality_Score_10": 4.95,
      "Conflict_Penalty_Score_10": 5.7,
      "Opportunity_Score_10": 6.35,
      "Balance_Score_10": 5.43,
      "Kill_Switch_Score_10": 8.9,
      "False_Positive_Risk_Score_10": 2.9,
      "Archetype_Tax_Score_10": 3.0,
      "Survivability_Score_10": 2.74,
      "Asymmetry_Score_10": 8.9,
      "Calibration_Utility_Score_10": 7.35,
      "Radical_Confidence_Score_10": 2.59,
      "Admission_Class": "blocked",
      "Override_Reason": "kill_switch_block",
      "Shortlist_Eligibility": "blocked",
      "Admission_Binding_Status": "blocked_kill",
      "Selection_Lane": "blocked_kill",
      "Leakage_Penalty_Score": 3.0,
      "Veto_Flag": true,
      "Veto_Reasons": "kill_switch_block",
      "Selector_Profile": "v5.5_prediction_ready_selector",
      "Fragility_Reason": "hard_reject",
      "Idea_Family": "continuation|no_theme|SHORT|nonusd|strong",
      "Survivor_Score": 2.526,
      "Tournament_Pool": "radical_board",
      "Tournament_Pool_Display": "Radical board",
      "Tournament_Pool_Eligible": "radical_board",
      "Local_Pool_Score": -11.9847,
      "Tournament_Finalist_Flag": false,
      "Shortlist_Slot_Name": "",
      "Shortlist_Slot_Order": NaN,
      "Crowding_Block_Reason": "",
      "Selection_Passed_Over_For_Diversity": "",
      "Comparative_Edge_Score_10": 1.95,
      "Comparator_Floor_Score_10": 0.67,
      "Dominance_Score_10": 1.57,
      "Primary_Shortlist_Flag": false,
      "Primary_Override_Flag": false,
      "Shadow_Watchlist_Flag": false,
      "Shadow_Watchlist_Reason": "",
      "Shadow_Watchlist_Order": NaN,
      "In_Top_Shortlist": false,
      "Setup_Quality_Grade_10": 1.72,
      "Setup_Quality_Grade_100": 17.2,
      "Setup_Quality_Band": "E",
      "Prediction_Top_Strengths": "execution 9.6, asymmetry 8.9, utility 7.3",
      "Prediction_Main_Risks": "gate_pressure 16.8, kill_switch 8.9",
      "Prediction_Breakdown": "SHORT continuation; strengths: execution 9.6, asymmetry 8.9, utility 7.3; risks: gate_pressure 16.8, kill_switch 8.9; admission: blocked / blocked_kill",
      "Prediction_Score_Version": "v5.5_prediction_quality_v2",
      "Prediction_Uses_Only_Contemporaneous_Inputs": true,
      "Prediction_Forbidden_Field_Leak": false,
      "Prediction_Input_Fingerprint": "5c43e1ff06dbc596",
      "Prediction_Integrity_Status": "clean_contemporaneous_only",
      "Prediction_Rank": 14
    },
    {
      "Snapshot_Date": "2026-05-20",
      "Prediction_Reference_Timestamp": "2026-05-20 09:53:33",
      "Market_Reference_Timestamp": "1970-01-01 00:00:00.000000698",
      "Instrument": "EURCHF",
      "status": "OK",
      "Universe_Layer": "Layer 1 — Core execution universe",
      "Cluster_Tags": "CHF haven cluster, EUR relative-value cluster, HTF conflict",
      "W1_Bias": "BEARISH",
      "D1_Bias": "BULLISH",
      "Price_Side_vs_D1_Range": "premium",
      "Alignment": "full conflict",
      "Liquidity_Condition": "external liquidity taken",
      "Sweep_Quality": "clean sweep only",
      "Liquidity_Side": "buy-side",
      "Liquidity_Tier": "major",
      "Liquidity_Reference_Type": "swing high",
      "Rejection_Quality": "moderate rejection",
      "Follow_Through": "clean follow-through",
      "Both_Sides_Taken_Recently": true,
      "Displacement_Quality": "weak / no displacement",
      "MSS_BOS": "partial shift",
      "Array_Quality": "weak",
      "Session_Quality": "acceptable but not ideal",
      "RS_RW_Alignment": "mixed",
      "SMT_Hint": "none",
      "Pivot_Regime": "daily: bullish above pivot | weekly: bullish above pivot",
      "Pivot_Zone_Fit": "price in neutral zone",
      "Pivot_Confluence": "mixed confluence",
      "Pivot_Conflict": "no meaningful pivot conflict",
      "Pivot_Stretch": "not stretched",
      "Technical_Score_0_4": 0.2,
      "Legacy_Confidence_Score": 0.75,
      "Legacy_Confidence_Band": "medium",
      "Confidence_Score": 0.215,
      "Confidence_Band": "low",
      "Technical_Quality_Score_10": 3.9,
      "Execution_Realism_Score_10": 10.0,
      "Calibrated_Confidence_Score_10": 2.15,
      "Selection_Score": -11.2914,
      "Final_Rank_Score": -11.3474,
      "Data_Quality": "good",
      "Entry_Label": "D-tier avoid",
      "Preferred_Side": "LONG",
      "Best_Entry": 0.9162,
      "Structural_Entry": 0.9147,
      "Calibration_Entry": 0.9162,
      "Entry_Distance_ATR": 0.018,
      "SL": 0.9155,
      "TP1": 0.917,
      "TP2": 0.9177,
      "Current_Price": 0.916,
      "ATR_H1": 0.0005,
      "RR_TP1": 1.1429,
      "RR_TP2": 2.1429,
      "Execution_Line": "Buy-limit: 0.9162 | SL: 0.9155 | TP1: 0.917 | TP2: 0.9177 | RR1: 1.1429 | RR2: 2.1429",
      "Execution_Source": "zone",
      "Setup_Archetype": "continuation",
      "Decision_Book": "Rejected",
      "Live_Gate_Passed": false,
      "Calibration_Gate_Passed": false,
      "Gate_Passed": false,
      "Gate_Fail_Reasons": "d_tier, weak_impulse",
      "Decision_Setup_Quality": 0.25,
      "Decision_Execution_Quality": 3.8,
      "Decision_Portfolio_Fit": 0.0,
      "Decision_Rank_Score": -12.1416,
      "Base_Ranking_Score": -12.0816,
      "Overlap_Penalty": 0.0,
      "Ranking_Score": -11.3474,
      "Calibration_Soft_Candidate": false,
      "Calibration_Candidate_Bucket": "hard_reject",
      "Soft_Candidate": false,
      "Soft_Fail_Adjustment": 0.0,
      "Continuation_Subquality": 0.37,
      "Continuation_Elite_Eligible": false,
      "Context_Quality_Score_10": 5.45,
      "Trigger_Quality_Score_10": 4.45,
      "Conflict_Penalty_Score_10": 5.7,
      "Opportunity_Score_10": 6.35,
      "Balance_Score_10": 4.4,
      "Kill_Switch_Score_10": 8.9,
      "False_Positive_Risk_Score_10": 2.9,
      "Archetype_Tax_Score_10": 3.0,
      "Survivability_Score_10": 2.39,
      "Asymmetry_Score_10": 8.4,
      "Calibration_Utility_Score_10": 7.35,
      "Radical_Confidence_Score_10": 2.15,
      "Admission_Class": "blocked",
      "Override_Reason": "kill_switch_block",
      "Shortlist_Eligibility": "blocked",
      "Admission_Binding_Status": "blocked_kill",
      "Selection_Lane": "blocked_kill",
      "Leakage_Penalty_Score": 3.0,
      "Veto_Flag": true,
      "Veto_Reasons": "kill_switch_block",
      "Selector_Profile": "v5.5_prediction_ready_selector",
      "Fragility_Reason": "hard_reject",
      "Idea_Family": "continuation|no_theme|LONG|nonusd|strong",
      "Survivor_Score": 2.2985,
      "Tournament_Pool": "radical_board",
      "Tournament_Pool_Display": "Radical board",
      "Tournament_Pool_Eligible": "radical_board",
      "Local_Pool_Score": -12.1416,
      "Tournament_Finalist_Flag": false,
      "Shortlist_Slot_Name": "",
      "Shortlist_Slot_Order": NaN,
      "Crowding_Block_Reason": "",
      "Selection_Passed_Over_For_Diversity": "",
      "Comparative_Edge_Score_10": 1.6,
      "Comparator_Floor_Score_10": 0.5,
      "Dominance_Score_10": 1.27,
      "Primary_Shortlist_Flag": false,
      "Primary_Override_Flag": false,
      "Shadow_Watchlist_Flag": false,
      "Shadow_Watchlist_Reason": "",
      "Shadow_Watchlist_Order": NaN,
      "In_Top_Shortlist": false,
      "Setup_Quality_Grade_10": 1.47,
      "Setup_Quality_Grade_100": 14.7,
      "Setup_Quality_Band": "E",
      "Prediction_Top_Strengths": "execution 10.0, asymmetry 8.4, utility 7.3",
      "Prediction_Main_Risks": "gate_pressure 16.8, kill_switch 8.9",
      "Prediction_Breakdown": "LONG continuation; strengths: execution 10.0, asymmetry 8.4, utility 7.3; risks: gate_pressure 16.8, kill_switch 8.9; admission: blocked / blocked_kill",
      "Prediction_Score_Version": "v5.5_prediction_quality_v2",
      "Prediction_Uses_Only_Contemporaneous_Inputs": true,
      "Prediction_Forbidden_Field_Leak": false,
      "Prediction_Input_Fingerprint": "af188e5253fa71e7",
      "Prediction_Integrity_Status": "clean_contemporaneous_only",
      "Prediction_Rank": 15
    },
    {
      "Snapshot_Date": "2026-05-20",
      "Prediction_Reference_Timestamp": "2026-05-20 09:53:33",
      "Market_Reference_Timestamp": "1970-01-01 00:00:00.000000698",
      "Instrument": "EURAUD",
      "status": "OK",
      "Universe_Layer": "Layer 2 — Relative-value crosses",
      "Cluster_Tags": "EUR relative-value cluster, HTF conflict, commodity bloc",
      "W1_Bias": "BEARISH",
      "D1_Bias": "BULLISH",
      "Price_Side_vs_D1_Range": "premium",
      "Alignment": "full conflict",
      "Liquidity_Condition": "external liquidity taken",
      "Sweep_Quality": "clean sweep only",
      "Liquidity_Side": "sell-side",
      "Liquidity_Tier": "major",
      "Liquidity_Reference_Type": "swing low",
      "Rejection_Quality": "moderate rejection",
      "Follow_Through": "limited follow-through",
      "Both_Sides_Taken_Recently": true,
      "Displacement_Quality": "moderate displacement",
      "MSS_BOS": "partial shift",
      "Array_Quality": "good",
      "Session_Quality": "acceptable but not ideal",
      "RS_RW_Alignment": "clear alignment",
      "SMT_Hint": "none",
      "Pivot_Regime": "daily: bearish below pivot | weekly: bullish above pivot",
      "Pivot_Zone_Fit": "price in buy zone",
      "Pivot_Confluence": "daily only",
      "Pivot_Conflict": "mild pivot conflict",
      "Pivot_Stretch": "not stretched",
      "Technical_Score_0_4": 2.3,
      "Legacy_Confidence_Score": 0.75,
      "Legacy_Confidence_Band": "medium",
      "Confidence_Score": 0.193,
      "Confidence_Band": "low",
      "Technical_Quality_Score_10": 4.55,
      "Execution_Realism_Score_10": 10.0,
      "Calibrated_Confidence_Score_10": 1.93,
      "Selection_Score": -10.1883,
      "Final_Rank_Score": -10.2443,
      "Data_Quality": "good",
      "Entry_Label": "B-tier reactive setup",
      "Preferred_Side": "LONG",
      "Best_Entry": 1.6293,
      "Structural_Entry": 1.6172,
      "Calibration_Entry": 1.6293,
      "Entry_Distance_ATR": 0.103,
      "SL": 1.628,
      "TP1": 1.631,
      "TP2": 1.6323,
      "Current_Price": 1.6299,
      "ATR_H1": 0.0017,
      "RR_TP1": 1.3077,
      "RR_TP2": 2.3077,
      "Execution_Line": "Buy-limit: 1.6293 | SL: 1.628 | TP1: 1.631 | TP2: 1.6323 | RR1: 1.3077 | RR2: 2.3077",
      "Execution_Source": "zone",
      "Setup_Archetype": "continuation",
      "Decision_Book": "A-book",
      "Live_Gate_Passed": false,
      "Calibration_Gate_Passed": true,
      "Gate_Passed": true,
      "Gate_Fail_Reasons": "full_conflict",
      "Decision_Setup_Quality": 1.35,
      "Decision_Execution_Quality": 3.8,
      "Decision_Portfolio_Fit": 0.0,
      "Decision_Rank_Score": -11.2278,
      "Base_Ranking_Score": -11.1678,
      "Overlap_Penalty": 0.0,
      "Ranking_Score": -10.2443,
      "Calibration_Soft_Candidate": false,
      "Calibration_Candidate_Bucket": "hard_pass",
      "Soft_Candidate": false,
      "Soft_Fail_Adjustment": 0.0,
      "Continuation_Subquality": 0.23,
      "Continuation_Elite_Eligible": true,
      "Context_Quality_Score_10": 4.5,
      "Trigger_Quality_Score_10": 6.0,
      "Conflict_Penalty_Score_10": 3.0,
      "Opportunity_Score_10": 2.8,
      "Balance_Score_10": 4.46,
      "Kill_Switch_Score_10": 4.2,
      "False_Positive_Risk_Score_10": 4.6,
      "Archetype_Tax_Score_10": 3.0,
      "Survivability_Score_10": 3.98,
      "Asymmetry_Score_10": 7.8,
      "Calibration_Utility_Score_10": 2.2,
      "Radical_Confidence_Score_10": 1.93,
      "Admission_Class": "blocked",
      "Override_Reason": "hard_reject",
      "Shortlist_Eligibility": "blocked",
      "Admission_Binding_Status": "blocked_hard",
      "Selection_Lane": "blocked_hard",
      "Leakage_Penalty_Score": 3.0,
      "Veto_Flag": false,
      "Veto_Reasons": "",
      "Selector_Profile": "v5.5_prediction_ready_selector",
      "Fragility_Reason": "",
      "Idea_Family": "continuation|no_theme|LONG|nonusd|strong",
      "Survivor_Score": 1.877,
      "Tournament_Pool": "radical_board",
      "Tournament_Pool_Display": "Radical board",
      "Tournament_Pool_Eligible": "radical_board",
      "Local_Pool_Score": -11.2278,
      "Tournament_Finalist_Flag": false,
      "Shortlist_Slot_Name": "",
      "Shortlist_Slot_Order": NaN,
      "Crowding_Block_Reason": "",
      "Selection_Passed_Over_For_Diversity": "",
      "Comparative_Edge_Score_10": 2.02,
      "Comparator_Floor_Score_10": 0.5,
      "Dominance_Score_10": 1.56,
      "Primary_Shortlist_Flag": false,
      "Primary_Override_Flag": false,
      "Shadow_Watchlist_Flag": false,
      "Shadow_Watchlist_Reason": "",
      "Shadow_Watchlist_Order": NaN,
      "In_Top_Shortlist": false,
      "Setup_Quality_Grade_10": 1.4,
      "Setup_Quality_Grade_100": 14.0,
      "Setup_Quality_Band": "E",
      "Prediction_Top_Strengths": "execution 10.0, asymmetry 7.8, trigger 6.0",
      "Prediction_Main_Risks": "gate_pressure 17.7, false_positive_risk 4.6",
      "Prediction_Breakdown": "LONG continuation; strengths: execution 10.0, asymmetry 7.8, trigger 6.0; risks: gate_pressure 17.7, false_positive_risk 4.6; admission: blocked / blocked_hard",
      "Prediction_Score_Version": "v5.5_prediction_quality_v2",
      "Prediction_Uses_Only_Contemporaneous_Inputs": true,
      "Prediction_Forbidden_Field_Leak": false,
      "Prediction_Input_Fingerprint": "07cd909239277120",
      "Prediction_Integrity_Status": "clean_contemporaneous_only",
      "Prediction_Rank": 16
    }
  ]
}